Workbook
Name CS: CS!$A$2:$K$38
Name CS_test: #REF!
Name Impact: 'S00 Impact'!$A$1:$H$40
Name ImpactAir: #REF!

Sheet Rail
A1: All prices are i 2025 price level year | C1: AP train persons | D1: AP train freight | E1: GW train person | F1: GW train freight | G1: Accidents - train passengers | H1: Noise - train passengers | I1: Accidents - train freight | J1: Noise - train freight
B2: Country | C2: € cent/pkm | D2: € cent/tkm | E2: € cent/pkm | F2: € cent/tkm | G2: €ct/pkm | H2: €ct/pkm | I2: €ct/tkm | J2: €ct/tkm
A3: AL | B3: Albania | C3: 0.021 | D3: 0.019 | E3: 0.152 | F3: 0.087 | G3: 0.052 | H3: 0.145 | I3: 0.027 | J3: 0.039
A4: AT | B4: Austria | C4: 0.032 | D4: 0.011 | E4: 0.152 | F4: 0.087 | G4: 0.112 | H4: 0.114 | I4: 0.031 | J4: 0.141
A5: BA | B5: Belarus | C5: 0.078 | D5: 0.045 | E5: 0.152 | F5: 0.087 | G5: 0.074 | H5: 0.134 | I5: 0.027 | J5: 0.038
A6: BE | B6: Belgium | C6: 0.366 | D6: 0.211 | E6: 0.152 | F6: 0.087 | G6: 0.071 | H6: 0.04 | I6: 0.025 | J6: 0.066
A7: BG | B7: Bulgaria | C7: 0.047 | D7: 0.027 | E7: 0.152 | F7: 0.087 | G7: 0.085 | H7: 0.215 | I7: 0.027 | J7: 0.03
A8: BY | B8: Bonsnia & Herzegovina | C8: 0.074 | D8: 0.044 | E8: 0.152 | F8: 0.087 | G8: 0.071 | H8: 0.031 | I8: 0.027 | J8: 0.034
A9: CH | B9: Switzerland | C9: 0.04 | D9: 0.023 | E9: 0.152 | F9: 0.087 | G9: 0.138 | H9: 0.22 | I9: 0.014 | J9: 0.059
A10: CZ | B10: Czech Republic | C10: 0.081 | D10: 0.043 | E10: 0.152 | F10: 0.087 | G10: 0.055 | H10: 0.1 | I10: 0.028 | J10: 0.128
A11: DE | B11: Germany | C11: 0.035 | D11: 0.02 | E11: 0.152 | F11: 0.087 | G11: 0.085 | H11: 0.143 | I11: 0.027 | J11: 0.038
A12: DK | B12: Denmark | C12: 0.046 | D12: 0.031 | E12: 0.152 | F12: 0.087 | G12: 0.057 | H12: 0.053 | I12: 0.031 | J12: 0.128
A13: EE | B13: Estonia | C13: 0.318 | D13: 0.183 | E13: 0.152 | F13: 0.087 | G13: 0.071 | H13: 0.038 | I13: 0.034 | J13: 0.198
A14: ES | B14: Spain | C14: 0.033 | D14: 0.019 | E14: 0.152 | F14: 0.087 | G14: 0.064 | H14: 0.163 | I14: 0.027 | J14: 0.029
... A41: YU | B41: Yugoslavia | C41: 0.042 | D41: 0.024 | E41: 0.152 | F41: 0.087 | G41: 0.071 | H41: 0.038 | I41: 0.027 | J41: 0.049

Sheet Full overview
A1: Scenario | C1: Type | D1: Investment costs (M€) | E1: Change in maintenance costs (M€/year) | G1: Opening year | H1: Construction period (year)
A2: 1 | B2: Munich - Verona | C2: Railway | D2: 14000 | E2: 7.4 | G2: 2030 | H2: 10
A3: 2 | B3: Naples - Messina | C3: Railway | D3: 6770 | E3: 4.7 | F3: * | G3: 2026 | H3: 7
A4: 3 | B4: Coimbra - Madrid (incl. upgrades) | C4: Railway + road | D4: 3870 | E4: 9.9 | G4: 2028 | H4: 7
A5: 4 | B5: North-west Spain | C5: Railway passenger | D5: 870 | E5: 9.1 | G5: 2026 | H5: 6
A6: 5 | B6: Bordeaux - San Sebastian (incl. upgrades) | C6: Railway + road | D6: 5570 | E6: 14.2 | G6: 2027 | H6: 7
A7: 6 | B7: Montpellier - Perpignan (incl. upgrades) | C7: Railway + road | D7: 7670 | E7: 8.2 | G7: 2029 | H7: 7
A8: 7 | B8: Saarbrucken - Morhange (incl. upgrades) | C8: Railway | D8: 930 | E8: 2.8 | G8: 2026 | H8: 6
A9: 8 | B9: Chambery - Torino | C9: Railway | D9: 6020 | E9: 1.7 | G9: 2027 | H9: 7
A10: 9 | B10: Milan - Hungary-Ukrane + Nove Zamky - Budapest | C10: Railway | D10: 23380 | E10: 7.6 | G10: 2030 | H10: 10
A11: 10 | B11: Hungary - Romania + Bulgary - Greece | C11: Railway + road | D11: 9870 | E11: 2.4 | G11: 2028 | H11: 8
A12: 11 | B12: Sibiu - Pitesti + Deva - Brasov | C12: Railway + road | D12: 4740 | E12: 1.8 | G12: 2028 | H12: 7
A13: 12 | B13: South of Finland | C13: Railway + road | D13: 2740 | E13: 1.7 | G13: 2027 | H13: 6
A14: 13 | B14: Nyköping - Södertälje | C14: Railway | D14: 2300 | E14: 0 | G14: 2026 | H14: 6
A15: 14 | B15: Stuttgart - Linz - Prague | C15: Railway + road | D15: 6240 | E15: 0.2 | G15: 2027 | H15: 7
... A37: 36 | B37: Belgian-French border - Compiegne | C37: Waterway | D37: 1250 | E37: 2.5 | G37: 2028 | H37: 6
A40: * | D40: Includes the bridge over the strait of Messina (4685 M€)

Sheet CS
A1: Consumers surplus for year | E1: 2035
A2: scenario | B2: Opening year | C2: CS_passenger | D2: CS_CarD | E2: CS_CarP | F2: CS_Air | G2: CS_Rail | H2: CS_freight | I2: CS_freight_Truck | J2: CS_freight_Rail | K2: CS_freight_IWW | M2: CS is calculated for 2035 and measured in 2025 prices
A3: 01 | B3: 2030 | C3: =SUM(D3:G3) -> 25814639 | D3: 3292020.1 | E3: 779110.84 | F3: 523558.63 | G3: 21219949 | H3: =SUM(I3:K3) -> 43975545 | I3: 41181339 | J3: 2794206.5 | K3: 0
A4: 02 | B4: 2026 | C4: =SUM(D4:G4) -> 35989224 | D4: 874796.51 | E4: 9256946.2 | F4: 474148.16 | G4: 25383333 | H4: =SUM(I4:K4) -> 346361.51 | I4: 0 | J4: 346361.51 | K4: 0 | M4: Conforms to the rule-of-a-half approximation
A5: 03 | B5: 2028 | C5: =SUM(D5:G5) -> 28491754 | D5: 25427347 | E5: -4651241.1 | F5: 1534941.8 | G5: 6180706.3 | H5: =SUM(I5:K5) -> 64500020 | I5: 64507209 | J5: -7189.5787 | K5: 0
A6: 04 | B6: 2026 | C6: =SUM(D6:G6) -> 12321237 | D6: 18800697 | E6: -10653150 | F6: 830984.59 | G6: 3342704.3 | H6: 12232479 | I6: 12201238 | J6: 31240.881 | K6: 0
A7: 05 | B7: 2027 | C7: =SUM(D7:G7) -> 92462354 | D7: 41582639 | E7: 9523842.4 | F7: 2780312.6 | G7: 38575561 | H7: =SUM(I7:K7) -> 12146614 | I7: 11835689 | J7: 310925.05 | K7: 0
A8: 06 | B8: 2029 | C8: =SUM(D8:G8) -> 3.8088879e+08 | D8: 2.5156145e+08 | E8: 1.0212076e+08 | F8: 1673009.3 | G8: 25533575 | H8: =SUM(I8:K8) -> 16361880 | I8: 13158877 | J8: 3203002.7 | K8: 0
A9: 07 | B9: 2026 | C9: =SUM(D9:G9) -> 16376222 | D9: -8352863.8 | E9: 8436954 | F9: 2642290.2 | G9: 13649841 | H9: =SUM(I9:K9) -> 2041799 | I9: 0 | J9: 2041799 | K9: 0
A10: 08 | B10: 2027 | C10: =SUM(D10:G10) -> 32671112 | D10: 11078106 | E10: 5293693.5 | F10: 1487546 | G10: 14811766 | H10: =SUM(I10:K10) -> 342465.87 | I10: 0 | J10: 342465.87 | K10: 0
A11: 09 | B11: 2030 | C11: =SUM(D11:G11) -> 8.067075e+08 | D11: 2.2953128e+08 | E11: 1.0780196e+08 | F11: 9569090 | G11: 4.5980517e+08 | H11: =SUM(I11:K11) -> 1.6244622e+08 | I11: 0 | J11: 1.6244622e+08 | K11: 0
A12: 10 | B12: 2028 | C12: =SUM(D12:G12) -> 2.8634481e+08 | D12: 1.3885025e+08 | E12: 48792286 | F12: 3049162.9 | G12: 95653114 | H12: 1.8307176e+08 | I12: 65226931 | J12: 1.1784482e+08 | K12: 0
A13: 11 | B13: 2028 | C13: =SUM(D13:G13) -> 1.4024007e+08 | D13: 98022962 | E13: 22920118 | F13: -376642.74 | G13: 19673628 | H13: =SUM(I13:K13) -> 1.4563944e+08 | I13: 91542939 | J13: 54096505 | K13: 0
A14: 12 | B14: 2027 | C14: =SUM(D14:G14) -> 36250561 | D14: 5327724.8 | E14: 10082210 | F14: 361984.49 | G14: 20478641 | H14: =SUM(I14:K14) -> 62457048 | I14: 35941454 | J14: 26515595 | K14: 0
A15: 13 | B15: 2026 | C15: =SUM(D15:G15) -> 27000735 | D15: 14593105 | E15: -1147100.2 | F15: 1137161.2 | G15: 12417569 | H15: =SUM(I15:K15) -> 2794206.5 | I15: 0 | J15: 2794206.5 | K15: 0
A16: 14 | B16: 2027 | C16: =SUM(D16:G16) -> 57227570 | D16: -2400919.9 | E16: -11566817 | F16: 7157099.4 | G16: 64038207 | H16: =SUM(I16:K16) -> 36832502 | I16: -5395036.1 | J16: 42227539 | K16: 0
A17: 15 | B17: 2027 | C17: =SUM(D17:G17) -> 1.1125133e+08 | D17: 36128921 | E17: 3885548.2 | F17: 10084067 | G17: 61152797 | H17: =SUM(I17:K17) -> 2.608117e+08 | I17: 99676380 | J17: 1.6113532e+08 | K17: 0
A18: 16 | B18: 2028 | C18: =SUM(D18:G18) -> 31295837 | D18: 17677533 | E18: 7315689.3 | F18: 1086287.5 | G18: 5216327.6 | H18: =SUM(I18:K18) -> 416020.15 | I18: 0 | J18: 416020.15 | K18: 0
A19: 17 | B19: 2027 | C19: =SUM(D19:G19) -> 18260970 | D19: 11938868 | E19: 3977513.7 | F19: 1545219.7 | G19: 799369.18 | H19: =SUM(I19:K19) -> 1387938.4 | I19: 0 | J19: 1387938.4 | K19: 0
A20: 18 | B20: 2029 | C20: =SUM(D20:G20) -> 1.0090258e+08 | D20: -2604051.6 | E20: 332222.07 | F20: 1076177.2 | G20: 1.0209824e+08 | H20: =SUM(I20:K20) -> 49153274 | I20: 41883980 | J20: 7269294.2 | K20: 0
A21: 19 | B21: 2026 | C21: =SUM(D21:G21) -> 38326682 | D21: 15194980 | E21: -9255131.2 | F21: 860433.36 | G21: 31526399 | H21: =SUM(I21:K21) -> 15557414 | I21: 3618021.3 | J21: 11939393 | K21: 0
A22: 20 | B22: 2027 | C22: =SUM(D22:G22) -> 67568116 | D22: 38349040 | E22: 3310327.9 | F22: 1475435.1 | G22: 24433313 | H22: =SUM(I22:K22) -> 26603746 | I22: 22160113 | J22: 4443632.7 | K22: 0
A23: 21 | B23: 2027 | C23: =SUM(D23:G23) -> 1.5641985e+08 | D23: 55571260 | E23: 29590106 | F23: 1230879.8 | G23: 70027607 | H23: =SUM(I23:K23) -> 3.4320803e+08 | I23: 2.1804485e+08 | J23: 1.2516318e+08 | K23: 0
A24: 22 | B24: 2028 | C24: =SUM(D24:G24) -> 36230828 | D24: 22710529 | E24: 6437491.7 | F24: 1656655.4 | G24: 5426152.3 | H24: =SUM(I24:K24) -> -26444396 | I24: -26525365 | J24: 80968.644 | K24: 0
... A38: 36 | B38: 2028 | C38: =SUM(D38:G38) -> 13987888 | D38: 1804712.7 | E38: 9426554.1 | F38: 1749114.6 | G38: 1007506.2 | H38: =SUM(I38:K38) -> 18428154 | I38: 0 | J38: 0 | K38: 18428154

Sheet Road
A1: All prices are i 2025 price level year | D1: Ap_car_petrol | E1: Ap_car_diesel | F1: Gw_car_petrol | G1: GW car diesel | H1: AP hgv diesel | I1: GW hgv diesel | J1: Accidents car | K1: Noise car | L1: Accidents - HGV | M1: Noise - HGV
B2: Country | D2: €ct/vkm | E2: €ct/vkm | F2: €ct/vkm | G2: €ct/vkm | H2: €ct/vkm | I2: €ct/vkm | J2: €ct/vkm | K2: €ct/vkm | L2: €ct/vkm | M2: €ct/vkm
A3: AL | B3: Albania | D3: 0.105 | E3: 0.297 | F3: 0.959 | G3: 0.956 | H3: 2.269 | I3: 4.453 | J3: 0.413 | K3: 0.34 | L3: 1.313 | M3: 2.949
A4: AT | B4: Austria | D4: 0.165 | E4: 0.649 | F4: 0.96 | G4: 0.955 | H4: 5.185 | I4: 4.453 | J4: 0.5 | K4: 0.713 | L4: 5.024 | M4: 4.707
A5: BA | B5: Belarus | D5: 0.09 | E5: 0.256 | F5: 0.959 | G5: 0.956 | H5: 1.95 | I5: 4.453 | J5: 0.355 | K5: 0.293 | L5: 1.128 | M5: 2.534
A6: BE | B6: Belgium | D6: 0.161 | E6: 0.462 | F6: 0.96 | G6: 0.955 | H6: 3.467 | I6: 4.453 | J6: 0.573 | K6: 0.658 | L6: 9.729 | M6: 4.345
A7: BG | B7: Bulgaria | D7: 0.08 | E7: 0.227 | F7: 0.959 | G7: 0.956 | H7: 1.735 | I7: 4.453 | J7: 0.315 | K7: 0.26 | L7: 1.004 | M7: 2.255
A8: BY | B8: Bonsnia & Herzegovina | D8: 0.101 | E8: 0.285 | F8: 0.959 | G8: 0.956 | H8: 2.177 | I8: 4.453 | J8: 0.396 | K8: 0.327 | L8: 1.259 | M8: 2.829
A9: CH | B9: Switzerland | D9: 0.309 | E9: 0.873 | F9: 0.959 | G9: 0.956 | H9: 6.662 | I9: 4.453 | J9: 1.211 | K9: 1 | L9: 3.855 | M9: 8.658
A10: CZ | B10: Czech Republic | D10: 0.145 | E10: 0.414 | F10: 0.96 | G10: 0.955 | H10: 3.162 | I10: 4.453 | J10: 0.222 | K10: 0.494 | L10: 1.947 | M10: 4.841
A11: DE | B11: Germany | D11: 0.148 | E11: 0.612 | F11: 0.96 | G11: 0.955 | H11: 4.924 | I11: 4.453 | J11: 0.38 | K11: 0.584 | L11: 3.853 | M11: 3.856
A12: DK | B12: Denmark | D12: 0.138 | E12: 0.365 | F12: 0.96 | G12: 0.955 | H12: 2.762 | I12: 4.453 | J12: 0.39 | K12: 0.858 | L12: 3.583 | M12: 5.663
A13: EE | B13: Estonia | D13: 0.207 | E13: 0.589 | F13: 0.96 | G13: 0.955 | H13: 4.5 | I13: 4.453 | J13: 0.225 | K13: 0.703 | L13: 2.771 | M13: 6.888
A14: ES | B14: Spain | D14: 0.17 | E14: 0.341 | F14: 0.96 | G14: 0.955 | H14: 2.433 | I14: 4.453 | J14: 0.451 | K14: 0.574 | L14: 0.496 | M14: 3.789
... A41: YU | B41: Yugoslavia | D41: 0.09 | E41: 0.256 | F41: 0.959 | G41: 0.956 | H41: 1.95 | I41: 4.453 | J41: 0.355 | K41: 0.293 | L41: 1.128 | M41: 2.534

Sheet Air
A1: All prices are i 2025 price level year | C1: Air pollution - air | D1: Global warming - air
B2: Country | C2: €ct/pkm | D2: €ct/pkm
B3: All countries | C3: 0.688 | D3: 0.499

Sheet IWW
A1: All prices are i 2025 price level year | C1: Air pollution - IWW | D1: Global warming IWW
B2: Country | C2: €ct/tkm | D2: €ct/tkm
A3: AL | B3: Albania | C3: 1.876 | D3: 0.272
A4: AT | B4: Austria | C4: 2.521 | D4: 0.272
A5: BA | B5: Belarus | C5: 1.876 | D5: 0.272
A6: BE | B6: Belgium | C6: 2.236 | D6: 0.272
A7: BG | B7: Bulgaria | C7: 0.47 | D7: 0.272
A8: BY | B8: Bonsnia & Herzegovina | C8: 1.876 | D8: 0.272
A9: CH | B9: Switzerland | C9: 1.876 | D9: 0.272
A10: CZ | B10: Czech Republic | C10: 1.876 | D10: 0.272
A11: DE | B11: Germany | C11: 2.429 | D11: 0.272
A12: DK | B12: Denmark | C12: 2.684 | D12: 0.272
A13: EE | B13: Estonia | C13: 1.876 | D13: 0.272
A14: ES | B14: Spain | C14: 1.876 | D14: 0.272
... A41: YU | B41: Yugoslavia | C41: 1.272 | D41: 0.272

Sheet S00 Impact
A1: Scenario | B1: CountryCode | C1: vkm_petrol_Carpassenger | D1: vkm_diesel_Carpassenger | E1: vkm_hgv_Freight | F1: Total_IWW_TonKM | G1: PersonKM_RailPassenger | H1: TonKM_RailFreight | J1: _TYPE_ | K1: _FREQ_ | L1: personkm_Air
A2: 0 | B2: AL | C2: 2.1980666e+09 | D2: 5.4375694e+08 | E2: 7.772212e+08 | G2: 1.2697104e+08 | H2: 5.9557851e+08 | J2: 0 | K2: 3153 | L2: 8.392938e+11
A3: 0 | B3: AT | C3: 4.3085971e+10 | D3: 2.7049782e+10 | E3: 6.8853187e+09 | F3: 7.1064248e+09 | G3: 1.5860344e+10 | H3: 2.4759775e+10
A4: 0 | B4: BA | C4: 5.0277972e+09 | D4: 1.2335822e+09 | E4: 8.434936e+08 | F4: 7.3871775e+08 | G4: 5.9999837e+08 | H4: 1.2084542e+09
A5: 0 | B5: BE | C5: 4.2897807e+10 | D5: 3.255379e+10 | E5: 8.4078117e+09 | F5: 9.5886557e+09 | G5: 1.4152909e+10 | H5: 9.8150371e+09
A6: 0 | B6: BG | C6: 2.7971419e+10 | D6: 6.8351173e+09 | E6: 3.8406982e+09 | F6: 2.1006345e+09 | G6: 1.700996e+10 | H6: 2.3009823e+10
A7: 0 | B7: BY | C7: 1.9233009e+10 | D7: 4.6363897e+09 | E7: 1.043522e+10 | G7: 7.7116123e+09 | H7: 2.6951466e+10
A8: 0 | B8: CH | C8: 3.9946537e+10 | D8: 5.7129371e+09 | E8: 3.6435066e+09 | F8: 38941402 | G8: 1.1678971e+10 | H8: 1.1557304e+10
A9: 0 | B9: CZ | C9: 3.1730503e+10 | D9: 6.8905019e+09 | E9: 8.547688e+09 | F9: 45302166 | G9: 9.3607733e+09 | H9: 3.5367292e+10
A10: 0 | B10: DE | C10: 3.8000961e+11 | D10: 8.867191e+10 | E10: 4.652768e+10 | F10: 7.5684748e+10 | G10: 1.1489967e+11 | H10: 1.1011037e+11
A11: 0 | B11: DK | C11: 3.7244767e+10 | D11: 3.8658467e+09 | E11: 7.2427306e+09 | G11: 6.3847484e+09 | H11: 3.3950105e+09
A12: 0 | B12: EE | C12: 3.3566489e+09 | D12: 6.0964292e+08 | E12: 1.8199685e+09 | G12: 2.9024163e+08 | H12: 3.0995576e+10
A13: 0 | B13: ES | C13: 1.7610576e+11 | D13: 9.4465086e+10 | E13: 4.8189133e+10 | G13: 2.9510205e+10 | H13: 2.4316358e+10
A14: 0 | B14: FI | C14: 2.9660486e+10 | D14: 4.3296043e+09 | E14: 5.6539688e+09 | G14: 7.6550922e+09 | H14: 2.2105141e+10
A15: 0 | B15: FR | C15: 2.4535292e+11 | D15: 1.677295e+11 | E15: 4.404751e+10 | F15: 1.2023247e+10 | G15: 9.5137533e+10 | H15: 5.5777392e+10
A16: 0 | B16: GR | C16: 2.7384386e+10 | D16: 6.7792426e+09 | E16: 6.2845605e+09 | G16: 2.9315963e+09 | H16: 1.4283851e+09
A17: 0 | B17: HR | C17: 2.2445419e+10 | D17: 5.5769196e+09 | E17: 2.6703844e+09 | F17: 3.1189513e+08 | G17: 9.1561312e+09 | H17: 7.5068775e+09
A18: 0 | B18: HU | C18: 2.9563781e+10 | D18: 6.0743789e+09 | E18: 5.3968855e+09 | F18: 1.1182449e+10 | G18: 1.5426045e+10 | H18: 2.3852046e+10
A19: 0 | B19: IE | C19: 2.7587363e+10 | D19: 4.7737827e+09 | E19: 4.8707765e+09 | G19: 1.9392754e+09 | H19: 6.5537916e+08
A20: 0 | B20: IT | C20: 2.1159644e+11 | D20: 5.5783953e+10 | E20: 3.6794525e+10 | G20: 5.1018835e+10 | H20: 3.5835679e+10
A21: 0 | B21: LI | C21: 79960872 | D21: 23695145 | E21: 17673163 | G21: 13065987 | H21: 27023259
A22: 0 | B22: LT | C22: 8.5413707e+09 | D22: 2.0352728e+09 | E22: 4.6477433e+09 | F22: 1945882.9 | G22: 1.3133662e+10 | H22: 3.682413e+10
A23: 0 | B23: LU | C23: 5.5509197e+09 | D23: 2.6305587e+09 | E23: 9.0345769e+08 | G23: 1.5839722e+08 | H23: 5.7487031e+08
A24: 0 | B24: LV | C24: 7.2294819e+09 | D24: 1.438647e+09 | E24: 2.5990066e+09 | F24: 3057704.3 | G24: 8.0563569e+09 | H24: 5.0294596e+10
A25: 0 | B25: MD | C25: 5.605123e+09 | D25: 1.3833211e+09 | E25: 1.6182919e+09 | G25: 1.4122504e+09 | H25: 3.4629097e+09
A26: 0 | B26: ME | C26: 1.5157725e+09 | D26: 3.7488258e+08 | E26: 1.8944283e+08 | G26: 1.3515923e+08 | H26: 1.8993997e+09
A27: 0 | B27: MK | C27: 4.7996908e+09 | D27: 1.1888017e+09 | E27: 1.3549474e+09 | G27: 7.3383016e+08 | H27: 4.1491795e+08
A28: 0 | B28: NL | C28: 9.5300016e+10 | D28: 1.9265209e+10 | E28: 1.0286574e+10 | F28: 3.9737085e+10 | G28: 1.2558823e+10 | H28: 6.5718528e+09
A29: 0 | B29: NO | C29: 4.0194211e+10 | D29: 9.4038715e+09 | E29: 3.8603025e+09 | G29: 4.5280239e+09 | H29: 4.7564625e+09
A30: 0 | B30: PL | C30: 9.6095814e+10 | D30: 1.8900619e+10 | E30: 3.0156034e+10 | F30: 8.8307032e+08 | G30: 5.3870262e+10 | H30: 1.3167324e+11
A31: 0 | B31: PT | C31: 3.7367256e+10 | D31: 9.7777466e+09 | E31: 6.7178966e+09 | G31: 4.7176368e+09 | H31: 4.6541758e+09
A32: 0 | B32: RO | C32: 3.8572847e+10 | D32: 9.4241244e+09 | E32: 1.3976914e+10 | F32: 2.1604111e+10 | G32: 1.1339484e+10 | H32: 5.7844965e+10
A33: 0 | B33: RU | C33: 1.5810768e+11 | D33: 3.8793216e+10 | E33: 9.0632809e+10 | G33: 1.0534824e+11 | H33: 2.3285279e+11
A34: 0 | B34: SE | C34: 5.7554853e+10 | D34: 4.4883265e+09 | E34: 8.4311722e+09 | G34: 1.7913194e+10 | H34: 3.5584287e+10
A35: 0 | B35: SI | C35: 1.1790025e+10 | D35: 3.0859471e+09 | E35: 2.3349838e+09 | G35: 5.7381661e+09 | H35: 9.9885562e+09
A36: 0 | B36: SK | C36: 1.2780131e+10 | D36: 3.096644e+09 | E36: 4.0691924e+09 | F36: 7.0620128e+08 | G36: 2.5205881e+09 | H36: 2.3498613e+10
A37: 0 | B37: TR | C37: 1.1410953e+11 | D37: 2.7980099e+10 | E37: 1.1229698e+10 | G37: 5.0477639e+10 | H37: 1.3378092e+10
A38: 0 | B38: UA | C38: 7.4014817e+10 | D38: 1.8038036e+10 | E38: 2.2515409e+10 | G38: 3.5592575e+10 | H38: 7.7262588e+10
A39: 0 | B39: UK | C39: 3.3050775e+11 | D39: 7.5070057e+10 | E39: 2.6289449e+10 | F39: 3.2638265e+08 | G39: 4.8531517e+10 | H39: 3.7357669e+10
A40: 0 | B40: YU | C40: 2.0537374e+10 | D40: 5.0188134e+09 | E40: 2.1440241e+09 | F40: 1.3212523e+10 | G40: 2.0572184e+10 | H40: 9.3398794e+09

Sheet S01 Impact
A1: Difference from Baseline | O1: Type | P1: Air Pollution | Q1: Air Pollution | R1: Air Pollution | S1: Air Pollution | T1: Air Pollution | U1: Air Pollution | V1: Air Pollution | W1: Global Warming | X1: Global Warming | Y1: Global Warming | Z1: Global Warming | AA1: Global Warming | AB1: Global Warming | AC1: Global Warming | AD1: Accidents | AE1: Accidents | AF1: Accidents | AG1: Accidents | AH1: Noise | AI1: Noise | AJ1: Noise | AK1: Noise
A2: Scenario | B2: CountryCode | C2: vkm_petrol_Carpassenger | D2: vkm_diesel_Carpassenger | E2: vkm_hgv_Freight | F2: Total_IWW_TonKM | G2: PersonKM_RailPassenger | H2: TonKM_RailFreight | J2: _TYPE_ | K2: _FREQ_ | L2: personkm_Air | N2: Scenario | O2: CountryCode | P2: Car Petrol (€) | Q2: Car Diesel (€) | R2: HGV Diesel (€) | S2: Train Person (€) | T2: Train Freight (€) | U2: IWW (€) | V2: Air (€) | W2: Car Petrol (€) | X2: Car Diesel (€) | Y2: HGV Diesel (€) | Z2: Train Person (€) | AA2: Train Freight (€) | AB2: IWW (€) | AC2: Air (€) | AD2: Car (€) | AE2: HGV (€) | AF2: Train Person (€) | AG2: Train Freight (€) | AH2: Car (€) | AI2: HGV (€) | AJ2: Train Person (€) | AK2: Train Freight (€)
A3: =A45 -> 1 | B3: =IF(B45='S00 Impact'!B2,B45,0) -> AL | C3: =-(C45-'S00 Impact'!C2) -> 3436050.7 | D3: =-(D45-'S00 Impact'!D2) -> 852927.49 | E3: =-(E45-'S00 Impact'!E2) -> -146086.33 | F3: =-(F45-'S00 Impact'!F2) -> 0 | G3: =-(G45-'S00 Impact'!G2) -> -2224575.2 | H3: =-(H45-'S00 Impact'!H2) -> -53539.545 | J3: =J45 -> 0 | K3: =K45 -> 3153 | L3: =-(L45-'S00 Impact'!L2) -> 1.8203724e+09 | N3: =A3 -> 1 | O3: =B3 -> AL | P3: =C3*Road!D3/100 -> 3607.8533 | Q3: =D3*Road!E3/100 -> 2533.1946 | R3: =E3*Road!H3/100 -> -3314.6989 | S3: =G3*Rail!C3/100 -> -467.16078 | T3: =H3*Rail!D3/100 -> -10.172514 | U3: =F3*IWW!C3/100 -> 0 | W3: =C3*Road!F3/100 -> 32951.726 | X3: =D3*Road!G3/100 -> 8153.9868 | Y3: =E3*Road!I3/100 -> -6505.2244 | Z3: =G3*Rail!E3/100 -> -3381.3542 | AA3: =H3*Rail!F3/100 -> -46.579404 | AB3: =F3*IWW!D3/100 -> 0 | AD3: =(C3+D3)*Road!J3/100 -> 17713.48 | AE3: =E3*Road!L3/100 -> -1918.1136 | AF3: =G3*Rail!G3/100 -> -1156.7791 | AG3: =H3*Rail!I3/100 -> -14.455677 | AH3: =(C3+D3)*Road!K3/100 -> 14582.526 | AI3: =E3*Road!M3/100 -> -4308.086 | AJ3: =G3*Rail!H3/100 -> -3225.634 | AK3: =H3*Rail!J3/100 -> -20.880423
A4: =A46 -> 1 | B4: =IF(B46='S00 Impact'!B3,B46,0) -> AT | C4: =-(C46-'S00 Impact'!C3) -> 24900595 | D4: =-(D46-'S00 Impact'!D3) -> 8721566.5 | E4: =-(E46-'S00 Impact'!E3) -> -16192406 | F4: =-(F46-'S00 Impact'!F3) -> -5011676.6 | G4: =-(G46-'S00 Impact'!G3) -> -1.2845524e+08 | H4: =-(H46-'S00 Impact'!H3) -> -86278391 | N4: =A4 -> 1 | O4: =B4 -> AT | P4: =C4*Road!D4/100 -> 41085.982 | Q4: =D4*Road!E4/100 -> 56602.967 | R4: =E4*Road!H4/100 -> -839576.23 | S4: =G4*Rail!C4/100 -> -41105.676 | T4: =H4*Rail!D4/100 -> -9490.623 | U4: =F4*IWW!C4/100 -> -126344.37 | W4: =C4*Road!F4/100 -> 239045.71 | X4: =D4*Road!G4/100 -> 83290.96 | Y4: =E4*Road!I4/100 -> -721047.82 | Z4: =G4*Rail!E4/100 -> -195251.96 | AA4: =H4*Rail!F4/100 -> -75062.2 | AB4: =F4*IWW!D4/100 -> -13631.76 | AD4: =(C4+D4)*Road!J4/100 -> 168110.81 | AE4: =E4*Road!L4/100 -> -813506.45 | AF4: =G4*Rail!G4/100 -> -143869.87 | AG4: =H4*Rail!I4/100 -> -26746.301 | AH4: =(C4+D4)*Road!K4/100 -> 239726.01 | AI4: =E4*Road!M4/100 -> -762176.53 | AJ4: =G4*Rail!H4/100 -> -146438.97 | AK4: =H4*Rail!J4/100 -> -121652.53
A5: =A47 -> 1 | B5: =IF(B47='S00 Impact'!B4,B47,0) -> BA | C5: =-(C47-'S00 Impact'!C4) -> 9108102.1 | D5: =-(D47-'S00 Impact'!D4) -> 2118000.4 | E5: =-(E47-'S00 Impact'!E4) -> -460906.8 | F5: =-(F47-'S00 Impact'!F4) -> -4170066.3 | G5: =-(G47-'S00 Impact'!G4) -> 3835422.8 | H5: =-(H47-'S00 Impact'!H4) -> -1636312.3 | N5: =A5 -> 1 | O5: =B5 -> BA | P5: =C5*Road!D5/100 -> 8197.2919 | Q5: =D5*Road!E5/100 -> 5422.081 | R5: =E5*Road!H5/100 -> -8987.6825 | S5: =G5*Rail!C5/100 -> 2991.6298 | T5: =H5*Rail!D5/100 -> -736.34054 | U5: =F5*IWW!C5/100 -> -78230.444 | W5: =C5*Road!F5/100 -> 87346.7 | X5: =D5*Road!G5/100 -> 20248.084 | Y5: =E5*Road!I5/100 -> -20524.18 | Z5: =G5*Rail!E5/100 -> 5829.8427 | AA5: =H5*Rail!F5/100 -> -1423.5917 | AB5: =F5*IWW!D5/100 -> -11342.58 | AD5: =(C5+D5)*Road!J5/100 -> 39852.664 | AE5: =E5*Road!L5/100 -> -5199.0287 | AF5: =G5*Rail!G5/100 -> 2838.2129 | AG5: =H5*Rail!I5/100 -> -441.80433 | AH5: =(C5+D5)*Road!K5/100 -> 32892.48 | AI5: =E5*Road!M5/100 -> -11679.378 | AJ5: =G5*Rail!H5/100 -> 5139.4666 | AK5: =H5*Rail!J5/100 -> -621.79868
A6: =A48 -> 1 | B6: =IF(B48='S00 Impact'!B5,B48,0) -> BE | C6: =-(C48-'S00 Impact'!C5) -> 7574832 | D6: =-(D48-'S00 Impact'!D5) -> -417678.53 | E6: =-(E48-'S00 Impact'!E5) -> -5325689.8 | F6: =-(F48-'S00 Impact'!F5) -> 2932680.9 | G6: =-(G48-'S00 Impact'!G5) -> -41281184 | H6: =-(H48-'S00 Impact'!H5) -> 3236667.1 | N6: =A6 -> 1 | O6: =B6 -> BE | P6: =C6*Road!D6/100 -> 12195.48 | Q6: =D6*Road!E6/100 -> -1929.6748 | R6: =E6*Road!H6/100 -> -184641.67 | S6: =G6*Rail!C6/100 -> -151089.13 | T6: =H6*Rail!D6/100 -> 6829.3675 | U6: =F6*IWW!C6/100 -> 65574.746 | W6: =C6*Road!F6/100 -> 72718.387 | X6: =D6*Road!G6/100 -> -3988.8299 | Y6: =E6*Road!I6/100 -> -237152.97 | Z6: =G6*Rail!E6/100 -> -62747.4 | AA6: =H6*Rail!F6/100 -> 2815.9004 | AB6: =F6*IWW!D6/100 -> 7976.8921 | AD6: =(C6+D6)*Road!J6/100 -> 41010.489 | AE6: =E6*Road!L6/100 -> -518136.36 | AF6: =G6*Rail!G6/100 -> -29309.641 | AG6: =H6*Rail!I6/100 -> 809.16677 | AH6: =(C6+D6)*Road!K6/100 -> 47094.07 | AI6: =E6*Road!M6/100 -> -231401.22 | AJ6: =G6*Rail!H6/100 -> -16512.474 | AK6: =H6*Rail!J6/100 -> 2136.2003
A7: =A49 -> 1 | B7: =IF(B49='S00 Impact'!B6,B49,0) -> BG | C7: =-(C49-'S00 Impact'!C6) -> -412367.81 | D7: =-(D49-'S00 Impact'!D6) -> -996611.55 | E7: =-(E49-'S00 Impact'!E6) -> -1665044.6 | F7: =-(F49-'S00 Impact'!F6) -> -1347452.4 | G7: =-(G49-'S00 Impact'!G6) -> -5180360.8 | H7: =-(H49-'S00 Impact'!H6) -> -10124819 | N7: =A7 -> 1 | O7: =B7 -> BG | P7: =C7*Road!D7/100 -> -329.89425 | Q7: =D7*Road!E7/100 -> -2262.3082 | R7: =E7*Road!H7/100 -> -28888.524 | S7: =G7*Rail!C7/100 -> -2434.7696 | T7: =H7*Rail!D7/100 -> -2733.7011 | U7: =F7*IWW!C7/100 -> -6333.0265 | W7: =C7*Road!F7/100 -> -3954.6073 | X7: =D7*Road!G7/100 -> -9527.6064 | Y7: =E7*Road!I7/100 -> -74144.437 | Z7: =G7*Rail!E7/100 -> -7874.1484 | AA7: =H7*Rail!F7/100 -> -8808.5924 | AB7: =F7*IWW!D7/100 -> -3665.0706 | AD7: =(C7+D7)*Road!J7/100 -> -4438.285 | AE7: =E7*Road!L7/100 -> -16717.048 | AF7: =G7*Rail!G7/100 -> -4403.3067 | AG7: =H7*Rail!I7/100 -> -2733.7011 | AH7: =(C7+D7)*Road!K7/100 -> -3663.3463 | AI7: =E7*Road!M7/100 -> -37546.756 | AJ7: =G7*Rail!H7/100 -> -11137.776 | AK7: =H7*Rail!J7/100 -> -3037.4457
A8: =A50 -> 1 | B8: =IF(B50='S00 Impact'!B7,B50,0) -> BY | C8: =-(C50-'S00 Impact'!C7) -> 15745076 | D8: =-(D50-'S00 Impact'!D7) -> 3926120 | E8: =-(E50-'S00 Impact'!E7) -> 27352081 | F8: =-(F50-'S00 Impact'!F7) -> 0 | G8: =-(G50-'S00 Impact'!G7) -> 84498665 | H8: =-(H50-'S00 Impact'!H7) -> -98858064 | N8: =A8 -> 1 | O8: =B8 -> BY | P8: =C8*Road!D8/100 -> 15902.527 | Q8: =D8*Road!E8/100 -> 11189.442 | R8: =E8*Road!H8/100 -> 595454.8 | S8: =G8*Rail!C8/100 -> 62529.012 | T8: =H8*Rail!D8/100 -> -43497.548 | U8: =F8*IWW!C8/100 -> 0 | W8: =C8*Road!F8/100 -> 150995.28 | X8: =D8*Road!G8/100 -> 37533.707 | Y8: =E8*Road!I8/100 -> 1217988.2 | Z8: =G8*Rail!E8/100 -> 128437.97 | AA8: =H8*Rail!F8/100 -> -86006.515 | AB8: =F8*IWW!D8/100 -> 0 | AD8: =(C8+D8)*Road!J8/100 -> 77897.936 | AE8: =E8*Road!L8/100 -> 344362.7 | AF8: =G8*Rail!G8/100 -> 59994.052 | AG8: =H8*Rail!I8/100 -> -26691.677 | AH8: =(C8+D8)*Road!K8/100 -> 64324.811 | AI8: =E8*Road!M8/100 -> 773790.37 | AJ8: =G8*Rail!H8/100 -> 26194.586 | AK8: =H8*Rail!J8/100 -> -33611.742
A9: =A51 -> 1 | B9: =IF(B51='S00 Impact'!B8,B51,0) -> CH | C9: =-(C51-'S00 Impact'!C8) -> 1850019.3 | D9: =-(D51-'S00 Impact'!D8) -> -563102.88 | E9: =-(E51-'S00 Impact'!E8) -> -325735.81 | F9: =-(F51-'S00 Impact'!F8) -> -28417.494 | G9: =-(G51-'S00 Impact'!G8) -> -43362143 | H9: =-(H51-'S00 Impact'!H8) -> 63328448 | N9: =A9 -> 1 | O9: =B9 -> CH | P9: =C9*Road!D9/100 -> 5716.5597 | Q9: =D9*Road!E9/100 -> -4915.8881 | R9: =E9*Road!H9/100 -> -21700.52 | S9: =G9*Rail!C9/100 -> -17344.857 | T9: =H9*Rail!D9/100 -> 14565.543 | U9: =F9*IWW!C9/100 -> -533.11219 | W9: =C9*Road!F9/100 -> 17741.685 | X9: =D9*Road!G9/100 -> -5383.2635 | Y9: =E9*Road!I9/100 -> -14505.016 | Z9: =G9*Rail!E9/100 -> -65910.457 | AA9: =H9*Rail!F9/100 -> 55095.75 | AB9: =F9*IWW!D9/100 -> -77.295584 | AD9: =(C9+D9)*Road!J9/100 -> 15584.558 | AE9: =E9*Road!L9/100 -> -12557.116 | AF9: =G9*Rail!G9/100 -> -59839.757 | AG9: =H9*Rail!I9/100 -> 8865.9827 | AH9: =(C9+D9)*Road!K9/100 -> 12869.164 | AI9: =E9*Road!M9/100 -> -28202.207 | AJ9: =G9*Rail!H9/100 -> -95396.714 | AK9: =H9*Rail!J9/100 -> 37363.784
A10: =A52 -> 1 | B10: =IF(B52='S00 Impact'!B9,B52,0) -> CZ | C10: =-(C52-'S00 Impact'!C9) -> 12752685 | D10: =-(D52-'S00 Impact'!D9) -> 2284276.8 | E10: =-(E52-'S00 Impact'!E9) -> -7910937.6 | F10: =-(F52-'S00 Impact'!F9) -> -9640.8314 | G10: =-(G52-'S00 Impact'!G9) -> -22446281 | H10: =-(H52-'S00 Impact'!H9) -> -41236607 | N10: =A10 -> 1 | O10: =B10 -> CZ | P10: =C10*Road!D10/100 -> 18491.393 | Q10: =D10*Road!E10/100 -> 9456.906 | R10: =E10*Road!H10/100 -> -250143.85 | S10: =G10*Rail!C10/100 -> -18181.488 | T10: =H10*Rail!D10/100 -> -17731.741 | U10: =F10*IWW!C10/100 -> -180.862 | W10: =C10*Road!F10/100 -> 122425.78 | X10: =D10*Road!G10/100 -> 21814.844 | Y10: =E10*Road!I10/100 -> -352274.05 | Z10: =G10*Rail!E10/100 -> -34118.347 | AA10: =H10*Rail!F10/100 -> -35875.848 | AB10: =F10*IWW!D10/100 -> -26.223061 | AD10: =(C10+D10)*Road!J10/100 -> 33382.055 | AE10: =E10*Road!L10/100 -> -154025.95 | AF10: =G10*Rail!G10/100 -> -12345.455 | AG10: =H10*Rail!I10/100 -> -11546.25 | AH10: =(C10+D10)*Road!K10/100 -> 74282.591 | AI10: =E10*Road!M10/100 -> -382968.49 | AJ10: =G10*Rail!H10/100 -> -22446.281 | AK10: =H10*Rail!J10/100 -> -52782.857
A11: =A53 -> 1 | B11: =IF(B53='S00 Impact'!B10,B53,0) -> DE | C11: =-(C53-'S00 Impact'!C10) -> 1.2026586e+08 | D11: =-(D53-'S00 Impact'!D10) -> 20035440 | E11: =-(E53-'S00 Impact'!E10) -> 5792555.8 | F11: =-(F53-'S00 Impact'!F10) -> -23129189 | G11: =-(G53-'S00 Impact'!G10) -> -4.0388373e+08 | H11: =-(H53-'S00 Impact'!H10) -> 2.1627852e+08 | N11: =A11 -> 1 | O11: =B11 -> DE | P11: =C11*Road!D11/100 -> 177993.47 | Q11: =D11*Road!E11/100 -> 122616.89 | R11: =E11*Road!H11/100 -> 285225.45 | S11: =G11*Rail!C11/100 -> -141359.31 | T11: =H11*Rail!D11/100 -> 43255.703 | U11: =F11*IWW!C11/100 -> -561808.01 | W11: =C11*Road!F11/100 -> 1154552.2 | X11: =D11*Road!G11/100 -> 191338.45 | Y11: =E11*Road!I11/100 -> 257942.51 | Z11: =G11*Rail!E11/100 -> -613903.28 | AA11: =H11*Rail!F11/100 -> 188162.31 | AB11: =F11*IWW!D11/100 -> -62911.395 | AD11: =(C11+D11)*Road!J11/100 -> 533144.93 | AE11: =E11*Road!L11/100 -> 223187.17 | AF11: =G11*Rail!G11/100 -> -343301.17 | AG11: =H11*Rail!I11/100 -> 58395.199 | AH11: =(C11+D11)*Road!K11/100 -> 819359.58 | AI11: =E11*Road!M11/100 -> 223360.95 | AJ11: =G11*Rail!H11/100 -> -577553.74 | AK11: =H11*Rail!J11/100 -> 82185.836
A12: =A54 -> 1 | B12: =IF(B54='S00 Impact'!B11,B54,0) -> DK | C12: =-(C54-'S00 Impact'!C11) -> -56184322 | D12: =-(D54-'S00 Impact'!D11) -> -10097752 | E12: =-(E54-'S00 Impact'!E11) -> -14845245 | F12: =-(F54-'S00 Impact'!F11) -> 0 | G12: =-(G54-'S00 Impact'!G11) -> -19383865 | H12: =-(H54-'S00 Impact'!H11) -> -42.930384 | N12: =A12 -> 1 | O12: =B12 -> DK | P12: =C12*Road!D12/100 -> -77534.365 | Q12: =D12*Road!E12/100 -> -36856.797 | R12: =E12*Road!H12/100 -> -410025.65 | S12: =G12*Rail!C12/100 -> -8916.5778 | T12: =H12*Rail!D12/100 -> -0.013308419 | U12: =F12*IWW!C12/100 -> 0 | W12: =C12*Road!F12/100 -> -539369.5 | X12: =D12*Road!G12/100 -> -96433.536 | Y12: =E12*Road!I12/100 -> -661058.74 | Z12: =G12*Rail!E12/100 -> -29463.475 | AA12: =H12*Rail!F12/100 -> -0.037349434 | AB12: =F12*IWW!D12/100 -> 0 | AD12: =(C12+D12)*Road!J12/100 -> -258500.09 | AE12: =E12*Road!L12/100 -> -531905.11 | AF12: =G12*Rail!G12/100 -> -11048.803 | AG12: =H12*Rail!I12/100 -> -0.013308419 | AH12: =(C12+D12)*Road!K12/100 -> -568700.2 | AI12: =E12*Road!M12/100 -> -840686.2 | AJ12: =G12*Rail!H12/100 -> -10273.448 | AK12: =H12*Rail!J12/100 -> -0.054950892
A13: =A55 -> 1 | B13: =IF(B55='S00 Impact'!B12,B55,0) -> EE | C13: =-(C55-'S00 Impact'!C12) -> 4151031.9 | D13: =-(D55-'S00 Impact'!D12) -> 670432.58 | E13: =-(E55-'S00 Impact'!E12) -> -544644.72 | F13: =-(F55-'S00 Impact'!F12) -> 0 | G13: =-(G55-'S00 Impact'!G12) -> 398593.28 | H13: =-(H55-'S00 Impact'!H12) -> 32445610 | N13: =A13 -> 1 | O13: =B13 -> EE | P13: =C13*Road!D13/100 -> 8592.636 | Q13: =D13*Road!E13/100 -> 3948.8479 | R13: =E13*Road!H13/100 -> -24509.012 | S13: =G13*Rail!C13/100 -> 1267.5266 | T13: =H13*Rail!D13/100 -> 59375.466 | U13: =F13*IWW!C13/100 -> 0 | W13: =C13*Road!F13/100 -> 39849.906 | X13: =D13*Road!G13/100 -> 6402.6312 | Y13: =E13*Road!I13/100 -> -24253.029 | Z13: =G13*Rail!E13/100 -> 605.86179 | AA13: =H13*Rail!F13/100 -> 28227.681 | AB13: =F13*IWW!D13/100 -> 0 | AD13: =(C13+D13)*Road!J13/100 -> 10848.295 | AE13: =E13*Road!L13/100 -> -15092.105 | AF13: =G13*Rail!G13/100 -> 283.00123 | AG13: =H13*Rail!I13/100 -> 11031.507 | AH13: =(C13+D13)*Road!K13/100 -> 33894.895 | AI13: =E13*Road!M13/100 -> -37515.128 | AJ13: =G13*Rail!H13/100 -> 151.46545 | AK13: =H13*Rail!J13/100 -> 64242.308
A14: =A56 -> 1 | B14: =IF(B56='S00 Impact'!B13,B56,0) -> ES | C14: =-(C56-'S00 Impact'!C13) -> -67647316 | D14: =-(D56-'S00 Impact'!D13) -> -42966739 | E14: =-(E56-'S00 Impact'!E13) -> -1694350.6 | F14: =-(F56-'S00 Impact'!F13) -> 0 | G14: =-(G56-'S00 Impact'!G13) -> 60637428 | H14: =-(H56-'S00 Impact'!H13) -> 1055334 | N14: =A14 -> 1 | O14: =B14 -> ES | P14: =C14*Road!D14/100 -> -115000.44 | Q14: =D14*Road!E14/100 -> -146516.58 | R14: =E14*Road!H14/100 -> -41223.55 | S14: =G14*Rail!C14/100 -> 20010.351 | T14: =H14*Rail!D14/100 -> 200.51346 | U14: =F14*IWW!C14/100 -> 0 | W14: =C14*Road!F14/100 -> -649414.23 | X14: =D14*Road!G14/100 -> -410332.35 | Y14: =E14*Road!I14/100 -> -75449.432 | Z14: =G14*Rail!E14/100 -> 92168.89 | AA14: =H14*Rail!F14/100 -> 918.1406 | AB14: =F14*IWW!D14/100 -> 0 | AD14: =(C14+D14)*Road!J14/100 -> -498869.39 | AE14: =E14*Road!L14/100 -> -8403.979 | AF14: =G14*Rail!G14/100 -> 38807.954 | AG14: =H14*Rail!I14/100 -> 284.94019 | AH14: =(C14+D14)*Road!K14/100 -> -634924.67 | AI14: =E14*Road!M14/100 -> -64198.944 | AJ14: =G14*Rail!H14/100 -> 98839.007 | AK14: =H14*Rail!J14/100 -> 306.04687
A15: =A57 -> 1 | B15: =IF(B57='S00 Impact'!B14,B57,0) -> FI | C15: =-(C57-'S00 Impact'!C14) -> 24519108 | D15: =-(D57-'S00 Impact'!D14) -> 4529216.5 | E15: =-(E57-'S00 Impact'!E14) -> -2258745 | F15: =-(F57-'S00 Impact'!F14) -> 0 | G15: =-(G57-'S00 Impact'!G14) -> -30883793 | H15: =-(H57-'S00 Impact'!H14) -> -7269170.8 | N15: =A15 -> 1 | O15: =B15 -> FI | P15: =C15*Road!D15/100 -> 47076.688 | Q15: =D15*Road!E15/100 -> 24729.522 | R15: =E15*Road!H15/100 -> -94167.08 | S15: =G15*Rail!C15/100 -> -11427.003 | T15: =H15*Rail!D15/100 -> -2544.2098 | U15: =F15*IWW!C15/100 -> 0 | W15: =C15*Road!F15/100 -> 235383.44 | X15: =D15*Road!G15/100 -> 43254.017 | Y15: =E15*Road!I15/100 -> -100581.92 | Z15: =G15*Rail!E15/100 -> -46943.366 | AA15: =H15*Rail!F15/100 -> -6324.1786 | AB15: =F15*IWW!D15/100 -> 0 | AD15: =(C15+D15)*Road!J15/100 -> 131298.43 | AE15: =E15*Road!L15/100 -> -57981.985 | AF15: =G15*Rail!G15/100 -> -28721.928 | AG15: =H15*Rail!I15/100 -> -3125.7434 | AH15: =(C15+D15)*Road!K15/100 -> 189104.59 | AI15: =E15*Road!M15/100 -> -144153.11 | AJ15: =G15*Rail!H15/100 -> -34281.01 | AK15: =H15*Rail!J15/100 -> -9667.9972
... A41: =A83 -> 1 | B41: =IF(B83='S00 Impact'!B40,B83,0) -> YU | C41: =-(C83-'S00 Impact'!C40) -> 12164320 | D41: =-(D83-'S00 Impact'!D40) -> 1546728.3 | E41: =-(E83-'S00 Impact'!E40) -> -1075056.2 | F41: =-(F83-'S00 Impact'!F40) -> -8061478.1 | G41: =-(G83-'S00 Impact'!G40) -> 35107405 | H41: =-(H83-'S00 Impact'!H40) -> 2417812.6 | N41: =A41 -> 1 | O41: =B41 -> YU | P41: =C41*Road!D41/100 -> 10947.888 | Q41: =D41*Road!E41/100 -> 3959.6245 | R41: =E41*Road!H41/100 -> -20963.595 | S41: =G41*Rail!C41/100 -> 14745.11 | T41: =H41*Rail!D41/100 -> 580.27503 | U41: =F41*IWW!C41/100 -> -102542 | W41: =C41*Road!F41/100 -> 116655.83 | X41: =D41*Road!G41/100 -> 14786.723 | Y41: =E41*Road!I41/100 -> -47872.251 | Z41: =G41*Rail!E41/100 -> 53363.256 | AA41: =H41*Rail!F41/100 -> 2103.497 | AB41: =F41*IWW!D41/100 -> -21927.22 | AD41: =(C41+D41)*Road!J41/100 -> 48674.221 | AE41: =E41*Road!L41/100 -> -12126.633 | AF41: =G41*Rail!G41/100 -> 24926.258 | AG41: =H41*Rail!I41/100 -> 652.80941 | AH41: =(C41+D41)*Road!K41/100 -> 40173.371 | AI41: =E41*Road!M41/100 -> -27241.923 | AJ41: =G41*Rail!H41/100 -> 13340.814 | AK41: =H41*Rail!J41/100 -> 1184.7282
N42: =N41 -> 1 | O42: Total | P42: =SUM(P3:P41) -> 287276.58 | Q42: =SUM(Q3:Q41) -> 26367.327 | R42: =SUM(R3:R41) -> -3799293.8 | S42: =SUM(S3:S41) -> -1349271.1 | T42: =SUM(T3:T41) -> -123301.71 | U42: =SUM(U3:U41) -> -1263349.1 | V42: =L3*Air!C3/100 -> 12524162 | W42: =SUM(W3:W41) -> 4328270 | X42: =SUM(X3:X41) -> 444928.38 | Y42: =SUM(Y3:Y41) -> -5621466.5 | Z42: =SUM(Z3:Z41) -> -3731336.3 | AA42: =SUM(AA3:AA41) -> 164826.11 | AB42: =SUM(AB3:AB41) -> -171277.5 | AC42: =L3*Air!D3/100 -> 9083658.1 | AD42: =SUM(AD3:AD41) -> 749663.74 | AE42: =SUM(AE3:AE41) -> -2091332 | AF42: =SUM(AF3:AF41) -> -1893173.4 | AG42: =SUM(AG3:AG41) -> 31170.618 | AH42: =SUM(AH3:AH41) -> 72036.384 | AI42: =SUM(AI3:AI41) -> -2562343.4 | AJ42: =SUM(AJ3:AJ41) -> -2650529.7 | AK42: =SUM(AK3:AK41) -> -112698.51 | AL42: =SUM(P42:AK42) -> 2342986.1
V43: =SUM(P42:V42) -> 6302590.1 | AC43: =SUM(W42:AC42) -> 4497602.3 | AG43: =SUM(AD42:AG42) -> -3203671.1 | AK43: =SUM(AH42:AK42) -> -5253535.2
A44: Scenario | B44: CountryCode | C44: vkm_petrol_Carpassenger | D44: vkm_diesel_Carpassenger | E44: vkm_hgv_Freight | F44: Total_IWW_TonKM | G44: PersonKM_RailPassenger | H44: TonKM_RailFreight | J44: _TYPE_ | K44: _FREQ_ | L44: personkm_Air
A45: 1 | B45: AL | C45: 2.1946305e+09 | D45: 5.4290401e+08 | E45: 7.7736729e+08 | G45: 1.2919561e+08 | H45: 5.9563205e+08 | J45: 0 | K45: 3153 | L45: 8.3747343e+11
A46: 1 | B46: AT | C46: 4.306107e+10 | D46: 2.7041061e+10 | E46: 6.9015111e+09 | F46: 7.1114365e+09 | G46: 1.59888e+10 | H46: 2.4846053e+10
A47: 1 | B47: BA | C47: 5.0186891e+09 | D47: 1.2314642e+09 | E47: 8.4395451e+08 | F47: 7.4288782e+08 | G47: 5.9616295e+08 | H47: 1.2100905e+09
A48: 1 | B48: BE | C48: 4.2890233e+10 | D48: 3.2554207e+10 | E48: 8.4131374e+09 | F48: 9.585723e+09 | G48: 1.4194191e+10 | H48: 9.8118004e+09
A49: 1 | B49: BG | C49: 2.7971831e+10 | D49: 6.8361139e+09 | E49: 3.8423632e+09 | F49: 2.1019819e+09 | G49: 1.7015141e+10 | H49: 2.3019948e+10
A50: 1 | B50: BY | C50: 1.9217264e+10 | D50: 4.6324636e+09 | E50: 1.0407868e+10 | G50: 7.6271136e+09 | H50: 2.7050324e+10
A51: 1 | B51: CH | C51: 3.9944687e+10 | D51: 5.7135003e+09 | E51: 3.6438324e+09 | F51: 38969820 | G51: 1.1722333e+10 | H51: 1.1493976e+10
A52: 1 | B52: CZ | C52: 3.1717751e+10 | D52: 6.8882176e+09 | E52: 8.5555989e+09 | F52: 45311807 | G52: 9.3832196e+09 | H52: 3.5408529e+10
A53: 1 | B53: DE | C53: 3.7988934e+11 | D53: 8.8651875e+10 | E53: 4.6521887e+10 | F53: 7.5707877e+10 | G53: 1.1530356e+11 | H53: 1.0989409e+11
A54: 1 | B54: DK | C54: 3.7300951e+10 | D54: 3.8759444e+09 | E54: 7.2575758e+09 | G54: 6.4041322e+09 | H54: 3.3950105e+09
A55: 1 | B55: EE | C55: 3.3524979e+09 | D55: 6.0897248e+08 | E55: 1.8205132e+09 | G55: 2.8984304e+08 | H55: 3.0963131e+10
A56: 1 | B56: ES | C56: 1.7617341e+11 | D56: 9.4508052e+10 | E56: 4.8190827e+10 | G56: 2.9449567e+10 | H56: 2.4315302e+10
A57: 1 | B57: FI | C57: 2.9635967e+10 | D57: 4.325075e+09 | E57: 5.6562276e+09 | G57: 7.685976e+09 | H57: 2.211241e+10
A58: 1 | B58: FR | C58: 2.4538014e+11 | D58: 1.6776506e+11 | E58: 4.4052248e+10 | F58: 1.202358e+10 | G58: 9.5228413e+10 | H58: 5.5772116e+10
A59: 1 | B59: GR | C59: 2.7367376e+10 | D59: 6.7750061e+09 | E59: 6.2801838e+09 | G59: 2.9098501e+09 | H59: 1.4354068e+09
A60: 1 | B60: HR | C60: 2.2442137e+10 | D60: 5.5764745e+09 | E60: 2.6739356e+09 | F60: 3.1370498e+08 | G60: 9.2550823e+09 | H60: 7.5194226e+09
A61: 1 | B61: HU | C61: 2.9564689e+10 | D61: 6.0746475e+09 | E61: 5.3926668e+09 | F61: 1.1189849e+10 | G61: 1.5314321e+10 | H61: 2.372996e+10
A62: 1 | B62: IE | C62: 2.7595517e+10 | D62: 4.7750097e+09 | E62: 4.8659036e+09 | G62: 1.9408054e+09 | H62: 6.5536353e+08
A63: 1 | B63: IT | C63: 2.1149886e+11 | D63: 5.5750632e+10 | E63: 3.6796672e+10 | G63: 5.0980708e+10 | H63: 3.5958865e+10
A64: 1 | B64: LI | C64: 79887940 | D64: 23501476 | E64: 18047856 | G64: 15599827 | H64: 29501252
A65: 1 | B65: LT | C65: 8.537557e+09 | D65: 2.0340216e+09 | E65: 4.6497686e+09 | F65: 1945882.9 | G65: 1.3299707e+10 | H65: 3.6778794e+10
A66: 1 | B66: LU | C66: 5.5562924e+09 | D66: 2.6314174e+09 | E66: 9.0262664e+08 | G66: 1.584633e+08 | H66: 5.7564128e+08
A67: 1 | B67: LV | C67: 7.2348758e+09 | D67: 1.4398798e+09 | E67: 2.5981976e+09 | F67: 3057704.3 | G67: 8.1476257e+09 | H67: 5.0186649e+10
A68: 1 | B68: MD | C68: 5.5953155e+09 | D68: 1.381358e+09 | E68: 1.6184641e+09 | G68: 1.4134611e+09 | H68: 3.456984e+09
A69: 1 | B69: ME | C69: 1.5170271e+09 | D69: 3.7520356e+08 | E69: 1.8863374e+08 | G69: 1.3756604e+08 | H69: 1.8993832e+09
A70: 1 | B70: MK | C70: 4.8007771e+09 | D70: 1.1890492e+09 | E70: 1.3559311e+09 | G70: 7.2460355e+08 | H70: 4.1493305e+08
A71: 1 | B71: NL | C71: 9.5261795e+10 | D71: 1.9257978e+10 | E71: 1.0286859e+10 | F71: 3.9737151e+10 | G71: 1.2597379e+10 | H71: 6.5796306e+09
A72: 1 | B72: NO | C72: 4.0307644e+10 | D72: 9.4284933e+09 | E72: 3.860385e+09 | G72: 4.5270885e+09 | H72: 4.7576899e+09
A73: 1 | B73: PL | C73: 9.6025648e+10 | D73: 1.8884757e+10 | E73: 3.0172381e+10 | F73: 8.8262398e+08 | G73: 5.4083283e+10 | H73: 1.3158118e+11
A74: 1 | B74: PT | C74: 3.7356636e+10 | D74: 9.7755191e+09 | E74: 6.7215522e+09 | G74: 4.7100356e+09 | H74: 4.656334e+09
A75: 1 | B75: RO | C75: 3.8560359e+10 | D75: 9.4223422e+09 | E75: 1.3977085e+10 | F75: 2.1618614e+10 | G75: 1.1347015e+10 | H75: 5.7831373e+10
A76: 1 | B76: RU | C76: 1.5801291e+11 | D76: 3.8769348e+10 | E76: 9.0724043e+10 | G76: 1.0655919e+11 | H76: 2.3284499e+11
A77: 1 | B77: SE | C77: 5.754049e+10 | D77: 4.4888045e+09 | E77: 8.3914587e+09 | G77: 1.8027515e+10 | H77: 3.5563083e+10
A78: 1 | B78: SI | C78: 1.1788358e+10 | D78: 3.0865589e+09 | E78: 2.3271181e+09 | G78: 5.7612005e+09 | H78: 9.9879787e+09
A79: 1 | B79: SK | C79: 1.2751612e+10 | D79: 3.089747e+09 | E79: 4.0765055e+09 | F79: 7.0669744e+08 | G79: 2.5188758e+09 | H79: 2.3520859e+10
A80: 1 | B80: TR | C80: 1.140287e+11 | D80: 2.7961318e+10 | E80: 1.1219567e+10 | G80: 5.051873e+10 | H80: 1.3370962e+10
A81: 1 | B81: UA | C81: 7.3905311e+10 | D81: 1.8012012e+10 | E81: 2.2557852e+10 | G81: 3.5500381e+10 | H81: 7.7378314e+10
A82: 1 | B82: UK | C82: 3.3059876e+11 | D82: 7.5091825e+10 | E82: 2.6294497e+10 | F82: 3.2636544e+08 | G82: 4.8653585e+10 | H82: 3.7375333e+10
A83: 1 | B83: YU | C83: 2.052521e+10 | D83: 5.0172667e+09 | E83: 2.1450991e+09 | F83: 1.3220585e+10 | G83: 2.0537077e+10 | H83: 9.3374616e+09

Sheet S10 Impact
A1: Difference from Baseline | O1: Type | P1: Air Pollution | Q1: Air Pollution | R1: Air Pollution | S1: Air Pollution | T1: Air Pollution | U1: Air Pollution | V1: Air Pollution | W1: Global Warming | X1: Global Warming | Y1: Global Warming | Z1: Global Warming | AA1: Global Warming | AB1: Global Warming | AC1: Global Warming | AD1: Accidents | AE1: Accidents | AF1: Accidents | AG1: Accidents | AH1: Noise | AI1: Noise | AJ1: Noise | AK1: Noise
A2: Scenario | B2: CountryCode | C2: vkm_petrol_Carpassenger | D2: vkm_diesel_Carpassenger | E2: vkm_hgv_Freight | F2: Total_IWW_TonKM | G2: PersonKM_RailPassenger | H2: TonKM_RailFreight | J2: _TYPE_ | K2: _FREQ_ | L2: personkm_Air | N2: Scenario | O2: CountryCode | P2: Car Petrol (€) | Q2: Car Diesel (€) | R2: HGV Diesel (€) | S2: Train Person (€) | T2: Train Freight (€) | U2: IWW (€) | V2: Air (€) | W2: Car Petrol (€) | X2: Car Diesel (€) | Y2: HGV Diesel (€) | Z2: Train Person (€) | AA2: Train Freight (€) | AB2: IWW (€) | AC2: Air (€) | AD2: Car (€) | AE2: HGV (€) | AF2: Train Person (€) | AG2: Train Freight (€) | AH2: Car (€) | AI2: HGV (€) | AJ2: Train Person (€) | AK2: Train Freight (€)
A3: =A45 -> 10 | B3: =IF(B45='S00 Impact'!B2,B45,0) -> AL | C3: =-(C45-'S00 Impact'!C2) -> 9255162.2 | D3: =-(D45-'S00 Impact'!D2) -> 2143899.3 | E3: =-(E45-'S00 Impact'!E2) -> -355285.61 | F3: =-(F45-'S00 Impact'!F2) -> 0 | G3: =-(G45-'S00 Impact'!G2) -> -433334.2 | H3: =-(H45-'S00 Impact'!H2) -> -1685061.9 | J3: =J45 -> 0 | K3: =K45 -> 3153 | L3: =-(L45-'S00 Impact'!L2) -> 1.4384403e+09 | N3: =A3 -> 10 | O3: =B3 -> AL | P3: =C3*Road!D3/100 -> 9717.9203 | Q3: =D3*Road!E3/100 -> 6367.3809 | R3: =E3*Road!H3/100 -> -8061.4304 | S3: =G3*Rail!C3/100 -> -91.000182 | T3: =H3*Rail!D3/100 -> -320.16176 | U3: =F3*IWW!C3/100 -> 0 | W3: =C3*Road!F3/100 -> 88757.006 | X3: =D3*Road!G3/100 -> 20495.677 | Y3: =E3*Road!I3/100 -> -15820.868 | Z3: =G3*Rail!E3/100 -> -658.66799 | AA3: =H3*Rail!F3/100 -> -1466.0038 | AB3: =F3*IWW!D3/100 -> 0 | AD3: =(C3+D3)*Road!J3/100 -> 47078.124 | AE3: =E3*Road!L3/100 -> -4664.9 | AF3: =G3*Rail!G3/100 -> -225.33378 | AG3: =H3*Rail!I3/100 -> -454.96671 | AH3: =(C3+D3)*Road!K3/100 -> 38756.809 | AI3: =E3*Road!M3/100 -> -10477.373 | AJ3: =G3*Rail!H3/100 -> -628.33459 | AK3: =H3*Rail!J3/100 -> -657.17414
A4: =A46 -> 10 | B4: =IF(B46='S00 Impact'!B3,B46,0) -> AT | C4: =-(C46-'S00 Impact'!C3) -> -57014963 | D4: =-(D46-'S00 Impact'!D3) -> -13069218 | E4: =-(E46-'S00 Impact'!E3) -> -30358889 | F4: =-(F46-'S00 Impact'!F3) -> -2630514.2 | G4: =-(G46-'S00 Impact'!G3) -> -4.0385122e+08 | H4: =-(H46-'S00 Impact'!H3) -> -44195056 | N4: =A4 -> 10 | O4: =B4 -> AT | P4: =C4*Road!D4/100 -> -94074.689 | Q4: =D4*Road!E4/100 -> -84819.224 | R4: =E4*Road!H4/100 -> -1574108.4 | S4: =G4*Rail!C4/100 -> -129232.39 | T4: =H4*Rail!D4/100 -> -4861.4561 | U4: =F4*IWW!C4/100 -> -66315.262 | W4: =C4*Road!F4/100 -> -547343.65 | X4: =D4*Road!G4/100 -> -124811.03 | Y4: =E4*Road!I4/100 -> -1351881.3 | Z4: =G4*Rail!E4/100 -> -613853.85 | AA4: =H4*Rail!F4/100 -> -38449.699 | AB4: =F4*IWW!D4/100 -> -7154.9985 | AD4: =(C4+D4)*Road!J4/100 -> -350420.9 | AE4: =E4*Road!L4/100 -> -1525230.6 | AF4: =G4*Rail!G4/100 -> -452313.36 | AG4: =H4*Rail!I4/100 -> -13700.467 | AH4: =(C4+D4)*Road!K4/100 -> -499700.21 | AI4: =E4*Road!M4/100 -> -1428992.9 | AJ4: =G4*Rail!H4/100 -> -460390.39 | AK4: =H4*Rail!J4/100 -> -62315.029
A5: =A47 -> 10 | B5: =IF(B47='S00 Impact'!B4,B47,0) -> BA | C5: =-(C47-'S00 Impact'!C4) -> 84872859 | D5: =-(D47-'S00 Impact'!D4) -> 21485350 | E5: =-(E47-'S00 Impact'!E4) -> -29017172 | F5: =-(F47-'S00 Impact'!F4) -> -858931.97 | G5: =-(G47-'S00 Impact'!G4) -> 1740137.1 | H5: =-(H47-'S00 Impact'!H4) -> -1691217 | N5: =A5 -> 10 | O5: =B5 -> BA | P5: =C5*Road!D5/100 -> 76385.574 | Q5: =D5*Road!E5/100 -> 55002.496 | R5: =E5*Road!H5/100 -> -565834.86 | S5: =G5*Rail!C5/100 -> 1357.3069 | T5: =H5*Rail!D5/100 -> -761.04765 | U5: =F5*IWW!C5/100 -> -16113.564 | W5: =C5*Road!F5/100 -> 813930.72 | X5: =D5*Road!G5/100 -> 205399.95 | Y5: =E5*Road!I5/100 -> -1292134.7 | Z5: =G5*Rail!E5/100 -> 2645.0084 | AA5: =H5*Rail!F5/100 -> -1471.3588 | AB5: =F5*IWW!D5/100 -> -2336.2949 | AD5: =(C5+D5)*Road!J5/100 -> 377571.64 | AE5: =E5*Road!L5/100 -> -327313.7 | AF5: =G5*Rail!G5/100 -> 1287.7014 | AG5: =H5*Rail!I5/100 -> -456.62859 | AH5: =(C5+D5)*Road!K5/100 -> 311629.55 | AI5: =E5*Road!M5/100 -> -735295.14 | AJ5: =G5*Rail!H5/100 -> 2331.7837 | AK5: =H5*Rail!J5/100 -> -642.66246
A6: =A48 -> 10 | B6: =IF(B48='S00 Impact'!B5,B48,0) -> BE | C6: =-(C48-'S00 Impact'!C5) -> 12815894 | D6: =-(D48-'S00 Impact'!D5) -> 2188291.6 | E6: =-(E48-'S00 Impact'!E5) -> 100125.86 | F6: =-(F48-'S00 Impact'!F5) -> 7455332 | G6: =-(G48-'S00 Impact'!G5) -> -9214287.4 | H6: =-(H48-'S00 Impact'!H5) -> 4749826.3 | N6: =A6 -> 10 | O6: =B6 -> BE | P6: =C6*Road!D6/100 -> 20633.589 | Q6: =D6*Road!E6/100 -> 10109.907 | R6: =E6*Road!H6/100 -> 3471.3637 | S6: =G6*Rail!C6/100 -> -33724.292 | T6: =H6*Rail!D6/100 -> 10022.133 | U6: =F6*IWW!C6/100 -> 166701.22 | W6: =C6*Road!F6/100 -> 123032.58 | X6: =D6*Road!G6/100 -> 20898.184 | Y6: =E6*Road!I6/100 -> 4458.6047 | Z6: =G6*Rail!E6/100 -> -14005.717 | AA6: =H6*Rail!F6/100 -> 4132.3489 | AB6: =F6*IWW!D6/100 -> 20278.503 | AD6: =(C6+D6)*Road!J6/100 -> 85973.983 | AE6: =E6*Road!L6/100 -> 9741.2453 | AF6: =G6*Rail!G6/100 -> -6542.144 | AG6: =H6*Rail!I6/100 -> 1187.4566 | AH6: =(C6+D6)*Road!K6/100 -> 98727.54 | AI6: =E6*Road!M6/100 -> 4350.4688 | AJ6: =G6*Rail!H6/100 -> -3685.715 | AK6: =H6*Rail!J6/100 -> 3134.8853
A7: =A49 -> 10 | B7: =IF(B49='S00 Impact'!B6,B49,0) -> BG | C7: =-(C49-'S00 Impact'!C6) -> -1.8039222e+09 | D7: =-(D49-'S00 Impact'!D6) -> -4.1058798e+08 | E7: =-(E49-'S00 Impact'!E6) -> -11078412 | F7: =-(F49-'S00 Impact'!F6) -> 67569.391 | G7: =-(G49-'S00 Impact'!G6) -> -1.2400438e+09 | H7: =-(H49-'S00 Impact'!H6) -> 1.6108526e+09 | N7: =A7 -> 10 | O7: =B7 -> BG | P7: =C7*Road!D7/100 -> -1443137.8 | Q7: =D7*Road!E7/100 -> -932034.72 | R7: =E7*Road!H7/100 -> -192210.45 | S7: =G7*Rail!C7/100 -> -582820.61 | T7: =H7*Rail!D7/100 -> 434930.19 | U7: =F7*IWW!C7/100 -> 317.57614 | W7: =C7*Road!F7/100 -> -17299614 | X7: =D7*Road!G7/100 -> -3925221.1 | Y7: =E7*Road!I7/100 -> -493321.68 | Z7: =G7*Rail!E7/100 -> -1884866.6 | AA7: =H7*Rail!F7/100 -> 1401441.7 | AB7: =F7*IWW!D7/100 -> 183.78874 | AD7: =(C7+D7)*Road!J7/100 -> -6975707 | AE7: =E7*Road!L7/100 -> -111227.25 | AF7: =G7*Rail!G7/100 -> -1054037.3 | AG7: =H7*Rail!I7/100 -> 434930.19 | AH7: =(C7+D7)*Road!K7/100 -> -5757726.5 | AI7: =E7*Road!M7/100 -> -249818.19 | AJ7: =G7*Rail!H7/100 -> -2666094.3 | AK7: =H7*Rail!J7/100 -> 483255.77
A8: =A50 -> 10 | B8: =IF(B50='S00 Impact'!B7,B50,0) -> BY | C8: =-(C50-'S00 Impact'!C7) -> 39995418 | D8: =-(D50-'S00 Impact'!D7) -> 8085517.6 | E8: =-(E50-'S00 Impact'!E7) -> 19546749 | F8: =-(F50-'S00 Impact'!F7) -> 0 | G8: =-(G50-'S00 Impact'!G7) -> 39937318 | H8: =-(H50-'S00 Impact'!H7) -> -60981352 | N8: =A8 -> 10 | O8: =B8 -> BY | P8: =C8*Road!D8/100 -> 40395.372 | Q8: =D8*Road!E8/100 -> 23043.725 | R8: =E8*Road!H8/100 -> 425532.74 | S8: =G8*Rail!C8/100 -> 29553.615 | T8: =H8*Rail!D8/100 -> -26831.795 | U8: =F8*IWW!C8/100 -> 0 | W8: =C8*Road!F8/100 -> 383556.06 | X8: =D8*Road!G8/100 -> 77297.549 | Y8: =E8*Road!I8/100 -> 870416.75 | Z8: =G8*Rail!E8/100 -> 60704.723 | AA8: =H8*Rail!F8/100 -> -53053.777 | AB8: =F8*IWW!D8/100 -> 0 | AD8: =(C8+D8)*Road!J8/100 -> 190400.5 | AE8: =E8*Road!L8/100 -> 246093.58 | AF8: =G8*Rail!G8/100 -> 28355.496 | AG8: =H8*Rail!I8/100 -> -16464.965 | AH8: =(C8+D8)*Road!K8/100 -> 157224.66 | AI8: =E8*Road!M8/100 -> 552977.54 | AJ8: =G8*Rail!H8/100 -> 12380.569 | AK8: =H8*Rail!J8/100 -> -20733.66
A9: =A51 -> 10 | B9: =IF(B51='S00 Impact'!B8,B51,0) -> CH | C9: =-(C51-'S00 Impact'!C8) -> -9321981.4 | D9: =-(D51-'S00 Impact'!D8) -> -5163097.8 | E9: =-(E51-'S00 Impact'!E8) -> 4601611.6 | F9: =-(F51-'S00 Impact'!F8) -> 343937.98 | G9: =-(G51-'S00 Impact'!G8) -> 5964163.8 | H9: =-(H51-'S00 Impact'!H8) -> 31123177 | N9: =A9 -> 10 | O9: =B9 -> CH | P9: =C9*Road!D9/100 -> -28804.922 | Q9: =D9*Road!E9/100 -> -45073.843 | R9: =E9*Road!H9/100 -> 306559.36 | S9: =G9*Rail!C9/100 -> 2385.6655 | T9: =H9*Rail!D9/100 -> 7158.3308 | U9: =F9*IWW!C9/100 -> 6452.2765 | W9: =C9*Road!F9/100 -> -89397.802 | X9: =D9*Road!G9/100 -> -49359.215 | Y9: =E9*Road!I9/100 -> 204909.76 | Z9: =G9*Rail!E9/100 -> 9065.529 | AA9: =H9*Rail!F9/100 -> 27077.164 | AB9: =F9*IWW!D9/100 -> 935.5113 | AD9: =(C9+D9)*Road!J9/100 -> -175414.31 | AE9: =E9*Road!L9/100 -> 177392.13 | AF9: =G9*Rail!G9/100 -> 8230.5461 | AG9: =H9*Rail!I9/100 -> 4357.2448 | AH9: =(C9+D9)*Road!K9/100 -> -144850.79 | AI9: =E9*Road!M9/100 -> 398407.53 | AJ9: =G9*Rail!H9/100 -> 13121.16 | AK9: =H9*Rail!J9/100 -> 18362.675
A10: =A52 -> 10 | B10: =IF(B52='S00 Impact'!B9,B52,0) -> CZ | C10: =-(C52-'S00 Impact'!C9) -> -3.6809602e+08 | D10: =-(D52-'S00 Impact'!D9) -> -78279129 | E10: =-(E52-'S00 Impact'!E9) -> -6202531.1 | F10: =-(F52-'S00 Impact'!F9) -> -6167.3151 | G10: =-(G52-'S00 Impact'!G9) -> 18940931 | H10: =-(H52-'S00 Impact'!H9) -> -59988953 | N10: =A10 -> 10 | O10: =B10 -> CZ | P10: =C10*Road!D10/100 -> -533739.23 | Q10: =D10*Road!E10/100 -> -324075.59 | R10: =E10*Road!H10/100 -> -196124.03 | S10: =G10*Rail!C10/100 -> 15342.154 | T10: =H10*Rail!D10/100 -> -25795.25 | U10: =F10*IWW!C10/100 -> -115.69883 | W10: =C10*Road!F10/100 -> -3533721.8 | X10: =D10*Road!G10/100 -> -747565.68 | Y10: =E10*Road!I10/100 -> -276198.71 | Z10: =G10*Rail!E10/100 -> 28790.215 | AA10: =H10*Rail!F10/100 -> -52190.389 | AB10: =F10*IWW!D10/100 -> -16.775097 | AD10: =(C10+D10)*Road!J10/100 -> -990952.84 | AE10: =E10*Road!L10/100 -> -120763.28 | AF10: =G10*Rail!G10/100 -> 10417.512 | AG10: =H10*Rail!I10/100 -> -16796.907 | AH10: =(C10+D10)*Road!K10/100 -> -2205093.2 | AI10: =E10*Road!M10/100 -> -300264.53 | AJ10: =G10*Rail!H10/100 -> 18940.931 | AK10: =H10*Rail!J10/100 -> -76785.86
A11: =A53 -> 10 | B11: =IF(B53='S00 Impact'!B10,B53,0) -> DE | C11: =-(C53-'S00 Impact'!C10) -> -4.4749235e+08 | D11: =-(D53-'S00 Impact'!D10) -> -1.0326924e+08 | E11: =-(E53-'S00 Impact'!E10) -> -38669.076 | F11: =-(F53-'S00 Impact'!F10) -> -1550662.7 | G11: =-(G53-'S00 Impact'!G10) -> -5.7245521e+08 | H11: =-(H53-'S00 Impact'!H10) -> -34047.561 | N11: =A11 -> 10 | O11: =B11 -> DE | P11: =C11*Road!D11/100 -> -662288.67 | Q11: =D11*Road!E11/100 -> -632007.74 | R11: =E11*Road!H11/100 -> -1904.0653 | S11: =G11*Rail!C11/100 -> -200359.32 | T11: =H11*Rail!D11/100 -> -6.8095122 | U11: =F11*IWW!C11/100 -> -37665.597 | W11: =C11*Road!F11/100 -> -4295926.5 | X11: =D11*Road!G11/100 -> -986221.23 | Y11: =E11*Road!I11/100 -> -1721.9339 | Z11: =G11*Rail!E11/100 -> -870131.92 | AA11: =H11*Rail!F11/100 -> -29.621378 | AB11: =F11*IWW!D11/100 -> -4217.8026 | AD11: =(C11+D11)*Road!J11/100 -> -2092894 | AE11: =E11*Road!L11/100 -> -1489.9195 | AF11: =G11*Rail!G11/100 -> -486586.93 | AG11: =H11*Rail!I11/100 -> -9.1928415 | AH11: =(C11+D11)*Road!K11/100 -> -3216447.7 | AI11: =E11*Road!M11/100 -> -1491.0796 | AJ11: =G11*Rail!H11/100 -> -818610.95 | AK11: =H11*Rail!J11/100 -> -12.938073
A12: =A54 -> 10 | B12: =IF(B54='S00 Impact'!B11,B54,0) -> DK | C12: =-(C54-'S00 Impact'!C11) -> -1.0643979e+08 | D12: =-(D54-'S00 Impact'!D11) -> -25434360 | E12: =-(E54-'S00 Impact'!E11) -> 8665957 | F12: =-(F54-'S00 Impact'!F11) -> 0 | G12: =-(G54-'S00 Impact'!G11) -> 18040301 | H12: =-(H54-'S00 Impact'!H11) -> -21216.629 | N12: =A12 -> 10 | O12: =B12 -> DK | P12: =C12*Road!D12/100 -> -146886.91 | Q12: =D12*Road!E12/100 -> -92835.415 | R12: =E12*Road!H12/100 -> 239353.73 | S12: =G12*Rail!C12/100 -> 8298.5384 | T12: =H12*Rail!D12/100 -> -6.5771549 | U12: =F12*IWW!C12/100 -> 0 | W12: =C12*Road!F12/100 -> -1021822 | X12: =D12*Road!G12/100 -> -242898.14 | Y12: =E12*Road!I12/100 -> 385895.07 | Z12: =G12*Rail!E12/100 -> 27421.257 | AA12: =H12*Rail!F12/100 -> -18.458467 | AB12: =F12*IWW!D12/100 -> 0 | AD12: =(C12+D12)*Road!J12/100 -> -514309.18 | AE12: =E12*Road!L12/100 -> 310501.24 | AF12: =G12*Rail!G12/100 -> 10282.971 | AG12: =H12*Rail!I12/100 -> -6.5771549 | AH12: =(C12+D12)*Road!K12/100 -> -1131480.2 | AI12: =E12*Road!M12/100 -> 490753.15 | AJ12: =G12*Rail!H12/100 -> 9561.3595 | AK12: =H12*Rail!J12/100 -> -27.157285
A13: =A55 -> 10 | B13: =IF(B55='S00 Impact'!B12,B55,0) -> EE | C13: =-(C55-'S00 Impact'!C12) -> -6252838.3 | D13: =-(D55-'S00 Impact'!D12) -> -151811.41 | E13: =-(E55-'S00 Impact'!E12) -> 6535735.8 | F13: =-(F55-'S00 Impact'!F12) -> 0 | G13: =-(G55-'S00 Impact'!G12) -> -1480216 | H13: =-(H55-'S00 Impact'!H12) -> -26942454 | N13: =A13 -> 10 | O13: =B13 -> EE | P13: =C13*Road!D13/100 -> -12943.375 | Q13: =D13*Road!E13/100 -> -894.16923 | R13: =E13*Road!H13/100 -> 294108.11 | S13: =G13*Rail!C13/100 -> -4707.0868 | T13: =H13*Rail!D13/100 -> -49304.69 | U13: =F13*IWW!C13/100 -> 0 | W13: =C13*Road!F13/100 -> -60027.248 | X13: =D13*Road!G13/100 -> -1449.799 | Y13: =E13*Road!I13/100 -> 291036.31 | Z13: =G13*Rail!E13/100 -> -2249.9283 | AA13: =H13*Rail!F13/100 -> -23439.935 | AB13: =F13*IWW!D13/100 -> 0 | AD13: =(C13+D13)*Road!J13/100 -> -14410.462 | AE13: =E13*Road!L13/100 -> 181105.24 | AF13: =G13*Rail!G13/100 -> -1050.9533 | AG13: =H13*Rail!I13/100 -> -9160.4342 | AH13: =(C13+D13)*Road!K13/100 -> -45024.688 | AI13: =E13*Road!M13/100 -> 450181.48 | AJ13: =G13*Rail!H13/100 -> -562.48207 | AK13: =H13*Rail!J13/100 -> -53346.058
A14: =A56 -> 10 | B14: =IF(B56='S00 Impact'!B13,B56,0) -> ES | C14: =-(C56-'S00 Impact'!C13) -> -1.1619115e+08 | D14: =-(D56-'S00 Impact'!D13) -> -42747907 | E14: =-(E56-'S00 Impact'!E13) -> 738890.52 | F14: =-(F56-'S00 Impact'!F13) -> 0 | G14: =-(G56-'S00 Impact'!G13) -> 1.1502058e+08 | H14: =-(H56-'S00 Impact'!H13) -> 5801362.6 | N14: =A14 -> 10 | O14: =B14 -> ES | P14: =C14*Road!D14/100 -> -197524.95 | Q14: =D14*Road!E14/100 -> -145770.36 | R14: =E14*Road!H14/100 -> 17977.206 | S14: =G14*Rail!C14/100 -> 37956.792 | T14: =H14*Rail!D14/100 -> 1102.2589 | U14: =F14*IWW!C14/100 -> 0 | W14: =C14*Road!F14/100 -> -1115435 | X14: =D14*Road!G14/100 -> -408242.51 | Y14: =E14*Road!I14/100 -> 32902.795 | Z14: =G14*Rail!E14/100 -> 174831.28 | AA14: =H14*Rail!F14/100 -> 5047.1855 | AB14: =F14*IWW!D14/100 -> 0 | AD14: =(C14+D14)*Road!J14/100 -> -716815.12 | AE14: =E14*Road!L14/100 -> 3664.897 | AF14: =G14*Rail!G14/100 -> 73613.171 | AG14: =H14*Rail!I14/100 -> 1566.3679 | AH14: =(C14+D14)*Road!K14/100 -> -912310.16 | AI14: =E14*Road!M14/100 -> 27996.562 | AJ14: =G14*Rail!H14/100 -> 187483.55 | AK14: =H14*Rail!J14/100 -> 1682.3952
A15: =A57 -> 10 | B15: =IF(B57='S00 Impact'!B14,B57,0) -> FI | C15: =-(C57-'S00 Impact'!C14) -> 16277406 | D15: =-(D57-'S00 Impact'!D14) -> 4263410 | E15: =-(E57-'S00 Impact'!E14) -> 825545.88 | F15: =-(F57-'S00 Impact'!F14) -> 0 | G15: =-(G57-'S00 Impact'!G14) -> -1357643.5 | H15: =-(H57-'S00 Impact'!H14) -> -11146628 | N15: =A15 -> 10 | O15: =B15 -> FI | P15: =C15*Road!D15/100 -> 31252.62 | Q15: =D15*Road!E15/100 -> 23278.218 | R15: =E15*Road!H15/100 -> 34417.008 | S15: =G15*Rail!C15/100 -> -502.3281 | T15: =H15*Rail!D15/100 -> -3901.3198 | U15: =F15*IWW!C15/100 -> 0 | W15: =C15*Road!F15/100 -> 156263.1 | X15: =D15*Road!G15/100 -> 40715.565 | Y15: =E15*Road!I15/100 -> 36761.558 | Z15: =G15*Rail!E15/100 -> -2063.6181 | AA15: =H15*Rail!F15/100 -> -9697.5664 | AB15: =F15*IWW!D15/100 -> 0 | AD15: =(C15+D15)*Road!J15/100 -> 92844.49 | AE15: =E15*Road!L15/100 -> 21191.763 | AF15: =G15*Rail!G15/100 -> -1262.6085 | AG15: =H15*Rail!I15/100 -> -4793.0501 | AH15: =(C15+D15)*Road!K15/100 -> 133720.71 | AI15: =E15*Road!M15/100 -> 52686.338 | AJ15: =G15*Rail!H15/100 -> -1506.9843 | AK15: =H15*Rail!J15/100 -> -14825.015
... A41: =A83 -> 10 | B41: =IF(B83='S00 Impact'!B40,B83,0) -> YU | C41: =-(C83-'S00 Impact'!C40) -> 2.1737542e+09 | D41: =-(D83-'S00 Impact'!D40) -> 4.8155212e+08 | E41: =-(E83-'S00 Impact'!E40) -> 6842417.5 | F41: =-(F83-'S00 Impact'!F40) -> -502038.3 | G41: =-(G83-'S00 Impact'!G40) -> 4.1415275e+09 | H41: =-(H83-'S00 Impact'!H40) -> 8.1087991e+08 | N41: =A41 -> 10 | O41: =B41 -> YU | P41: =C41*Road!D41/100 -> 1956378.8 | Q41: =D41*Road!E41/100 -> 1232773.4 | R41: =E41*Road!H41/100 -> 133427.14 | S41: =G41*Rail!C41/100 -> 1739441.5 | T41: =H41*Rail!D41/100 -> 194611.18 | U41: =F41*IWW!C41/100 -> -6385.9272 | W41: =C41*Road!F41/100 -> 20846303 | X41: =D41*Road!G41/100 -> 4603638.3 | Y41: =E41*Road!I41/100 -> 304692.85 | Z41: =G41*Rail!E41/100 -> 6295121.8 | AA41: =H41*Rail!F41/100 -> 705465.53 | AB41: =F41*IWW!D41/100 -> -1365.5442 | AD41: =(C41+D41)*Road!J41/100 -> 9426337.4 | AE41: =E41*Road!L41/100 -> 77182.469 | AF41: =G41*Rail!G41/100 -> 2940484.5 | AG41: =H41*Rail!I41/100 -> 218937.58 | AH41: =(C41+D41)*Road!K41/100 -> 7780047.5 | AI41: =E41*Road!M41/100 -> 173386.86 | AJ41: =G41*Rail!H41/100 -> 1573780.4 | AK41: =H41*Rail!J41/100 -> 397331.16
N42: =N41 -> 10 | O42: Total | P42: =SUM(P3:P41) -> -7384879.5 | Q42: =SUM(Q3:Q41) -> -5478187.8 | R42: =SUM(R3:R41) -> 6928189.3 | S42: =SUM(S3:S41) -> 2384968.7 | T42: =SUM(T3:T41) -> -66137.378 | U42: =SUM(U3:U41) -> 185827.93 | V42: =L3*Air!C3/100 -> 9896469.3 | W42: =SUM(W3:W41) -> -47451967 | X42: =SUM(X3:X41) -> -11419531 | Y42: =SUM(Y3:Y41) -> 15089197 | Z42: =SUM(Z3:Z41) -> -2903285.7 | AA42: =SUM(AA3:AA41) -> -385515.69 | AB42: =SUM(AB3:AB41) -> 26453.15 | AC42: =L3*Air!D3/100 -> 7177817.1 | AD42: =SUM(AD3:AD41) -> -22369885 | AE42: =SUM(AE3:AE41) -> 3432348 | AF42: =SUM(AF3:AF41) -> -1726698.9 | AG42: =SUM(AG3:AG41) -> -103615.17 | AH42: =SUM(AH3:AH41) -> -24076537 | AI42: =SUM(AI3:AI41) -> 11212804 | AJ42: =SUM(AJ3:AJ41) -> -5162900.1 | AK42: =SUM(AK3:AK41) -> -2433573.6 | AL42: =SUM(P42:AK42) -> -74628639
V43: =SUM(P42:V42) -> 6466250.5 | AC43: =SUM(W42:AC42) -> -39866832 | AG43: =SUM(AD42:AG42) -> -20767851 | AK43: =SUM(AH42:AK42) -> -20460206
A44: scenario | B44: CountryCode | C44: vkm_petrol_Carpassenger | D44: vkm_diesel_Carpassenger | E44: vkm_hgv_Freight | F44: Total_IWW_TonKM | G44: PersonKM_RailPassenger | H44: TonKM_RailFreight | J44: _TYPE_ | K44: _FREQ_ | L44: personkm_Air
A45: 10 | B45: AL | C45: 2.1888114e+09 | D45: 5.4161304e+08 | E45: 7.7757649e+08 | G45: 1.2740437e+08 | H45: 5.9726357e+08 | J45: 0 | K45: 3153 | L45: 8.3785536e+11
A46: 10 | B46: AT | C46: 4.3142986e+10 | D46: 2.7062851e+10 | E46: 6.9156776e+09 | F46: 7.1090553e+09 | G46: 1.6264196e+10 | H46: 2.480397e+10
A47: 10 | B47: BA | C47: 4.9429243e+09 | D47: 1.2120968e+09 | E47: 8.7251077e+08 | F47: 7.3957669e+08 | G47: 5.9825823e+08 | H47: 1.2101454e+09
A48: 10 | B48: BE | C48: 4.2884992e+10 | D48: 3.2551601e+10 | E48: 8.4077116e+09 | F48: 9.5812004e+09 | G48: 1.4162124e+10 | H48: 9.8102873e+09
A49: 10 | B49: BG | C49: 2.9775341e+10 | D49: 7.2457053e+09 | E49: 3.8517766e+09 | F49: 2.1005669e+09 | G49: 1.8250004e+10 | H49: 2.139897e+10
A50: 10 | B50: BY | C50: 1.9193013e+10 | D50: 4.6283042e+09 | E50: 1.0415673e+10 | G50: 7.671675e+09 | H50: 2.7012447e+10
A51: 10 | B51: CH | C51: 3.9955859e+10 | D51: 5.7181002e+09 | E51: 3.638905e+09 | F51: 38597464 | G51: 1.1673007e+10 | H51: 1.1526181e+10
A52: 10 | B52: CZ | C52: 3.2098599e+10 | D52: 6.968781e+09 | E52: 8.5538905e+09 | F52: 45308333 | G52: 9.3418324e+09 | H52: 3.5427281e+10
A53: 10 | B53: DE | C53: 3.804571e+11 | D53: 8.877518e+10 | E53: 4.6527718e+10 | F53: 7.5686299e+10 | G53: 1.1547213e+11 | H53: 1.1011041e+11
A54: 10 | B54: DK | C54: 3.7351207e+10 | D54: 3.891281e+09 | E54: 7.2340646e+09 | G54: 6.3667081e+09 | H54: 3.3950317e+09
A55: 10 | B55: EE | C55: 3.3629018e+09 | D55: 6.0979473e+08 | E55: 1.8134328e+09 | G55: 2.9172185e+08 | H55: 3.1022519e+10
A56: 10 | B56: ES | C56: 1.7622195e+11 | D56: 9.4507834e+10 | E56: 4.8188394e+10 | G56: 2.9395184e+10 | H56: 2.4310556e+10
A57: 10 | B57: FI | C57: 2.9644208e+10 | D57: 4.3253409e+09 | E57: 5.6531433e+09 | G57: 7.6564498e+09 | H57: 2.2116287e+10
A58: 10 | B58: FR | C58: 2.4560397e+11 | D58: 1.6783922e+11 | E58: 4.4050754e+10 | F58: 1.2012701e+10 | G58: 9.5516405e+10 | H58: 5.5786633e+10
A59: 10 | B59: GR | C59: 2.7429018e+10 | D59: 6.790787e+09 | E59: 6.2561022e+09 | G59: 3.0235197e+09 | H59: 1.4138327e+09
A60: 10 | B60: HR | C60: 2.2176193e+10 | D60: 5.5141618e+09 | E60: 2.6611783e+09 | F60: 3.1227054e+08 | G60: 8.4646461e+09 | H60: 8.0282534e+09
A61: 10 | B61: HU | C61: 3.0629196e+10 | D61: 6.3156286e+09 | E61: 5.4094575e+09 | F61: 1.118554e+10 | G61: 1.6093275e+10 | H61: 2.3374475e+10
A62: 10 | B62: IE | C62: 2.7574845e+10 | D62: 4.7715534e+09 | E62: 4.8690082e+09 | G62: 1.9366195e+09 | H62: 6.5522891e+08
A63: 10 | B63: IT | C63: 2.1165353e+11 | D63: 5.5789359e+10 | E63: 3.6751618e+10 | G63: 5.0345754e+10 | H63: 3.579201e+10
A64: 10 | B64: LI | C64: 80624315 | D64: 23897855 | E64: 17694815 | G64: 12721579 | H64: 28926562
A65: 10 | B65: LT | C65: 8.54473e+09 | D65: 2.0373578e+09 | E65: 4.6397713e+09 | F65: 1945882.9 | G65: 1.3282965e+10 | H65: 3.6753826e+10
A66: 10 | B66: LU | C66: 5.5457695e+09 | D66: 2.6298629e+09 | E66: 9.0278364e+08 | G66: 1.5828903e+08 | H66: 5.7333795e+08
A67: 10 | B67: LV | C67: 7.2121915e+09 | D67: 1.4359038e+09 | E67: 2.6004592e+09 | F67: 3057704.3 | G67: 8.1387251e+09 | H67: 5.0292787e+10
A68: 10 | B68: MD | C68: 5.5726e+09 | D68: 1.3757219e+09 | E68: 1.6128979e+09 | G68: 1.4172288e+09 | H68: 3.4518674e+09
A69: 10 | B69: ME | C69: 1.5102208e+09 | D69: 3.7356533e+08 | E69: 1.882674e+08 | G69: 1.3582949e+08 | H69: 1.9009497e+09
A70: 10 | B70: MK | C70: 4.7434395e+09 | D70: 1.1760457e+09 | E70: 1.3518225e+09 | G70: 6.3907322e+08 | H70: 4.0932208e+08
A71: 10 | B71: NL | C71: 9.5266512e+10 | D71: 1.9259437e+10 | E71: 1.0287449e+10 | F71: 3.9737977e+10 | G71: 1.2557922e+10 | H71: 6.5887587e+09
A72: 10 | B72: NO | C72: 4.0221415e+10 | D72: 9.4060875e+09 | E72: 3.862091e+09 | G72: 4.4832238e+09 | H72: 4.7573675e+09
A73: 10 | B73: PL | C73: 9.6060849e+10 | D73: 1.8893949e+10 | E73: 3.0171435e+10 | F73: 8.8177327e+08 | G73: 5.4105038e+10 | H73: 1.3152247e+11
A74: 10 | B74: PT | C74: 3.7358296e+10 | D74: 9.7756517e+09 | E74: 6.7187957e+09 | G74: 4.7216228e+09 | H74: 4.656437e+09
A75: 10 | B75: RO | C75: 4.081867e+10 | D75: 9.9225955e+09 | E75: 1.400922e+10 | F75: 2.1603938e+10 | G75: 1.5267276e+10 | H75: 6.1001187e+10
A76: 10 | B76: RU | C76: 1.5853358e+11 | D76: 3.8900112e+10 | E76: 9.0305543e+10 | G76: 1.0635363e+11 | H76: 2.3280471e+11
A77: 10 | B77: SE | C77: 5.765837e+10 | D77: 4.5115169e+09 | E77: 8.4314445e+09 | G77: 1.790833e+10 | H77: 3.5559894e+10
A78: 10 | B78: SI | C78: 1.1771226e+10 | D78: 3.0838737e+09 | E78: 2.3228654e+09 | G78: 5.4912443e+09 | H78: 9.9204674e+09
A79: 10 | B79: SK | C79: 1.2894123e+10 | D79: 3.1201692e+09 | E79: 4.06015e+09 | F79: 7.0645474e+08 | G79: 2.5150847e+09 | H79: 2.3596348e+10
A80: 10 | B80: TR | C80: 1.1495628e+11 | D80: 2.8171019e+10 | E80: 1.1229572e+10 | G80: 4.9772969e+10 | H80: 1.3360897e+10
A81: 10 | B81: UA | C81: 7.3818799e+10 | D81: 1.7995946e+10 | E81: 2.2523814e+10 | G81: 3.5514108e+10 | H81: 7.7078226e+10
A82: 10 | B82: UK | C82: 3.3038087e+11 | D82: 7.5039605e+10 | E82: 2.6293399e+10 | F82: 3.2637929e+08 | G82: 4.8555182e+10 | H82: 3.7368529e+10
A83: 10 | B83: YU | C83: 1.836362e+10 | D83: 4.5372613e+09 | E83: 2.1371817e+09 | F83: 1.3213025e+10 | G83: 1.6430657e+10 | H83: 8.5289995e+09

Sheet S18 Impact
A1: Difference from Baseline | O1: Type | P1: Air Pollution | Q1: Air Pollution | R1: Air Pollution | S1: Air Pollution | T1: Air Pollution | U1: Air Pollution | V1: Air Pollution | W1: Global Warming | X1: Global Warming | Y1: Global Warming | Z1: Global Warming | AA1: Global Warming | AB1: Global Warming | AC1: Global Warming | AD1: Accidents | AE1: Accidents | AF1: Accidents | AG1: Accidents | AH1: Noise | AI1: Noise | AJ1: Noise | AK1: Noise
A2: Scenario | B2: CountryCode | C2: vkm_petrol_Carpassenger | D2: vkm_diesel_Carpassenger | E2: vkm_hgv_Freight | F2: Total_IWW_TonKM | G2: PersonKM_RailPassenger | H2: TonKM_RailFreight | J2: _TYPE_ | K2: _FREQ_ | L2: personkm_Air | N2: Scenario | O2: CountryCode | P2: Car Petrol (€) | Q2: Car Diesel (€) | R2: HGV Diesel (€) | S2: Train Person (€) | T2: Train Freight (€) | U2: IWW (€) | V2: Air (€) | W2: Car Petrol (€) | X2: Car Diesel (€) | Y2: HGV Diesel (€) | Z2: Train Person (€) | AA2: Train Freight (€) | AB2: IWW (€) | AC2: Air (€) | AD2: Car (€) | AE2: HGV (€) | AF2: Train Person (€) | AG2: Train Freight (€) | AH2: Car (€) | AI2: HGV (€) | AJ2: Train Person (€) | AK2: Train Freight (€)
A3: =A45 -> 18 | B3: =IF(B45='S00 Impact'!B2,B45,0) -> AL | C3: =-(C45-'S00 Impact'!C2) -> 2451879.6 | D3: =-(D45-'S00 Impact'!D2) -> 604553.75 | E3: =-(E45-'S00 Impact'!E2) -> 379041.52 | F3: =-(F45-'S00 Impact'!F2) -> 0 | G3: =-(G45-'S00 Impact'!G2) -> -1944887.6 | H3: =-(H45-'S00 Impact'!H2) -> -141355.56 | J3: =J45 -> 0 | K3: =K45 -> 3153 | L3: =-(L45-'S00 Impact'!L2) -> 5.2531332e+09 | N3: =A3 -> 18 | O3: =B3 -> AL | P3: =C3*Road!D3/100 -> 2574.4736 | Q3: =D3*Road!E3/100 -> 1795.5246 | R3: =E3*Road!H3/100 -> 8600.452 | S3: =G3*Rail!C3/100 -> -408.42639 | T3: =H3*Rail!D3/100 -> -26.857557 | U3: =F3*IWW!C3/100 -> 0 | W3: =C3*Road!F3/100 -> 23513.526 | X3: =D3*Road!G3/100 -> 5779.5339 | Y3: =E3*Road!I3/100 -> 16878.719 | Z3: =G3*Rail!E3/100 -> -2956.2291 | AA3: =H3*Rail!F3/100 -> -122.97934 | AB3: =F3*IWW!D3/100 -> 0 | AD3: =(C3+D3)*Road!J3/100 -> 12623.07 | AE3: =E3*Road!L3/100 -> 4976.8151 | AF3: =G3*Rail!G3/100 -> -1011.3415 | AG3: =H3*Rail!I3/100 -> -38.166002 | AH3: =(C3+D3)*Road!K3/100 -> 10391.874 | AI3: =E3*Road!M3/100 -> 11177.934 | AJ3: =G3*Rail!H3/100 -> -2820.087 | AK3: =H3*Rail!J3/100 -> -55.128669
A4: =A46 -> 18 | B4: =IF(B46='S00 Impact'!B3,B46,0) -> AT | C4: =-(C46-'S00 Impact'!C3) -> 35829404 | D4: =-(D46-'S00 Impact'!D3) -> 6777155.7 | E4: =-(E46-'S00 Impact'!E3) -> -19333791 | F4: =-(F46-'S00 Impact'!F3) -> -7312686.1 | G4: =-(G46-'S00 Impact'!G3) -> -1.2147369e+08 | H4: =-(H46-'S00 Impact'!H3) -> -67919974 | N4: =A4 -> 18 | O4: =B4 -> AT | P4: =C4*Road!D4/100 -> 59118.516 | Q4: =D4*Road!E4/100 -> 43983.741 | R4: =E4*Road!H4/100 -> -1002457 | S4: =G4*Rail!C4/100 -> -38871.581 | T4: =H4*Rail!D4/100 -> -7471.1971 | U4: =F4*IWW!C4/100 -> -184352.82 | W4: =C4*Road!F4/100 -> 343962.28 | X4: =D4*Road!G4/100 -> 64721.837 | Y4: =E4*Road!I4/100 -> -860933.69 | Z4: =G4*Rail!E4/100 -> -184640.01 | AA4: =H4*Rail!F4/100 -> -59090.377 | AB4: =F4*IWW!D4/100 -> -19890.506 | AD4: =(C4+D4)*Road!J4/100 -> 213032.8 | AE4: =E4*Road!L4/100 -> -971329.64 | AF4: =G4*Rail!G4/100 -> -136050.53 | AG4: =H4*Rail!I4/100 -> -21055.192 | AH4: =(C4+D4)*Road!K4/100 -> 303784.77 | AI4: =E4*Road!M4/100 -> -910041.52 | AJ4: =G4*Rail!H4/100 -> -138480.01 | AK4: =H4*Rail!J4/100 -> -95767.163
A5: =A47 -> 18 | B5: =IF(B47='S00 Impact'!B4,B47,0) -> BA | C5: =-(C47-'S00 Impact'!C4) -> 10596379 | D5: =-(D47-'S00 Impact'!D4) -> 2467225.5 | E5: =-(E47-'S00 Impact'!E4) -> 12076288 | F5: =-(F47-'S00 Impact'!F4) -> -7039800.4 | G5: =-(G47-'S00 Impact'!G4) -> -4640961.7 | H5: =-(H47-'S00 Impact'!H4) -> 790685.9 | N5: =A5 -> 18 | O5: =B5 -> BA | P5: =C5*Road!D5/100 -> 9536.7409 | Q5: =D5*Road!E5/100 -> 6316.0972 | R5: =E5*Road!H5/100 -> 235487.61 | S5: =G5*Rail!C5/100 -> -3619.9501 | T5: =H5*Rail!D5/100 -> 355.80865 | U5: =F5*IWW!C5/100 -> -132066.66 | W5: =C5*Road!F5/100 -> 101619.27 | X5: =D5*Road!G5/100 -> 23586.676 | Y5: =E5*Road!I5/100 -> 537757.08 | Z5: =G5*Rail!E5/100 -> -7054.2618 | AA5: =H5*Rail!F5/100 -> 687.89673 | AB5: =F5*IWW!D5/100 -> -19148.257 | AD5: =(C5+D5)*Road!J5/100 -> 46375.795 | AE5: =E5*Road!L5/100 -> 136220.52 | AF5: =G5*Rail!G5/100 -> -3434.3117 | AG5: =H5*Rail!I5/100 -> 213.48519 | AH5: =(C5+D5)*Road!K5/100 -> 38276.36 | AI5: =E5*Road!M5/100 -> 306013.13 | AJ5: =G5*Rail!H5/100 -> -6218.8887 | AK5: =H5*Rail!J5/100 -> 300.46064
A6: =A48 -> 18 | B6: =IF(B48='S00 Impact'!B5,B48,0) -> BE | C6: =-(C48-'S00 Impact'!C5) -> 43234600 | D6: =-(D48-'S00 Impact'!D5) -> 3000224.5 | E6: =-(E48-'S00 Impact'!E5) -> 1263651.1 | F6: =-(F48-'S00 Impact'!F5) -> -600783.54 | G6: =-(G48-'S00 Impact'!G5) -> -2.7820757e+08 | H6: =-(H48-'S00 Impact'!H5) -> 5462992.3 | N6: =A6 -> 18 | O6: =B6 -> BE | P6: =C6*Road!D6/100 -> 69607.707 | Q6: =D6*Road!E6/100 -> 13861.037 | R6: =E6*Road!H6/100 -> 43810.785 | S6: =G6*Rail!C6/100 -> -1018239.7 | T6: =H6*Rail!D6/100 -> 11526.914 | U6: =F6*IWW!C6/100 -> -13433.52 | W6: =C6*Road!F6/100 -> 415052.16 | X6: =D6*Road!G6/100 -> 28652.144 | Y6: =E6*Road!I6/100 -> 56270.385 | Z6: =G6*Rail!E6/100 -> -422875.5 | AA6: =H6*Rail!F6/100 -> 4752.8033 | AB6: =F6*IWW!D6/100 -> -1634.1312 | AD6: =(C6+D6)*Road!J6/100 -> 264925.55 | AE6: =E6*Road!L6/100 -> 122940.62 | AF6: =G6*Rail!G6/100 -> -197527.37 | AG6: =H6*Rail!I6/100 -> 1365.7481 | AH6: =(C6+D6)*Road!K6/100 -> 304225.15 | AI6: =E6*Road!M6/100 -> 54905.642 | AJ6: =G6*Rail!H6/100 -> -111283.03 | AK6: =H6*Rail!J6/100 -> 3605.5749
A7: =A49 -> 18 | B7: =IF(B49='S00 Impact'!B6,B49,0) -> BG | C7: =-(C49-'S00 Impact'!C6) -> 57883479 | D7: =-(D49-'S00 Impact'!D6) -> 10123959 | E7: =-(E49-'S00 Impact'!E6) -> 11069718 | F7: =-(F49-'S00 Impact'!F6) -> -3232595.7 | G7: =-(G49-'S00 Impact'!G6) -> -1.5747971e+08 | H7: =-(H49-'S00 Impact'!H6) -> -11883526 | N7: =A7 -> 18 | O7: =B7 -> BG | P7: =C7*Road!D7/100 -> 46306.783 | Q7: =D7*Road!E7/100 -> 22981.387 | R7: =E7*Road!H7/100 -> 192059.61 | S7: =G7*Rail!C7/100 -> -74015.464 | T7: =H7*Rail!D7/100 -> -3208.5522 | U7: =F7*IWW!C7/100 -> -15193.2 | W7: =C7*Road!F7/100 -> 555102.57 | X7: =D7*Road!G7/100 -> 96785.049 | Y7: =E7*Road!I7/100 -> 492934.54 | Z7: =G7*Rail!E7/100 -> -239369.16 | AA7: =H7*Rail!F7/100 -> -10338.668 | AB7: =F7*IWW!D7/100 -> -8792.6602 | AD7: =(C7+D7)*Road!J7/100 -> 214223.43 | AE7: =E7*Road!L7/100 -> 111139.97 | AF7: =G7*Rail!G7/100 -> -133857.75 | AG7: =H7*Rail!I7/100 -> -3208.5522 | AH7: =(C7+D7)*Road!K7/100 -> 176819.34 | AI7: =E7*Road!M7/100 -> 249622.14 | AJ7: =G7*Rail!H7/100 -> -338581.38 | AK7: =H7*Rail!J7/100 -> -3565.0579
A8: =A50 -> 18 | B8: =IF(B50='S00 Impact'!B7,B50,0) -> BY | C8: =-(C50-'S00 Impact'!C7) -> 1.2483832e+08 | D8: =-(D50-'S00 Impact'!D7) -> 27713498 | E8: =-(E50-'S00 Impact'!E7) -> 17929922 | F8: =-(F50-'S00 Impact'!F7) -> 0 | G8: =-(G50-'S00 Impact'!G7) -> 40830437 | H8: =-(H50-'S00 Impact'!H7) -> 1.9183897e+08 | N8: =A8 -> 18 | O8: =B8 -> BY | P8: =C8*Road!D8/100 -> 126086.71 | Q8: =D8*Road!E8/100 -> 78983.47 | R8: =E8*Road!H8/100 -> 390334.41 | S8: =G8*Rail!C8/100 -> 30214.523 | T8: =H8*Rail!D8/100 -> 84409.148 | U8: =F8*IWW!C8/100 -> 0 | W8: =C8*Road!F8/100 -> 1197199.5 | X8: =D8*Road!G8/100 -> 264941.04 | Y8: =E8*Road!I8/100 -> 798419.44 | Z8: =G8*Rail!E8/100 -> 62062.264 | AA8: =H8*Rail!F8/100 -> 166899.91 | AB8: =F8*IWW!D8/100 -> 0 | AD8: =(C8+D8)*Road!J8/100 -> 604105.21 | AE8: =E8*Road!L8/100 -> 225737.72 | AF8: =G8*Rail!G8/100 -> 28989.61 | AG8: =H8*Rail!I8/100 -> 51796.523 | AH8: =(C8+D8)*Road!K8/100 -> 498844.45 | AI8: =E8*Road!M8/100 -> 507237.5 | AJ8: =G8*Rail!H8/100 -> 12657.435 | AK8: =H8*Rail!J8/100 -> 65225.251
A9: =A51 -> 18 | B9: =IF(B51='S00 Impact'!B8,B51,0) -> CH | C9: =-(C51-'S00 Impact'!C8) -> 5751604.5 | D9: =-(D51-'S00 Impact'!D8) -> -3106527.9 | E9: =-(E51-'S00 Impact'!E8) -> 3812970.7 | F9: =-(F51-'S00 Impact'!F8) -> 153.58459 | G9: =-(G51-'S00 Impact'!G8) -> -18942852 | H9: =-(H51-'S00 Impact'!H8) -> 15463155 | N9: =A9 -> 18 | O9: =B9 -> CH | P9: =C9*Road!D9/100 -> 17772.458 | Q9: =D9*Road!E9/100 -> -27119.988 | R9: =E9*Road!H9/100 -> 254020.11 | S9: =G9*Rail!C9/100 -> -7577.1409 | T9: =H9*Rail!D9/100 -> 3556.5255 | U9: =F9*IWW!C9/100 -> 2.8812469 | W9: =C9*Road!F9/100 -> 55157.887 | X9: =D9*Road!G9/100 -> -29698.406 | Y9: =E9*Road!I9/100 -> 169791.59 | Z9: =G9*Rail!E9/100 -> -28793.135 | AA9: =H9*Rail!F9/100 -> 13452.944 | AB9: =F9*IWW!D9/100 -> 0.41775008 | AD9: =(C9+D9)*Road!J9/100 -> 32031.879 | AE9: =E9*Road!L9/100 -> 146990.02 | AF9: =G9*Rail!G9/100 -> -26141.136 | AG9: =H9*Rail!I9/100 -> 2164.8416 | AH9: =(C9+D9)*Road!K9/100 -> 26450.767 | AI9: =E9*Road!M9/100 -> 330127 | AJ9: =G9*Rail!H9/100 -> -41674.275 | AK9: =H9*Rail!J9/100 -> 9123.2612
A10: =A52 -> 18 | B10: =IF(B52='S00 Impact'!B9,B52,0) -> CZ | C10: =-(C52-'S00 Impact'!C9) -> 10225604 | D10: =-(D52-'S00 Impact'!D9) -> -516790.8 | E10: =-(E52-'S00 Impact'!E9) -> -5429515.4 | F10: =-(F52-'S00 Impact'!F9) -> -5569.7123 | G10: =-(G52-'S00 Impact'!G9) -> -4.3699512e+08 | H10: =-(H52-'S00 Impact'!H9) -> -40779867 | N10: =A10 -> 18 | O10: =B10 -> CZ | P10: =C10*Road!D10/100 -> 14827.126 | Q10: =D10*Road!E10/100 -> -2139.5139 | R10: =E10*Road!H10/100 -> -171681.28 | S10: =G10*Rail!C10/100 -> -353966.05 | T10: =H10*Rail!D10/100 -> -17535.343 | U10: =F10*IWW!C10/100 -> -104.4878 | W10: =C10*Road!F10/100 -> 98165.797 | X10: =D10*Road!G10/100 -> -4935.3521 | Y10: =E10*Road!I10/100 -> -241776.32 | Z10: =G10*Rail!E10/100 -> -664232.58 | AA10: =H10*Rail!F10/100 -> -35478.484 | AB10: =F10*IWW!D10/100 -> -15.149617 | AD10: =(C10+D10)*Road!J10/100 -> 21553.565 | AE10: =E10*Road!L10/100 -> -105712.66 | AF10: =G10*Rail!G10/100 -> -240347.32 | AG10: =H10*Rail!I10/100 -> -11418.363 | AH10: =(C10+D10)*Road!K10/100 -> 47961.536 | AI10: =E10*Road!M10/100 -> -262842.84 | AJ10: =G10*Rail!H10/100 -> -436995.12 | AK10: =H10*Rail!J10/100 -> -52198.23
A11: =A53 -> 18 | B11: =IF(B53='S00 Impact'!B10,B53,0) -> DE | C11: =-(C53-'S00 Impact'!C10) -> 3.7931243e+08 | D11: =-(D53-'S00 Impact'!D10) -> 51771269 | E11: =-(E53-'S00 Impact'!E10) -> 167028.15 | F11: =-(F53-'S00 Impact'!F10) -> -29109520 | G11: =-(G53-'S00 Impact'!G10) -> -3.2735189e+09 | H11: =-(H53-'S00 Impact'!H10) -> 5.2324278e+08 | N11: =A11 -> 18 | O11: =B11 -> DE | P11: =C11*Road!D11/100 -> 561382.4 | Q11: =D11*Road!E11/100 -> 316840.16 | R11: =E11*Road!H11/100 -> 8224.4659 | S11: =G11*Rail!C11/100 -> -1145731.6 | T11: =H11*Rail!D11/100 -> 104648.56 | U11: =F11*IWW!C11/100 -> -707070.24 | W11: =C11*Road!F11/100 -> 3641399.3 | X11: =D11*Road!G11/100 -> 494415.62 | Y11: =E11*Road!I11/100 -> 7437.7634 | Z11: =G11*Rail!E11/100 -> -4975748.7 | AA11: =H11*Rail!F11/100 -> 455221.21 | AB11: =F11*IWW!D11/100 -> -79177.895 | AD11: =(C11+D11)*Road!J11/100 -> 1638118.1 | AE11: =E11*Road!L11/100 -> 6435.5945 | AF11: =G11*Rail!G11/100 -> -2782491 | AG11: =H11*Rail!I11/100 -> 141275.55 | AH11: =(C11+D11)*Road!K11/100 -> 2517528.8 | AI11: =E11*Road!M11/100 -> 6440.6053 | AJ11: =G11*Rail!H11/100 -> -4681132 | AK11: =H11*Rail!J11/100 -> 198832.25
A12: =A54 -> 18 | B12: =IF(B54='S00 Impact'!B11,B54,0) -> DK | C12: =-(C54-'S00 Impact'!C11) -> 2.0047856e+08 | D12: =-(D54-'S00 Impact'!D11) -> 21329801 | E12: =-(E54-'S00 Impact'!E11) -> -21217441 | F12: =-(F54-'S00 Impact'!F11) -> 0 | G12: =-(G54-'S00 Impact'!G11) -> -1.1613456e+09 | H12: =-(H54-'S00 Impact'!H11) -> -6.3868046e+08 | N12: =A12 -> 18 | O12: =B12 -> DK | P12: =C12*Road!D12/100 -> 276660.41 | Q12: =D12*Road!E12/100 -> 77853.772 | R12: =E12*Road!H12/100 -> -586025.73 | S12: =G12*Rail!C12/100 -> -534218.99 | T12: =H12*Rail!D12/100 -> -197990.94 | U12: =F12*IWW!C12/100 -> 0 | W12: =C12*Road!F12/100 -> 1924594.2 | X12: =D12*Road!G12/100 -> 203699.6 | Y12: =E12*Road!I12/100 -> -944812.66 | Z12: =G12*Rail!E12/100 -> -1765245.4 | AA12: =H12*Rail!F12/100 -> -555652 | AB12: =F12*IWW!D12/100 -> 0 | AD12: =(C12+D12)*Road!J12/100 -> 865052.6 | AE12: =E12*Road!L12/100 -> -760220.92 | AF12: =G12*Rail!G12/100 -> -661967.02 | AG12: =H12*Rail!I12/100 -> -197990.94 | AH12: =(C12+D12)*Road!K12/100 -> 1903115.7 | AI12: =E12*Road!M12/100 -> -1201543.7 | AJ12: =G12*Rail!H12/100 -> -615513.19 | AK12: =H12*Rail!J12/100 -> -817510.99
A13: =A55 -> 18 | B13: =IF(B55='S00 Impact'!B12,B55,0) -> EE | C13: =-(C55-'S00 Impact'!C12) -> 24903349 | D13: =-(D55-'S00 Impact'!D12) -> 4702633.6 | E13: =-(E55-'S00 Impact'!E12) -> 225285.32 | F13: =-(F55-'S00 Impact'!F12) -> 0 | G13: =-(G55-'S00 Impact'!G12) -> -3016497.2 | H13: =-(H55-'S00 Impact'!H12) -> 50325319 | N13: =A13 -> 18 | O13: =B13 -> EE | P13: =C13*Road!D13/100 -> 51549.931 | Q13: =D13*Road!E13/100 -> 27698.512 | R13: =E13*Road!H13/100 -> 10137.839 | S13: =G13*Rail!C13/100 -> -9592.4611 | T13: =H13*Rail!D13/100 -> 92095.334 | U13: =F13*IWW!C13/100 -> 0 | W13: =C13*Road!F13/100 -> 239072.15 | X13: =D13*Road!G13/100 -> 44910.151 | Y13: =E13*Road!I13/100 -> 10031.955 | Z13: =G13*Rail!E13/100 -> -4585.0758 | AA13: =H13*Rail!F13/100 -> 43783.028 | AB13: =F13*IWW!D13/100 -> 0 | AD13: =(C13+D13)*Road!J13/100 -> 66613.46 | AE13: =E13*Road!L13/100 -> 6242.6562 | AF13: =G13*Rail!G13/100 -> -2141.713 | AG13: =H13*Rail!I13/100 -> 17110.608 | AH13: =(C13+D13)*Road!K13/100 -> 208130.05 | AI13: =E13*Road!M13/100 -> 15517.653 | AJ13: =G13*Rail!H13/100 -> -1146.2689 | AK13: =H13*Rail!J13/100 -> 99644.132
A14: =A56 -> 18 | B14: =IF(B56='S00 Impact'!B13,B56,0) -> ES | C14: =-(C56-'S00 Impact'!C13) -> -89989007 | D14: =-(D56-'S00 Impact'!D13) -> -52344148 | E14: =-(E56-'S00 Impact'!E13) -> 5371809.5 | F14: =-(F56-'S00 Impact'!F13) -> 0 | G14: =-(G56-'S00 Impact'!G13) -> -1.4756207e+08 | H14: =-(H56-'S00 Impact'!H13) -> 3169759.1 | N14: =A14 -> 18 | O14: =B14 -> ES | P14: =C14*Road!D14/100 -> -152981.31 | Q14: =D14*Road!E14/100 -> -178493.55 | R14: =E14*Road!H14/100 -> 130696.12 | S14: =G14*Rail!C14/100 -> -48695.482 | T14: =H14*Rail!D14/100 -> 602.25423 | U14: =F14*IWW!C14/100 -> 0 | W14: =C14*Road!F14/100 -> -863894.47 | X14: =D14*Road!G14/100 -> -499886.62 | Y14: =E14*Road!I14/100 -> 239206.68 | Z14: =G14*Rail!E14/100 -> -224294.34 | AA14: =H14*Rail!F14/100 -> 2757.6904 | AB14: =F14*IWW!D14/100 -> 0 | AD14: =(C14+D14)*Road!J14/100 -> -641922.53 | AE14: =E14*Road!L14/100 -> 26644.175 | AF14: =G14*Rail!G14/100 -> -94439.723 | AG14: =H14*Rail!I14/100 -> 855.83496 | AH14: =(C14+D14)*Road!K14/100 -> -816992.31 | AI14: =E14*Road!M14/100 -> 203537.86 | AJ14: =G14*Rail!H14/100 -> -240526.17 | AK14: =H14*Rail!J14/100 -> 919.23014
A15: =A57 -> 18 | B15: =IF(B57='S00 Impact'!B14,B57,0) -> FI | C15: =-(C57-'S00 Impact'!C14) -> 1.5267848e+08 | D15: =-(D57-'S00 Impact'!D14) -> 23915602 | E15: =-(E57-'S00 Impact'!E14) -> -2804718.5 | F15: =-(F57-'S00 Impact'!F14) -> 0 | G15: =-(G57-'S00 Impact'!G14) -> 25655821 | H15: =-(H57-'S00 Impact'!H14) -> -35155266 | N15: =A15 -> 18 | O15: =B15 -> FI | P15: =C15*Road!D15/100 -> 293142.68 | Q15: =D15*Road!E15/100 -> 130579.19 | R15: =E15*Road!H15/100 -> -116928.71 | S15: =G15*Rail!C15/100 -> 9492.6537 | T15: =H15*Rail!D15/100 -> -12304.343 | U15: =F15*IWW!C15/100 -> 0 | W15: =C15*Road!F15/100 -> 1465713.4 | X15: =D15*Road!G15/100 -> 228394 | Y15: =E15*Road!I15/100 -> -124894.12 | Z15: =G15*Rail!E15/100 -> 38996.848 | AA15: =H15*Rail!F15/100 -> -30585.082 | AB15: =F15*IWW!D15/100 -> 0 | AD15: =(C15+D15)*Road!J15/100 -> 798205.24 | AE15: =E15*Road!L15/100 -> -71997.124 | AF15: =G15*Rail!G15/100 -> 23859.913 | AG15: =H15*Rail!I15/100 -> -15116.764 | AH15: =(C15+D15)*Road!K15/100 -> 1149627.5 | AI15: =E15*Road!M15/100 -> -178997.14 | AJ15: =G15*Rail!H15/100 -> 28477.961 | AK15: =H15*Rail!J15/100 -> -46756.504
... A41: =A83 -> 18 | B41: =IF(B83='S00 Impact'!B40,B83,0) -> YU | C41: =-(C83-'S00 Impact'!C40) -> 22063387 | D41: =-(D83-'S00 Impact'!D40) -> 1172699.8 | E41: =-(E83-'S00 Impact'!E40) -> 12121514 | F41: =-(F83-'S00 Impact'!F40) -> -16193663 | G41: =-(G83-'S00 Impact'!G40) -> -3.7154234e+08 | H41: =-(H83-'S00 Impact'!H40) -> 23584475 | N41: =A41 -> 18 | O41: =B41 -> YU | P41: =C41*Road!D41/100 -> 19857.048 | Q41: =D41*Road!E41/100 -> 3002.1115 | R41: =E41*Road!H41/100 -> 236369.52 | S41: =G41*Rail!C41/100 -> -156047.78 | T41: =H41*Rail!D41/100 -> 5660.2741 | U41: =F41*IWW!C41/100 -> -205983.4 | W41: =C41*Road!F41/100 -> 211587.88 | X41: =D41*Road!G41/100 -> 11211.01 | Y41: =E41*Road!I41/100 -> 539771.02 | Z41: =G41*Rail!E41/100 -> -564744.36 | AA41: =H41*Rail!F41/100 -> 20518.493 | AB41: =F41*IWW!D41/100 -> -44046.764 | AD41: =(C41+D41)*Road!J41/100 -> 82488.108 | AE41: =E41*Road!L41/100 -> 136730.68 | AF41: =G41*Rail!G41/100 -> -263795.06 | AG41: =H41*Rail!I41/100 -> 6367.8083 | AH41: =(C41+D41)*Road!K41/100 -> 68081.734 | AI41: =E41*Road!M41/100 -> 307159.17 | AJ41: =G41*Rail!H41/100 -> -141186.09 | AK41: =H41*Rail!J41/100 -> 11556.393
N42: =N41 -> 18 | O42: Total | P42: =SUM(P3:P41) -> 4014588.5 | Q42: =SUM(Q3:Q41) -> 1457059.1 | R42: =SUM(R3:R41) -> 3151437.1 | S42: =SUM(S3:S41) -> -7703545.1 | T42: =SUM(T3:T41) -> 257484.26 | U42: =SUM(U3:U41) -> -2252451.6 | V42: =L3*Air!C3/100 -> 36141557 | W42: =SUM(W3:W41) -> 24636428 | X42: =SUM(X3:X41) -> 3141235.9 | Y42: =SUM(Y3:Y41) -> 8494370.4 | Z42: =SUM(Z3:Z41) -> -19961131 | AA42: =SUM(AA3:AA41) -> 375607.2 | AB42: =SUM(AB3:AB41) -> -316860.73 | AC42: =L3*Air!D3/100 -> 26213135 | AD42: =SUM(AD3:AD41) -> 10096386 | AE42: =SUM(AE3:AE41) -> 1889881.8 | AF42: =SUM(AF3:AF41) -> -9872213.7 | AG42: =SUM(AG3:AG41) -> 159527.76 | AH42: =SUM(AH3:AH41) -> 16659967 | AI42: =SUM(AI3:AI41) -> 6537424.6 | AJ42: =SUM(AJ3:AJ41) -> -13160894 | AK42: =SUM(AK3:AK41) -> -88179.258 | AL42: =SUM(P42:AK42) -> 89870814
V43: =SUM(P42:V42) -> 35066129 | AC43: =SUM(W42:AC42) -> 42582785 | AG43: =SUM(AD42:AG42) -> 2273581.6 | AK43: =SUM(AH42:AK42) -> 9948318.7
A44: scenario | B44: CountryCode | C44: vkm_petrol_Carpassenger | D44: vkm_diesel_Carpassenger | E44: vkm_hgv_Freight | F44: Total_IWW_TonKM | G44: PersonKM_RailPassenger | H44: TonKM_RailFreight | J44: _TYPE_ | K44: _FREQ_ | L44: personkm_Air
A45: 18 | B45: AL | C45: 2.1956147e+09 | D45: 5.4315239e+08 | E45: 7.7684216e+08 | G45: 1.2891592e+08 | H45: 5.9571987e+08 | J45: 0 | K45: 3153 | L45: 8.3404067e+11
A46: 18 | B46: AT | C46: 4.3050142e+10 | D46: 2.7043005e+10 | E46: 6.9046525e+09 | F46: 7.1137375e+09 | G46: 1.5981818e+10 | H46: 2.4827695e+10
A47: 18 | B47: BA | C47: 5.0172008e+09 | D47: 1.2311149e+09 | E47: 8.3141731e+08 | F47: 7.4575755e+08 | G47: 6.0463933e+08 | H47: 1.2076635e+09
A48: 18 | B48: BE | C48: 4.2854573e+10 | D48: 3.255079e+10 | E48: 8.4065481e+09 | F48: 9.5892565e+09 | G48: 1.4431117e+10 | H48: 9.8095741e+09
A49: 18 | B49: BG | C49: 2.7913536e+10 | D49: 6.8249933e+09 | E49: 3.8296285e+09 | F49: 2.1038671e+09 | G49: 1.716744e+10 | H49: 2.3021706e+10
A50: 18 | B50: BY | C50: 1.9108171e+10 | D50: 4.6086762e+09 | E50: 1.041729e+10 | G50: 7.6707819e+09 | H50: 2.6759627e+10
A51: 18 | B51: CH | C51: 3.9940785e+10 | D51: 5.7160437e+09 | E51: 3.6396937e+09 | F51: 38941248 | G51: 1.1697914e+10 | H51: 1.1541841e+10
A52: 18 | B52: CZ | C52: 3.1720278e+10 | D52: 6.8910186e+09 | E52: 8.5531175e+09 | F52: 45307736 | G52: 9.7977684e+09 | H52: 3.5408072e+10
A53: 18 | B53: DE | C53: 3.796303e+11 | D53: 8.8620139e+10 | E53: 4.6527512e+10 | F53: 7.5713858e+10 | G53: 1.1817319e+11 | H53: 1.0958713e+11
A54: 18 | B54: DK | C54: 3.7044288e+10 | D54: 3.8445169e+09 | E54: 7.263948e+09 | G54: 7.546094e+09 | H54: 4.0336909e+09
A55: 18 | B55: EE | C55: 3.3317456e+09 | D55: 6.0494028e+08 | E55: 1.8197433e+09 | G55: 2.9325813e+08 | H55: 3.0945251e+10
A56: 18 | B56: ES | C56: 1.7619575e+11 | D56: 9.451743e+10 | E56: 4.8183761e+10 | G56: 2.9657767e+10 | H56: 2.4313188e+10
A57: 18 | B57: FI | C57: 2.9507807e+10 | D57: 4.3056887e+09 | E57: 5.6567735e+09 | G57: 7.6294364e+09 | H57: 2.2140296e+10
A58: 18 | B58: FR | C58: 2.4535858e+11 | D58: 1.6776254e+11 | E58: 4.4055771e+10 | F58: 1.2023671e+10 | G58: 9.5639744e+10 | H58: 5.5803695e+10
A59: 18 | B59: GR | C59: 2.7389714e+10 | D59: 6.7813187e+09 | E59: 6.3030834e+09 | G59: 2.9912466e+09 | H59: 1.427294e+09
A60: 18 | B60: HR | C60: 2.2415366e+10 | D60: 5.5704803e+09 | E60: 2.6630585e+09 | F60: 3.1495224e+08 | G60: 9.1239252e+09 | H60: 7.4896544e+09
A61: 18 | B61: HU | C61: 2.955011e+10 | D61: 6.0743689e+09 | E61: 5.3948148e+09 | F61: 1.119397e+10 | G61: 1.5829424e+10 | H61: 2.3839101e+10
A62: 18 | B62: IE | C62: 2.7572346e+10 | D62: 4.7711418e+09 | E62: 4.8680381e+09 | G62: 1.9491378e+09 | H62: 6.5544061e+08
A63: 18 | B63: IT | C63: 2.1147657e+11 | D63: 5.5751141e+10 | E63: 3.6814112e+10 | G63: 5.1143746e+10 | H63: 3.5736246e+10
A64: 18 | B64: LI | C64: 80226143 | D64: 23688912 | E64: 17912009 | G64: 12955243 | H64: 28650359
A65: 18 | B65: LT | C65: 8.5017361e+09 | D65: 2.0274564e+09 | E65: 4.6451365e+09 | F65: 1945882.9 | G65: 1.3250521e+10 | H65: 3.6944675e+10
A66: 18 | B66: LU | C66: 5.5508298e+09 | D66: 2.6303923e+09 | E66: 9.0201654e+08 | G66: 1.586163e+08 | H66: 5.7528533e+08
A67: 18 | B67: LV | C67: 7.2082277e+09 | D67: 1.4354039e+09 | E67: 2.6117915e+09 | F67: 3057704.3 | G67: 8.1070169e+09 | H67: 5.0313683e+10
A68: 18 | B68: MD | C68: 5.5992948e+09 | D68: 1.3822934e+09 | E68: 1.6175281e+09 | G68: 1.4122896e+09 | H68: 3.4626235e+09
A69: 18 | B69: ME | C69: 1.5182764e+09 | D69: 3.7551288e+08 | E69: 1.893941e+08 | G69: 1.3847345e+08 | H69: 1.8997366e+09
A70: 18 | B70: MK | C70: 4.7933207e+09 | D70: 1.1873e+09 | E70: 1.3554279e+09 | G70: 7.6200545e+08 | H70: 4.1492093e+08
A71: 18 | B71: NL | C71: 9.5214823e+10 | D71: 1.9247925e+10 | E71: 1.0287327e+10 | F71: 3.9740944e+10 | G71: 1.2636891e+10 | H71: 6.6047362e+09
A72: 18 | B72: NO | C72: 4.0174612e+10 | D72: 9.3980177e+09 | E72: 3.8568419e+09 | G72: 5.4573127e+09 | H72: 4.7585702e+09
A73: 18 | B73: PL | C73: 9.5897158e+10 | D73: 1.8867804e+10 | E73: 3.0158649e+10 | F73: 8.8163562e+08 | G73: 5.4523318e+10 | H73: 1.3153816e+11
A74: 18 | B74: PT | C74: 3.7354777e+10 | D74: 9.7746504e+09 | E74: 6.719833e+09 | G74: 4.7516246e+09 | H74: 4.6554887e+09
A75: 18 | B75: RO | C75: 3.8512546e+10 | D75: 9.413107e+09 | E75: 1.3978561e+10 | F75: 2.1638933e+10 | G75: 1.1425436e+10 | H75: 5.7876034e+10
A76: 18 | B76: RU | C76: 1.5801789e+11 | D76: 3.8775666e+10 | E76: 9.0478849e+10 | G76: 1.0581425e+11 | H76: 2.3282761e+11
A77: 18 | B77: SE | C77: 5.7048215e+10 | D77: 4.4381932e+09 | E77: 8.3637187e+09 | G77: 2.0524734e+10 | H77: 3.5111248e+10
A78: 18 | B78: SI | C78: 1.1786522e+10 | D78: 3.0868302e+09 | E78: 2.3263193e+09 | G78: 5.7318524e+09 | H78: 9.9948993e+09
A79: 18 | B79: SK | C79: 1.2740194e+10 | D79: 3.0891989e+09 | E79: 4.072366e+09 | F79: 7.0694743e+08 | G79: 2.6185154e+09 | H79: 2.3560448e+10
A80: 18 | B80: TR | C80: 1.1401023e+11 | D80: 2.7964496e+10 | E80: 1.1224749e+10 | G80: 5.0965875e+10 | H80: 1.3376004e+10
A81: 18 | B81: UA | C81: 7.3846149e+10 | D81: 1.8001269e+10 | E81: 2.2528714e+10 | G81: 3.5846395e+10 | H81: 7.7291628e+10
A82: 18 | B82: UK | C82: 3.3044309e+11 | D82: 7.5055482e+10 | E82: 2.6286504e+10 | F82: 3.2638791e+08 | G82: 4.8795116e+10 | H82: 3.7378651e+10
A83: 18 | B83: YU | C83: 2.051531e+10 | D83: 5.0176407e+09 | E83: 2.1319026e+09 | F83: 1.3228717e+10 | G83: 2.0943726e+10 | H83: 9.3162949e+09

Sheet S20 Impact
A1: Difference from Baseline | O1: Type | P1: Air Pollution | Q1: Air Pollution | R1: Air Pollution | S1: Air Pollution | T1: Air Pollution | U1: Air Pollution | V1: Air Pollution | W1: Global Warming | X1: Global Warming | Y1: Global Warming | Z1: Global Warming | AA1: Global Warming | AB1: Global Warming | AC1: Global Warming | AD1: Accidents | AE1: Accidents | AF1: Accidents | AG1: Accidents | AH1: Noise | AI1: Noise | AJ1: Noise | AK1: Noise
A2: Scenario | B2: CountryCode | C2: vkm_petrol_Carpassenger | D2: vkm_diesel_Carpassenger | E2: vkm_hgv_Freight | F2: Total_IWW_TonKM | G2: PersonKM_RailPassenger | H2: TonKM_RailFreight | J2: _TYPE_ | K2: _FREQ_ | L2: personkm_Air | N2: Scenario | O2: CountryCode | P2: Car Petrol (€) | Q2: Car Diesel (€) | R2: HGV Diesel (€) | S2: Train Person (€) | T2: Train Freight (€) | U2: IWW (€) | V2: Air (€) | W2: Car Petrol (€) | X2: Car Diesel (€) | Y2: HGV Diesel (€) | Z2: Train Person (€) | AA2: Train Freight (€) | AB2: IWW (€) | AC2: Air (€) | AD2: Car (€) | AE2: HGV (€) | AF2: Train Person (€) | AG2: Train Freight (€) | AH2: Car (€) | AI2: HGV (€) | AJ2: Train Person (€) | AK2: Train Freight (€)
A3: =A45 -> 20 | B3: =IF(B45='S00 Impact'!B2,B45,0) -> AL | C3: =-(C45-'S00 Impact'!C2) -> -372484.23 | D3: =-(D45-'S00 Impact'!D2) -> -76136.722 | E3: =-(E45-'S00 Impact'!E2) -> 253566.76 | F3: =-(F45-'S00 Impact'!F2) -> 0 | G3: =-(G45-'S00 Impact'!G2) -> -2137819 | H3: =-(H45-'S00 Impact'!H2) -> -75300.951 | J3: =J45 -> 0 | K3: =K45 -> 3153 | L3: =-(L45-'S00 Impact'!L2) -> 8.3971637e+08 | N3: =A3 -> 20 | O3: =B3 -> AL | P3: =C3*Road!D3/100 -> -391.10844 | Q3: =D3*Road!E3/100 -> -226.12607 | R3: =E3*Road!H3/100 -> 5753.4298 | S3: =G3*Rail!C3/100 -> -448.942 | T3: =H3*Rail!D3/100 -> -14.307181 | U3: =F3*IWW!C3/100 -> 0 | W3: =C3*Road!F3/100 -> -3572.1238 | X3: =D3*Road!G3/100 -> -727.86707 | Y3: =E3*Road!I3/100 -> 11291.328 | Z3: =G3*Rail!E3/100 -> -3249.4849 | AA3: =H3*Rail!F3/100 -> -65.511828 | AB3: =F3*IWW!D3/100 -> 0 | AD3: =(C3+D3)*Road!J3/100 -> -1852.8045 | AE3: =E3*Road!L3/100 -> 3329.3316 | AF3: =G3*Rail!G3/100 -> -1111.6659 | AG3: =H3*Rail!I3/100 -> -20.331257 | AH3: =(C3+D3)*Road!K3/100 -> -1525.3112 | AI3: =E3*Road!M3/100 -> 7477.6838 | AJ3: =G3*Rail!H3/100 -> -3099.8376 | AK3: =H3*Rail!J3/100 -> -29.367371
A4: =A46 -> 20 | B4: =IF(B46='S00 Impact'!B3,B46,0) -> AT | C4: =-(C46-'S00 Impact'!C3) -> 13167566 | D4: =-(D46-'S00 Impact'!D3) -> 1583800.4 | E4: =-(E46-'S00 Impact'!E3) -> -18006333 | F4: =-(F46-'S00 Impact'!F3) -> -2599873.2 | G4: =-(G46-'S00 Impact'!G3) -> 5236356.9 | H4: =-(H46-'S00 Impact'!H3) -> 1.0468054e+08 | N4: =A4 -> 20 | O4: =B4 -> AT | P4: =C4*Road!D4/100 -> 21726.484 | Q4: =D4*Road!E4/100 -> 10278.865 | R4: =E4*Road!H4/100 -> -933628.37 | S4: =G4*Rail!C4/100 -> 1675.6342 | T4: =H4*Rail!D4/100 -> 11514.86 | U4: =F4*IWW!C4/100 -> -65542.803 | W4: =C4*Road!F4/100 -> 126408.63 | X4: =D4*Road!G4/100 -> 15125.294 | Y4: =E4*Road!I4/100 -> -801822.01 | Z4: =G4*Rail!E4/100 -> 7959.2624 | AA4: =H4*Rail!F4/100 -> 91072.071 | AB4: =F4*IWW!D4/100 -> -7071.6551 | AD4: =(C4+D4)*Road!J4/100 -> 73756.831 | AE4: =E4*Road!L4/100 -> -904638.17 | AF4: =G4*Rail!G4/100 -> 5864.7197 | AG4: =H4*Rail!I4/100 -> 32450.968 | AH4: =(C4+D4)*Road!K4/100 -> 105177.24 | AI4: =E4*Road!M4/100 -> -847558.1 | AJ4: =G4*Rail!H4/100 -> 5969.4468 | AK4: =H4*Rail!J4/100 -> 147599.56
A5: =A47 -> 20 | B5: =IF(B47='S00 Impact'!B4,B47,0) -> BA | C5: =-(C47-'S00 Impact'!C4) -> -3372065.4 | D5: =-(D47-'S00 Impact'!D4) -> -688309.84 | E5: =-(E47-'S00 Impact'!E4) -> -3897679.7 | F5: =-(F47-'S00 Impact'!F4) -> 420656.96 | G5: =-(G47-'S00 Impact'!G4) -> 3664850.7 | H5: =-(H47-'S00 Impact'!H4) -> 1945256.1 | N5: =A5 -> 20 | O5: =B5 -> BA | P5: =C5*Road!D5/100 -> -3034.8589 | Q5: =D5*Road!E5/100 -> -1762.0732 | R5: =E5*Road!H5/100 -> -76004.755 | S5: =G5*Rail!C5/100 -> 2858.5836 | T5: =H5*Rail!D5/100 -> 875.36525 | U5: =F5*IWW!C5/100 -> 7891.5246 | W5: =C5*Road!F5/100 -> -32338.107 | X5: =D5*Road!G5/100 -> -6580.2421 | Y5: =E5*Road!I5/100 -> -173563.68 | Z5: =G5*Rail!E5/100 -> 5570.5731 | AA5: =H5*Rail!F5/100 -> 1692.3728 | AB5: =F5*IWW!D5/100 -> 1144.1869 | AD5: =(C5+D5)*Road!J5/100 -> -14414.332 | AE5: =E5*Road!L5/100 -> -43965.827 | AF5: =G5*Rail!G5/100 -> 2711.9895 | AG5: =H5*Rail!I5/100 -> 525.21915 | AH5: =(C5+D5)*Road!K5/100 -> -11896.9 | AI5: =E5*Road!M5/100 -> -98767.204 | AJ5: =G5*Rail!H5/100 -> 4910.9 | AK5: =H5*Rail!J5/100 -> 739.19732
A6: =A48 -> 20 | B6: =IF(B48='S00 Impact'!B5,B48,0) -> BE | C6: =-(C48-'S00 Impact'!C5) -> 40893458 | D6: =-(D48-'S00 Impact'!D5) -> 3495516.4 | E6: =-(E48-'S00 Impact'!E5) -> 5158469 | F6: =-(F48-'S00 Impact'!F5) -> -1633777.8 | G6: =-(G48-'S00 Impact'!G5) -> -1.159959e+08 | H6: =-(H48-'S00 Impact'!H5) -> 22464688 | N6: =A6 -> 20 | O6: =B6 -> BE | P6: =C6*Road!D6/100 -> 65838.467 | Q6: =D6*Road!E6/100 -> 16149.286 | R6: =E6*Road!H6/100 -> 178844.12 | S6: =G6*Rail!C6/100 -> -424545 | T6: =H6*Rail!D6/100 -> 47400.492 | U6: =F6*IWW!C6/100 -> -36531.271 | W6: =C6*Road!F6/100 -> 392577.19 | X6: =D6*Road!G6/100 -> 33382.182 | Y6: =E6*Road!I6/100 -> 229706.62 | Z6: =G6*Rail!E6/100 -> -176313.77 | AA6: =H6*Rail!F6/100 -> 19544.278 | AB6: =F6*IWW!D6/100 -> -4443.8755 | AD6: =(C6+D6)*Road!J6/100 -> 254348.82 | AE6: =E6*Road!L6/100 -> 501867.45 | AF6: =G6*Rail!G6/100 -> -82357.091 | AG6: =H6*Rail!I6/100 -> 5616.172 | AH6: =(C6+D6)*Road!K6/100 -> 292079.45 | AI6: =E6*Road!M6/100 -> 224135.48 | AJ6: =G6*Rail!H6/100 -> -46398.361 | AK6: =H6*Rail!J6/100 -> 14826.694
A7: =A49 -> 20 | B7: =IF(B49='S00 Impact'!B6,B49,0) -> BG | C7: =-(C49-'S00 Impact'!C6) -> 12826416 | D7: =-(D49-'S00 Impact'!D6) -> 4063235.5 | E7: =-(E49-'S00 Impact'!E6) -> -2606163.6 | F7: =-(F49-'S00 Impact'!F6) -> -1199115.2 | G7: =-(G49-'S00 Impact'!G6) -> 26022526 | H7: =-(H49-'S00 Impact'!H6) -> -12086701 | N7: =A7 -> 20 | O7: =B7 -> BG | P7: =C7*Road!D7/100 -> 10261.133 | Q7: =D7*Road!E7/100 -> 9223.5446 | R7: =E7*Road!H7/100 -> -45216.938 | S7: =G7*Rail!C7/100 -> 12230.587 | T7: =H7*Rail!D7/100 -> -3263.4092 | U7: =F7*IWW!C7/100 -> -5635.8414 | W7: =C7*Road!F7/100 -> 123005.33 | X7: =D7*Road!G7/100 -> 38844.531 | Y7: =E7*Road!I7/100 -> -116052.46 | Z7: =G7*Rail!E7/100 -> 39554.24 | AA7: =H7*Rail!F7/100 -> -10515.43 | AB7: =F7*IWW!D7/100 -> -3261.5933 | AD7: =(C7+D7)*Road!J7/100 -> 53202.403 | AE7: =E7*Road!L7/100 -> -26165.882 | AF7: =G7*Rail!G7/100 -> 22119.147 | AG7: =H7*Rail!I7/100 -> -3263.4092 | AH7: =(C7+D7)*Road!K7/100 -> 43913.094 | AI7: =E7*Road!M7/100 -> -58768.989 | AJ7: =G7*Rail!H7/100 -> 55948.431 | AK7: =H7*Rail!J7/100 -> -3626.0102
A8: =A50 -> 20 | B8: =IF(B50='S00 Impact'!B7,B50,0) -> BY | C8: =-(C50-'S00 Impact'!C7) -> 54220661 | D8: =-(D50-'S00 Impact'!D7) -> 14172463 | E8: =-(E50-'S00 Impact'!E7) -> 44312749 | F8: =-(F50-'S00 Impact'!F7) -> 0 | G8: =-(G50-'S00 Impact'!G7) -> 87835855 | H8: =-(H50-'S00 Impact'!H7) -> 68053741 | N8: =A8 -> 20 | O8: =B8 -> BY | P8: =C8*Road!D8/100 -> 54762.867 | Q8: =D8*Road!E8/100 -> 40391.519 | R8: =E8*Road!H8/100 -> 964688.55 | S8: =G8*Rail!C8/100 -> 64998.533 | T8: =H8*Rail!D8/100 -> 29943.646 | U8: =F8*IWW!C8/100 -> 0 | W8: =C8*Road!F8/100 -> 519976.14 | X8: =D8*Road!G8/100 -> 135488.75 | Y8: =E8*Road!I8/100 -> 1973246.7 | Z8: =G8*Rail!E8/100 -> 133510.5 | AA8: =H8*Rail!F8/100 -> 59206.755 | AB8: =F8*IWW!D8/100 -> 0 | AD8: =(C8+D8)*Road!J8/100 -> 270836.77 | AE8: =E8*Road!L8/100 -> 557897.51 | AF8: =G8*Rail!G8/100 -> 62363.457 | AG8: =H8*Rail!I8/100 -> 18374.51 | AH8: =(C8+D8)*Road!K8/100 -> 223645.51 | AI8: =E8*Road!M8/100 -> 1253607.7 | AJ8: =G8*Rail!H8/100 -> 27229.115 | AK8: =H8*Rail!J8/100 -> 23138.272
A9: =A51 -> 20 | B9: =IF(B51='S00 Impact'!B8,B51,0) -> CH | C9: =-(C51-'S00 Impact'!C8) -> 509996.35 | D9: =-(D51-'S00 Impact'!D8) -> 541845.2 | E9: =-(E51-'S00 Impact'!E8) -> 6357737.5 | F9: =-(F51-'S00 Impact'!F8) -> -5738.8611 | G9: =-(G51-'S00 Impact'!G8) -> 7299446.1 | H9: =-(H51-'S00 Impact'!H8) -> -7805004.5 | N9: =A9 -> 20 | O9: =B9 -> CH | P9: =C9*Road!D9/100 -> 1575.8887 | Q9: =D9*Road!E9/100 -> 4730.3086 | R9: =E9*Road!H9/100 -> 423552.48 | S9: =G9*Rail!C9/100 -> 2919.7784 | T9: =H9*Rail!D9/100 -> -1795.151 | U9: =F9*IWW!C9/100 -> -107.66103 | W9: =C9*Road!F9/100 -> 4890.865 | X9: =D9*Road!G9/100 -> 5180.0401 | Y9: =E9*Road!I9/100 -> 283110.05 | Z9: =G9*Rail!E9/100 -> 11095.158 | AA9: =H9*Rail!F9/100 -> -6790.3539 | AB9: =F9*IWW!D9/100 -> -15.609702 | AD9: =(C9+D9)*Road!J9/100 -> 12737.801 | AE9: =E9*Road!L9/100 -> 245090.78 | AF9: =G9*Rail!G9/100 -> 10073.236 | AG9: =H9*Rail!I9/100 -> -1092.7006 | AH9: =(C9+D9)*Road!K9/100 -> 10518.416 | AI9: =E9*Road!M9/100 -> 550452.92 | AJ9: =G9*Rail!H9/100 -> 16058.781 | AK9: =H9*Rail!J9/100 -> -4604.9526
A10: =A52 -> 20 | B10: =IF(B52='S00 Impact'!B9,B52,0) -> CZ | C10: =-(C52-'S00 Impact'!C9) -> 11076066 | D10: =-(D52-'S00 Impact'!D9) -> 3162403.9 | E10: =-(E52-'S00 Impact'!E9) -> -4715054.5 | F10: =-(F52-'S00 Impact'!F9) -> -5824.3675 | G10: =-(G52-'S00 Impact'!G9) -> 6920661.8 | H10: =-(H52-'S00 Impact'!H9) -> -19955833 | N10: =A10 -> 20 | O10: =B10 -> CZ | P10: =C10*Road!D10/100 -> 16060.296 | Q10: =D10*Road!E10/100 -> 13092.352 | R10: =E10*Road!H10/100 -> -149090.02 | S10: =G10*Rail!C10/100 -> 5605.736 | T10: =H10*Rail!D10/100 -> -8581.0082 | U10: =F10*IWW!C10/100 -> -109.26513 | W10: =C10*Road!F10/100 -> 106330.23 | X10: =D10*Road!G10/100 -> 30200.957 | Y10: =E10*Road!I10/100 -> -209961.38 | Z10: =G10*Rail!E10/100 -> 10519.406 | AA10: =H10*Rail!F10/100 -> -17361.575 | AB10: =F10*IWW!D10/100 -> -15.84228 | AD10: =(C10+D10)*Road!J10/100 -> 31609.403 | AE10: =E10*Road!L10/100 -> -91802.111 | AF10: =G10*Rail!G10/100 -> 3806.364 | AG10: =H10*Rail!I10/100 -> -5587.6333 | AH10: =(C10+D10)*Road!K10/100 -> 70338.042 | AI10: =E10*Road!M10/100 -> -228255.79 | AJ10: =G10*Rail!H10/100 -> 6920.6618 | AK10: =H10*Rail!J10/100 -> -25543.466
A11: =A53 -> 20 | B11: =IF(B53='S00 Impact'!B10,B53,0) -> DE | C11: =-(C53-'S00 Impact'!C10) -> -5.3834478e+08 | D11: =-(D53-'S00 Impact'!D10) -> -1.3251096e+08 | E11: =-(E53-'S00 Impact'!E10) -> 7056751.6 | F11: =-(F53-'S00 Impact'!F10) -> -3966749.6 | G11: =-(G53-'S00 Impact'!G10) -> -4.1069463e+08 | H11: =-(H53-'S00 Impact'!H10) -> -85083098 | N11: =A11 -> 20 | O11: =B11 -> DE | P11: =C11*Road!D11/100 -> -796750.28 | Q11: =D11*Road!E11/100 -> -810967.08 | R11: =E11*Road!H11/100 -> 347474.45 | S11: =G11*Rail!C11/100 -> -143743.12 | T11: =H11*Rail!D11/100 -> -17016.62 | U11: =F11*IWW!C11/100 -> -96352.347 | W11: =C11*Road!F11/100 -> -5168109.9 | X11: =D11*Road!G11/100 -> -1265479.7 | Y11: =E11*Road!I11/100 -> 314237.15 | Z11: =G11*Rail!E11/100 -> -624255.84 | AA11: =H11*Rail!F11/100 -> -74022.295 | AB11: =F11*IWW!D11/100 -> -10789.559 | AD11: =(C11+D11)*Road!J11/100 -> -2549251.8 | AE11: =E11*Road!L11/100 -> 271896.64 | AF11: =G11*Rail!G11/100 -> -349090.44 | AG11: =H11*Rail!I11/100 -> -22972.437 | AH11: =(C11+D11)*Road!K11/100 -> -3917797.6 | AI11: =E11*Road!M11/100 -> 272108.34 | AJ11: =G11*Rail!H11/100 -> -587293.32 | AK11: =H11*Rail!J11/100 -> -32331.577
A12: =A54 -> 20 | B12: =IF(B54='S00 Impact'!B11,B54,0) -> DK | C12: =-(C54-'S00 Impact'!C11) -> 35158540 | D12: =-(D54-'S00 Impact'!D11) -> 10585381 | E12: =-(E54-'S00 Impact'!E11) -> 14948911 | F12: =-(F54-'S00 Impact'!F11) -> 0 | G12: =-(G54-'S00 Impact'!G11) -> -16319331 | H12: =-(H54-'S00 Impact'!H11) -> 442244.36 | N12: =A12 -> 20 | O12: =B12 -> DK | P12: =C12*Road!D12/100 -> 48518.786 | Q12: =D12*Road!E12/100 -> 38636.639 | R12: =E12*Road!H12/100 -> 412888.93 | S12: =G12*Rail!C12/100 -> -7506.8921 | T12: =H12*Rail!D12/100 -> 137.09575 | U12: =F12*IWW!C12/100 -> 0 | W12: =C12*Road!F12/100 -> 337521.99 | X12: =D12*Road!G12/100 -> 101090.39 | Y12: =E12*Road!I12/100 -> 665675.02 | Z12: =G12*Rail!E12/100 -> -24805.382 | AA12: =H12*Rail!F12/100 -> 384.7526 | AB12: =F12*IWW!D12/100 -> 0 | AD12: =(C12+D12)*Road!J12/100 -> 178401.29 | AE12: =E12*Road!L12/100 -> 535619.49 | AF12: =G12*Rail!G12/100 -> -9302.0184 | AG12: =H12*Rail!I12/100 -> 137.09575 | AH12: =(C12+D12)*Road!K12/100 -> 392482.84 | AI12: =E12*Road!M12/100 -> 846556.84 | AJ12: =G12*Rail!H12/100 -> -8649.2452 | AK12: =H12*Rail!J12/100 -> 566.07279
A13: =A55 -> 20 | B13: =IF(B55='S00 Impact'!B12,B55,0) -> EE | C13: =-(C55-'S00 Impact'!C12) -> -3001273.8 | D13: =-(D55-'S00 Impact'!D12) -> -566453.63 | E13: =-(E55-'S00 Impact'!E12) -> -3824354.1 | F13: =-(F55-'S00 Impact'!F12) -> 0 | G13: =-(G55-'S00 Impact'!G12) -> 1517784.1 | H13: =-(H55-'S00 Impact'!H12) -> 35466888 | N13: =A13 -> 20 | O13: =B13 -> EE | P13: =C13*Road!D13/100 -> -6212.6369 | Q13: =D13*Road!E13/100 -> -3336.4119 | R13: =E13*Road!H13/100 -> -172095.94 | S13: =G13*Rail!C13/100 -> 4826.5533 | T13: =H13*Rail!D13/100 -> 64904.406 | U13: =F13*IWW!C13/100 -> 0 | W13: =C13*Road!F13/100 -> -28812.229 | X13: =D13*Road!G13/100 -> -5409.6322 | Y13: =E13*Road!I13/100 -> -170298.49 | Z13: =G13*Rail!E13/100 -> 2307.0318 | AA13: =H13*Rail!F13/100 -> 30856.193 | AB13: =F13*IWW!D13/100 -> 0 | AD13: =(C13+D13)*Road!J13/100 -> -8027.3868 | AE13: =E13*Road!L13/100 -> -105972.85 | AF13: =G13*Rail!G13/100 -> 1077.6267 | AG13: =H13*Rail!I13/100 -> 12058.742 | AH13: =(C13+D13)*Road!K13/100 -> -25081.124 | AI13: =E13*Road!M13/100 -> -263421.51 | AJ13: =G13*Rail!H13/100 -> 576.75795 | AK13: =H13*Rail!J13/100 -> 70224.439
A14: =A56 -> 20 | B14: =IF(B56='S00 Impact'!B13,B56,0) -> ES | C14: =-(C56-'S00 Impact'!C13) -> -98916621 | D14: =-(D56-'S00 Impact'!D13) -> -53223897 | E14: =-(E56-'S00 Impact'!E13) -> -4960656.7 | F14: =-(F56-'S00 Impact'!F13) -> 0 | G14: =-(G56-'S00 Impact'!G13) -> 1.2318301e+08 | H14: =-(H56-'S00 Impact'!H13) -> -2795685.4 | N14: =A14 -> 20 | O14: =B14 -> ES | P14: =C14*Road!D14/100 -> -168158.26 | Q14: =D14*Road!E14/100 -> -181493.49 | R14: =E14*Road!H14/100 -> -120692.78 | S14: =G14*Rail!C14/100 -> 40650.394 | T14: =H14*Rail!D14/100 -> -531.18022 | U14: =F14*IWW!C14/100 -> 0 | W14: =C14*Road!F14/100 -> -949599.56 | X14: =D14*Road!G14/100 -> -508288.22 | Y14: =E14*Road!I14/100 -> -220898.04 | Z14: =G14*Rail!E14/100 -> 187238.18 | AA14: =H14*Rail!F14/100 -> -2432.2463 | AB14: =F14*IWW!D14/100 -> 0 | AD14: =(C14+D14)*Road!J14/100 -> -686153.74 | AE14: =E14*Road!L14/100 -> -24604.857 | AF14: =G14*Rail!G14/100 -> 78837.128 | AG14: =H14*Rail!I14/100 -> -754.83505 | AH14: =(C14+D14)*Road!K14/100 -> -873286.58 | AI14: =E14*Road!M14/100 -> -187959.28 | AJ14: =G14*Rail!H14/100 -> 200788.31 | AK14: =H14*Rail!J14/100 -> -810.74876
A15: =A57 -> 20 | B15: =IF(B57='S00 Impact'!B14,B57,0) -> FI | C15: =-(C57-'S00 Impact'!C14) -> 12074463 | D15: =-(D57-'S00 Impact'!D14) -> 1698020.6 | E15: =-(E57-'S00 Impact'!E14) -> 1806545.2 | F15: =-(F57-'S00 Impact'!F14) -> 0 | G15: =-(G57-'S00 Impact'!G14) -> 3174595.8 | H15: =-(H57-'S00 Impact'!H14) -> -4745588 | N15: =A15 -> 20 | O15: =B15 -> FI | P15: =C15*Road!D15/100 -> 23182.969 | Q15: =D15*Road!E15/100 -> 9271.1922 | R15: =E15*Road!H15/100 -> 75314.868 | S15: =G15*Rail!C15/100 -> 1174.6005 | T15: =H15*Rail!D15/100 -> -1660.9558 | U15: =F15*IWW!C15/100 -> 0 | W15: =C15*Road!F15/100 -> 115914.84 | X15: =D15*Road!G15/100 -> 16216.096 | Y15: =E15*Road!I15/100 -> 80445.456 | Z15: =G15*Rail!E15/100 -> 4825.3857 | AA15: =H15*Rail!F15/100 -> -4128.6616 | AB15: =F15*IWW!D15/100 -> 0 | AD15: =(C15+D15)*Road!J15/100 -> 62251.625 | AE15: =E15*Road!L15/100 -> 46374.014 | AF15: =G15*Rail!G15/100 -> 2952.3741 | AG15: =H15*Rail!I15/100 -> -2040.6028 | AH15: =(C15+D15)*Road!K15/100 -> 89658.867 | AI15: =E15*Road!M15/100 -> 115293.71 | AJ15: =G15*Rail!H15/100 -> 3523.8014 | AK15: =H15*Rail!J15/100 -> -6311.6321
... A41: =A83 -> 20 | B41: =IF(B83='S00 Impact'!B40,B83,0) -> YU | C41: =-(C83-'S00 Impact'!C40) -> -1407343.6 | D41: =-(D83-'S00 Impact'!D40) -> -2772888.1 | E41: =-(E83-'S00 Impact'!E40) -> -1693145.2 | F41: =-(F83-'S00 Impact'!F40) -> -7214035 | G41: =-(G83-'S00 Impact'!G40) -> 62029151 | H41: =-(H83-'S00 Impact'!H40) -> 10978921 | N41: =A41 -> 20 | O41: =B41 -> YU | P41: =C41*Road!D41/100 -> -1266.6092 | Q41: =D41*Road!E41/100 -> -7098.5936 | R41: =E41*Road!H41/100 -> -33016.331 | S41: =G41*Rail!C41/100 -> 26052.243 | T41: =H41*Rail!D41/100 -> 2634.9411 | U41: =F41*IWW!C41/100 -> -91762.525 | W41: =C41*Road!F41/100 -> -13496.425 | X41: =D41*Road!G41/100 -> -26508.81 | Y41: =E41*Road!I41/100 -> -75395.755 | Z41: =G41*Rail!E41/100 -> 94284.309 | AA41: =H41*Rail!F41/100 -> 9551.6613 | AB41: =F41*IWW!D41/100 -> -19622.175 | AD41: =(C41+D41)*Road!J41/100 -> -14839.822 | AE41: =E41*Road!L41/100 -> -19098.678 | AF41: =G41*Rail!G41/100 -> 44040.697 | AG41: =H41*Rail!I41/100 -> 2964.3087 | AH41: =(C41+D41)*Road!K41/100 -> -12248.079 | AI41: =E41*Road!M41/100 -> -42904.299 | AJ41: =G41*Rail!H41/100 -> 23571.077 | AK41: =H41*Rail!J41/100 -> 5379.6713
N42: =N41 -> 20 | O42: Total | P42: =SUM(P3:P41) -> -1064063.4 | Q42: =SUM(Q3:Q41) -> -976508.16 | R42: =SUM(R3:R41) -> 4211930.4 | S42: =SUM(S3:S41) -> -532367.32 | T42: =SUM(T3:T41) -> -95881.788 | U42: =SUM(U3:U41) -> -818026.43 | V42: =L3*Air!C3/100 -> 5777248.6 | W42: =SUM(W3:W41) -> -4911136.8 | X42: =SUM(X3:X41) -> -1757331.1 | Y42: =SUM(Y3:Y41) -> 9812454.8 | Z42: =SUM(Z3:Z41) -> -1571309.2 | AA42: =SUM(AA3:AA41) -> -173752.75 | AB42: =SUM(AB3:AB41) -> -120902.67 | AC42: =L3*Air!D3/100 -> 4190184.7 | AD42: =SUM(AD3:AD41) -> -2042817.7 | AE42: =SUM(AE3:AE41) -> 3267784.2 | AF42: =SUM(AF3:AF41) -> -742890.9 | AG42: =SUM(AG3:AG41) -> -73641.194 | AH42: =SUM(AH3:AH41) -> -5343418.1 | AI42: =SUM(AI3:AI41) -> 6579009.6 | AJ42: =SUM(AJ3:AJ41) -> -1222487.7 | AK42: =SUM(AK3:AK41) -> -131791.63 | AL42: =SUM(P42:AK42) -> 12260285
V43: =SUM(P42:V42) -> 6502331.9 | AC43: =SUM(W42:AC42) -> 5468206.9 | AG43: =SUM(AD42:AG42) -> 408434.38 | AK43: =SUM(AH42:AK42) -> -118687.74
A44: scenario | B44: CountryCode | C44: vkm_petrol_Carpassenger | D44: vkm_diesel_Carpassenger | E44: vkm_hgv_Freight | F44: Total_IWW_TonKM | G44: PersonKM_RailPassenger | H44: TonKM_RailFreight | J44: _TYPE_ | K44: _FREQ_ | L44: personkm_Air
A45: 20 | B45: AL | C45: 2.1984391e+09 | D45: 5.4383308e+08 | E45: 7.7696764e+08 | G45: 1.2910886e+08 | H45: 5.9565381e+08 | J45: 0 | K45: 3153 | L45: 8.3845409e+11
A46: 20 | B46: AT | C46: 4.3072803e+10 | D46: 2.7048198e+10 | E46: 6.903325e+09 | F46: 7.1090247e+09 | G46: 1.5855108e+10 | H46: 2.4655095e+10
A47: 20 | B47: BA | C47: 5.0311692e+09 | D47: 1.2342705e+09 | E47: 8.4739128e+08 | F47: 7.382971e+08 | G47: 5.9633352e+08 | H47: 1.2065089e+09
A48: 20 | B48: BE | C48: 4.2856914e+10 | D48: 3.2550294e+10 | E48: 8.4026533e+09 | F48: 9.5902895e+09 | G48: 1.4268905e+10 | H48: 9.7925724e+09
A49: 20 | B49: BG | C49: 2.7958593e+10 | D49: 6.8310541e+09 | E49: 3.8433044e+09 | F49: 2.1018336e+09 | G49: 1.6983938e+10 | H49: 2.302191e+10
A50: 20 | B50: BY | C50: 1.9178788e+10 | D50: 4.6222173e+09 | E50: 1.0390907e+10 | G50: 7.6237765e+09 | H50: 2.6883412e+10
A51: 20 | B51: CH | C51: 3.9946027e+10 | D51: 5.7123953e+09 | E51: 3.6371489e+09 | F51: 38947141 | G51: 1.1671671e+10 | H51: 1.1565109e+10
A52: 20 | B52: CZ | C52: 3.1719427e+10 | D52: 6.8873394e+09 | E52: 8.552403e+09 | F52: 45307990 | G52: 9.3538526e+09 | H52: 3.5387248e+10
A53: 20 | B53: DE | C53: 3.8054795e+11 | D53: 8.8804421e+10 | E53: 4.6520623e+10 | F53: 7.5688715e+10 | G53: 1.1531037e+11 | H53: 1.1019545e+11
A54: 20 | B54: DK | C54: 3.7209608e+10 | D54: 3.8552613e+09 | E54: 7.2277816e+09 | G54: 6.4010677e+09 | H54: 3.3945682e+09
A55: 20 | B55: EE | C55: 3.3596502e+09 | D55: 6.1020937e+08 | E55: 1.8237929e+09 | G55: 2.8872385e+08 | H55: 3.0960109e+10
A56: 20 | B56: ES | C56: 1.7620468e+11 | D56: 9.451831e+10 | E56: 4.8194093e+10 | G56: 2.9387022e+10 | H56: 2.4319153e+10
A57: 20 | B57: FI | C57: 2.9648411e+10 | D57: 4.3279062e+09 | E57: 5.6521623e+09 | G57: 7.6519176e+09 | H57: 2.2109886e+10
A58: 20 | B58: FR | C58: 2.4517604e+11 | D58: 1.677075e+11 | E58: 4.4054118e+10 | F58: 1.2024397e+10 | G58: 9.5000636e+10 | H58: 5.5835511e+10
A59: 20 | B59: GR | C59: 2.7379962e+10 | D59: 6.7789138e+09 | E59: 6.2786761e+09 | G59: 2.8856111e+09 | H59: 1.4287097e+09
A60: 20 | B60: HR | C60: 2.2440991e+10 | D60: 5.5762361e+09 | E60: 2.6734522e+09 | F60: 3.1171494e+08 | G60: 9.1029015e+09 | H60: 7.4848204e+09
A61: 20 | B61: HU | C61: 2.9565628e+10 | D61: 6.0722558e+09 | E61: 5.3969259e+09 | F61: 1.1187888e+10 | G61: 1.54423e+10 | H61: 2.3892855e+10
A62: 20 | B62: IE | C62: 2.7580504e+10 | D62: 4.7727473e+09 | E62: 4.8671485e+09 | G62: 1.9394489e+09 | H62: 6.5530657e+08
A63: 20 | B63: IT | C63: 2.1157126e+11 | D63: 5.577943e+10 | E63: 3.6797036e+10 | G63: 5.0959585e+10 | H63: 3.5874997e+10
A64: 20 | B64: LI | C64: 79704290 | D64: 23652935 | E64: 17998677 | G64: 12802203 | H64: 26258766
A65: 20 | B65: LT | C65: 8.5330807e+09 | D65: 2.0325628e+09 | E65: 4.6458647e+09 | F65: 1945882.9 | G65: 1.3197104e+10 | H65: 3.6941402e+10
A66: 20 | B66: LU | C66: 5.5459962e+09 | D66: 2.6300671e+09 | E66: 9.0329592e+08 | G66: 1.5797207e+08 | H66: 5.7221894e+08
A67: 20 | B67: LV | C67: 7.2351221e+09 | D67: 1.4406177e+09 | E67: 2.611143e+09 | F67: 3057704.3 | G67: 8.0948134e+09 | H67: 5.0269312e+10
A68: 20 | B68: MD | C68: 5.6168136e+09 | D68: 1.3861162e+09 | E68: 1.6164508e+09 | G68: 1.4120006e+09 | H68: 3.4664358e+09
A69: 20 | B69: ME | C69: 1.5187952e+09 | D69: 3.7562829e+08 | E69: 1.8885226e+08 | G69: 1.3742671e+08 | H69: 1.8994031e+09
A70: 20 | B70: MK | C70: 4.7984906e+09 | D70: 1.1885001e+09 | E70: 1.3557541e+09 | G70: 7.2009943e+08 | H70: 4.1494534e+08
A71: 20 | B71: NL | C71: 9.5192416e+10 | D71: 1.9240808e+10 | E71: 1.0286687e+10 | F71: 3.9746521e+10 | G71: 1.2491071e+10 | H71: 6.6041054e+09
A72: 20 | B72: NO | C72: 4.0205802e+10 | D72: 9.4006671e+09 | E72: 3.8595452e+09 | G72: 4.5262308e+09 | H72: 4.7576998e+09
A73: 20 | B73: PL | C73: 9.6015628e+10 | D73: 1.8884159e+10 | E73: 3.0165011e+10 | F73: 8.8233141e+08 | G73: 5.4203749e+10 | H73: 1.3158885e+11
A74: 20 | B74: PT | C74: 3.7368953e+10 | D74: 9.7776241e+09 | E74: 6.7191399e+09 | G74: 4.7027794e+09 | H74: 4.6566245e+09
A75: 20 | B75: RO | C75: 3.8568492e+10 | D75: 9.4218375e+09 | E75: 1.3980217e+10 | F75: 2.1616965e+10 | G75: 1.1331978e+10 | H75: 5.7841727e+10
A76: 20 | B76: RU | C76: 1.5838334e+11 | D76: 3.8860494e+10 | E76: 9.043234e+10 | G76: 1.0583603e+11 | H76: 2.3285628e+11
A77: 20 | B77: SE | C77: 5.7489636e+10 | D77: 4.4775403e+09 | E77: 8.439554e+09 | G77: 1.7939363e+10 | H77: 3.5588687e+10
A78: 20 | B78: SI | C78: 1.1791429e+10 | D78: 3.0883734e+09 | E78: 2.3262311e+09 | G78: 5.6991317e+09 | H78: 1.0036758e+10
A79: 20 | B79: SK | C79: 1.274424e+10 | D79: 3.0883308e+09 | E79: 4.0710945e+09 | F79: 7.0648014e+08 | G79: 2.509386e+09 | H79: 2.3566207e+10
A80: 20 | B80: TR | C80: 1.1417183e+11 | D80: 2.7993542e+10 | E80: 1.1222237e+10 | G80: 5.0421964e+10 | H80: 1.3377591e+10
A81: 20 | B81: UA | C81: 7.3900689e+10 | D81: 1.8010624e+10 | E81: 2.2514681e+10 | G81: 3.5852937e+10 | H81: 7.7284253e+10
A82: 20 | B82: UK | C82: 3.3081901e+11 | D82: 7.5142062e+10 | E82: 2.6292022e+10 | F82: 3.2638931e+08 | G82: 4.8626457e+10 | H82: 3.7367139e+10
A83: 20 | B83: YU | C83: 2.0538781e+10 | D83: 5.0215863e+09 | E83: 2.1457172e+09 | F83: 1.3219737e+10 | G83: 2.0510155e+10 | H83: 9.3289005e+09

Sheet CBA Result
B2: Price Growth | C2: 0.014 | D2: Impact on: CS, GW and AP | F2: Scenario | H2: Type | I2: Investment Cost (€) | J2: Change in Maintenance Cost (€/yr) | K2: Opening Year | L2: Construction Period (yr) | M2: Passenger CS (€) | N2: Freight CS (€) | O2: Sum of First Year Impacts (€) | P2: Air Pollution First Year Impacts (€) | Q2: Global Warming First Year Impacts (€) | R2: Traffic Accidents First Year Impacts (€) | S2: Noise First Year Impacts (€) | T2: NPV | U2: BCR | V2: IRR
B3: Traffic Growth | C3: 0.014 | D3: Impact on: CS, GW and AP | F3: 1 | G3: ='Full overview'!B2 -> Munich - Verona | H3: ='Full overview'!C2 -> Railway | I3: ='Full overview'!D2*(10^6) -> 14000000000 | J3: ='Full overview'!E2*(10^6) -> 7400000 | K3: ='Full overview'!G2 -> 2030 | L3: ='Full overview'!H2 -> 10 | M3: =CS!C3 -> 25814639 | N3: =CS!H3 -> 43975545 | O3: ='S01 Impact'!AL42 -> 2342986.1 | P3: ='S01 Impact'!$V$43 -> 6302590.1 | Q3: ='S01 Impact'!$AC$43 -> 4497602.3 | R3: ='S01 Impact'!$AG$43 -> -3203671.1 | S3: ='S01 Impact'!$AK$43 -> -5253535.2 | T3: =G63 -> -1.1000879e+10 | U3: =G64 -> 0.33452685 | V3: =G65 -> 0.0059987939
B4: Emission Growth | C4: -0.15 | D4: Impact on GW and AP | F4: 10 | G4: ='Full overview'!B11 -> Hungary - Romania + Bulgary - Greece | H4: ='Full overview'!C11 -> Railway + road | I4: ='Full overview'!D11*(10^6) -> 9870000000 | J4: ='Full overview'!E11*(10^6) -> 2400000 | K4: ='Full overview'!G11 -> 2028 | L4: ='Full overview'!H11 -> 8 | M4: =CS!C12 -> 2.8634481e+08 | N4: =CS!H12 -> 1.8307176e+08 | O4: ='S10 Impact'!AL42 -> -74628639 | P4: ='S10 Impact'!$V$43 -> 6466250.5 | Q4: ='S10 Impact'!$AC$43 -> -39866832 | R4: ='S10 Impact'!$AG$43 -> -20767851 | S4: ='S10 Impact'!$AK$43 -> -20460206 | T4: =G98 -> 6.1207018e+09 | U4: =G99 -> 1.5416528 | V4: =G100 -> 0.045383536
B5: Discount Rate | C5: 0.03 | F5: 18 | G5: ='Full overview'!B19 -> Fehmarn Belt (incl. upgrades) | H5: ='Full overview'!C19 -> Railway + road | I5: ='Full overview'!D19*(10^6) -> 6550000000 | J5: ='Full overview'!E19*(10^6) -> 4000000 | K5: ='Full overview'!G19 -> 2029 | L5: ='Full overview'!H19 -> 7 | M5: =CS!C20 -> 1.0090258e+08 | N5: =CS!H20 -> 49153274 | O5: ='S18 Impact'!AL42 -> 89870814 | P5: ='S18 Impact'!$V$43 -> 35066129 | Q5: ='S18 Impact'!$AC$43 -> 42582785 | R5: ='S18 Impact'!$AG$43 -> 2273581.6 | S5: ='S18 Impact'!$AK$43 -> 9948318.7 | T5: =G133 -> 2.9858524e+08 | U5: =G134 -> 1.0404315 | V5: =G135 -> 0.031345361
B6: Evaluation Period (Years) | C6: 50 | F6: 20 | G6: ='Full overview'!B21 -> Upgrades in Cologne | H6: ='Full overview'!C21 -> Railway + road | I6: ='Full overview'!D21*(10^6) -> 2470000000 | J6: ='Full overview'!E21*(10^6) -> 1900000 | K6: ='Full overview'!G21 -> 2027 | L6: ='Full overview'!H21 -> 6 | M6: =CS!C22 -> 67568116 | N6: =CS!H22 -> 26603746 | O6: ='S20 Impact'!AL42 -> 12260285 | P6: ='S20 Impact'!$V$43 -> 6502331.9 | Q6: ='S20 Impact'!$AC$43 -> 5468206.9 | R6: ='S20 Impact'!$AG$43 -> 408434.38 | S6: ='S20 Impact'!$AK$43 -> -118687.74 | T6: =G172 -> 1.0887241e+09 | U6: =G173 -> 1.3969514 | V6: =G174 -> 0.042327703
H33: 2020 | I33: 2021 | J33: 2022 | K33: 2023 | L33: 2024 | M33: 2025 | N33: 2026 | O33: 2027 | P33: 2028 | Q33: 2029 | R33: 2030 | S33: 2031 | T33: 2032 | U33: 2033 | V33: 2034 | W33: 2035 | X33: 2036 | Y33: 2037 | Z33: 2038 | AA33: 2039 | AB33: 2040 | AC33: 2041 | AD33: 2042 | AE33: 2043 | AF33: 2044 | AG33: 2045 | AH33: 2046 | AI33: 2047 | AJ33: 2048 | AK33: 2049 | AL33: 2050 | AM33: 2051 | AN33: 2052 | AO33: 2053 | AP33: 2054 | AQ33: 2055 | AR33: 2056 | AS33: 2057 | AT33: 2058 | AU33: 2059 | AV33: 2060 | AW33: 2061 | AX33: 2062 | AY33: 2063 | AZ33: 2064 | BA33: 2065 | BB33: 2066 | BC33: 2067 | BD33: 2068 | BE33: 2069 | BF33: 2070 | BG33: 2071 | BH33: 2072 | BI33: 2073 | BJ33: 2074 | BK33: 2075 | BL33: 2076 | BM33: 2077 | BN33: 2078 | BO33: 2079
D34: Scenario 1 | F34: Year | G34: Total | H34: -10 | I34: -9 | J34: -8 | K34: -7 | L34: -6 | M34: -5 | N34: -4 | O34: -3 | P34: -2 | Q34: -1 | R34: 0 | S34: 1 | T34: 2 | U34: 3 | V34: 4 | W34: 5 | X34: 6 | Y34: 7 | Z34: 8 | AA34: 9 | AB34: 10 | AC34: 11 | AD34: 12 | AE34: 13 | AF34: 14 | AG34: 15 | AH34: 16 | AI34: 17 | AJ34: 18 | AK34: 19 | AL34: 20 | AM34: 21 | AN34: 22 | AO34: 23 | AP34: 24 | AQ34: 25 | AR34: 26 | AS34: 27 | AT34: 28 | AU34: 29 | AV34: 30 | AW34: 31 | AX34: 32 | AY34: 33 | AZ34: 34 | BA34: 35 | BB34: 36 | BC34: 37 | BD34: 38 | BE34: 39 | BF34: 40 | BG34: 41 | BH34: 42 | BI34: 43 | BJ34: 44 | BK34: 45 | BL34: 46 | BM34: 47 | BN34: 48 | BO34: 49 | BP34: Comments
F35: Discount Factor | H35: =1/((1+$C$5)^H34) -> 1.3439164 | I35: =1/((1+$C$5)^I34) -> 1.3047732 | J35: =1/((1+$C$5)^J34) -> 1.2667701 | K35: =1/((1+$C$5)^K34) -> 1.2298739 | L35: =1/((1+$C$5)^L34) -> 1.1940523 | M35: =1/((1+$C$5)^M34) -> 1.1592741 | N35: =1/((1+$C$5)^N34) -> 1.1255088 | O35: =1/((1+$C$5)^O34) -> 1.092727 | ... Q35: =1/((1+$C$5)^Q34) -> 1.03 | R35: 1 | S35: =1/((1+$C$5)^S34) -> 0.97087379 | T35: =1/((1+$C$5)^T34) -> 0.94259591 | U35: =1/((1+$C$5)^U34) -> 0.91514166 | V35: =1/((1+$C$5)^V34) -> 0.88848705 | W35: =1/((1+$C$5)^W34) -> 0.86260878 | X35: =1/((1+$C$5)^X34) -> 0.83748426 | Y35: =1/((1+$C$5)^Y34) -> 0.81309151 | Z35: =1/((1+$C$5)^Z34) -> 0.78940923 | ... BO35: =1/((1+$C$5)^BO34) -> 0.23495029
F36: Traffic Growth | R36: 1 | S36: =(1+$C$3)^S34 -> 1.014 | T36: =(1+$C$3)^T34 -> 1.028196 | U36: =(1+$C$3)^U34 -> 1.0425907 | V36: =(1+$C$3)^V34 -> 1.057187 | W36: =(1+$C$3)^W34 -> 1.0719876 | X36: =(1+$C$3)^X34 -> 1.0869955 | Y36: =(1+$C$3)^Y34 -> 1.1022134 | Z36: =(1+$C$3)^Z34 -> 1.1176444 | ... AK36: =(1+$C$3)^AK34 -> 1.3023303 | AL36: =$AK$36 -> 1.3023303 | AM36: =$AK$36 -> 1.3023303 | AN36: =$AK$36 -> 1.3023303 | AO36: =$AK$36 -> 1.3023303 | AP36: =$AK$36 -> 1.3023303 | AQ36: =$AK$36 -> 1.3023303 | AR36: =$AK$36 -> 1.3023303 | AS36: =$AK$36 -> 1.3023303 | ... BO36: =$AK$36 -> 1.3023303 | BP36: Traffic Growth is projected for the first 19 years
F37: Price Growth | R37: 1 | S37: =(1+$C$2)^S34 -> 1.014 | T37: =(1+$C$2)^T34 -> 1.028196 | U37: =(1+$C$2)^U34 -> 1.0425907 | V37: =(1+$C$2)^V34 -> 1.057187 | W37: =(1+$C$2)^W34 -> 1.0719876 | X37: =(1+$C$2)^X34 -> 1.0869955 | Y37: =(1+$C$2)^Y34 -> 1.1022134 | Z37: =(1+$C$2)^Z34 -> 1.1176444 | ... BO37: =(1+$C$2)^BO34 -> 1.9763315
F38: Emission Growth | R38: 1 | S38: =(1+$C$4)^S34 -> 0.85 | T38: =(1+$C$4)^T34 -> 0.7225 | U38: =(1+$C$4)^U34 -> 0.614125 | V38: =(1+$C$4)^V34 -> 0.52200625 | W38: =(1+$C$4)^W34 -> 0.44370531 | X38: =(1+$C$4)^X34 -> 0.37714952 | Y38: =(1+$C$4)^Y34 -> 0.32057709 | Z38: =(1+$C$4)^Z34 -> 0.27249053 | ... BO38: =(1+$C$4)^BO34 -> 0.00034795843
F40: Construction Cost Discounted | G40: =SUM(H40:Q40) -> -1.6530914e+10 | H40: =-($I$3/-(MIN($H$34:$Q$34)))*H35 -> -1.8814829e+09 | I40: =-($I$3/-(MIN($H$34:$Q$34)))*I35 -> -1.8266825e+09 | J40: =-($I$3/-(MIN($H$34:$Q$34)))*J35 -> -1.7734781e+09 | K40: =-($I$3/-(MIN($H$34:$Q$34)))*K35 -> -1.7218234e+09 | L40: =-($I$3/-(MIN($H$34:$Q$34)))*L35 -> -1.6716732e+09 | M40: =-($I$3/-(MIN($H$34:$Q$34)))*M35 -> -1.6229837e+09 | N40: =-($I$3/-(MIN($H$34:$Q$34)))*N35 -> -1575712334 | O40: =-($I$3/-(MIN($H$34:$Q$34)))*O35 -> -1529817800 | ... Q40: =-($I$3/-(MIN($H$34:$Q$34)))*Q35 -> -1442000000
F41: Scrap Value | G41: =I3*BO35 -> 3.2893041e+09 | BO41: =I3 -> 14000000000
F42: Maintenance | G42: =SUM(S42:BO42) -> -362600000 | R42: =-$J$3 -> -7400000 | S42: =-$J$3 -> -7400000 | T42: =-$J$3 -> -7400000 | U42: =-$J$3 -> -7400000 | V42: =-$J$3 -> -7400000 | W42: =-$J$3 -> -7400000 | X42: =-$J$3 -> -7400000 | Y42: =-$J$3 -> -7400000 | ... BO42: =-$J$3 -> -7400000
BS43: For thescrap value to calculate the IRR do not keep it discounted
F44: Passenger CS | G44: =SUM(R44:BO44) -> 2.0208246e+09 | R44: =$M$3/(((1+C2)^(2035-$R$33))*((1+C3)^(2035-$R$33))) -> 22463969 | S44: =$R$44*S36*S37 -> 23097364 | T44: =$R$44*T36*T37 -> 23748617 | U44: =$R$44*U36*U37 -> 24418233 | V44: =$R$44*V36*V37 -> 25106729 | W44: =$R$44*W36*W37 -> 25814639 | X44: =$R$44*X36*X37 -> 26542508 | Y44: =$R$44*Y36*Y37 -> 27290901 | Z44: =$R$44*Z36*Z37 -> 28060395 | ... BO44: =$R$44*BO36*BO37 -> 57818582
F45: Freight CS | G45: =SUM(R45:BO45) -> 3.4424988e+09 | R45: =$N$3/(((1+C2)^(2035-$R$33))*((1+C3)^(2035-$R$33))) -> 38267640 | S45: =$R$45*S36*S37 -> 39346635 | T45: =$R$45*T36*T37 -> 40456053 | U45: =$R$45*U36*U37 -> 41596751 | V45: =$R$45*V36*V37 -> 42769613 | W45: =$R$45*W36*W37 -> 43975545 | X45: =$R$45*X36*X37 -> 45215480 | Y45: =$R$45*Y36*Y37 -> 46490376 | Z45: =$R$45*Z36*Z37 -> 47801218 | ... BO45: =$R$45*BO36*BO37 -> 98494646
F47: Air Pollution | G47: =SUM(R47:BO47) -> 49634142 | R47: =$P$3 -> 6302590.1 | S47: =$R$47*S36*S37*S38 -> 5508253.2 | T47: =$R$47*T36*T37*T38 -> 4814029.3 | U47: =$R$47*U36*U37*U38 -> 4207300.8 | V47: =$R$47*V36*V37*V38 -> 3677040.4 | W47: =$R$47*W36*W37*W38 -> 3213610.5 | X47: =$R$47*X36*X37*X38 -> 2808588.2 | Y47: =$R$47*Y36*Y37*Y38 -> 2454612.3 | Z47: =$R$47*Z36*Z37*Z38 -> 2145249.2 | ... BO47: =$R$47*BO36*BO37*BO38 -> 5644.5245
F48: Global Warming | G48: =SUM(R48:BO48) -> 35419507 | R48: =$Q$3 -> 4497602.3 | S48: =$R$48*S36*S37*S38 -> 3930754.2 | T48: =$R$48*T36*T37*T38 -> 3435347.9 | U48: =$R$48*U36*U37*U38 -> 3002379.3 | V48: =$R$48*V36*V37*V38 -> 2623979.3 | W48: =$R$48*W36*W37*W38 -> 2293270.2 | X48: =$R$48*X36*X37*X38 -> 2004241.6 | Y48: =$R$48*Y36*Y37*Y38 -> 1751640.2 | Z48: =$R$48*Z36*Z37*Z38 -> 1530875 | ... BO48: =$R$48*BO36*BO37*BO38 -> 4027.999
F49: Traffic Accidents | G49: =SUM(R49:BO49) -> -1.6018355e+08 | R49: =$R$3 -> -3203671.1 | S49: =$R$49 -> -3203671.1 | T49: =$R$49 -> -3203671.1 | U49: =$R$49 -> -3203671.1 | V49: =$R$49 -> -3203671.1 | W49: =$R$49 -> -3203671.1 | X49: =$R$49 -> -3203671.1 | Y49: =$R$49 -> -3203671.1 | Z49: =$R$49 -> -3203671.1 | ... BO49: =$R$49 -> -3203671.1
F50: Noise Pollution | G50: =SUM(R50:BO50) -> -2.6267676e+08 | R50: =$S$3 -> -5253535.2 | S50: =$R$50 -> -5253535.2 | T50: =$R$50 -> -5253535.2 | U50: =$R$50 -> -5253535.2 | V50: =$R$50 -> -5253535.2 | W50: =$R$50 -> -5253535.2 | X50: =$R$50 -> -5253535.2 | Y50: =$R$50 -> -5253535.2 | Z50: =$R$50 -> -5253535.2 | ... BO50: =$R$50 -> -5253535.2
F51: Non Discounted Sum | H51: =SUM(H40:H50)/H35 -> -1400000000 | I51: =SUM(I40:I50)/I35 -> -1400000000 | J51: =SUM(J40:J50)/J35 -> -1400000000 | K51: =SUM(K40:K50)/K35 -> -1400000000 | L51: =SUM(L40:L50)/L35 -> -1400000000 | M51: =SUM(M40:M50)/M35 -> -1400000000 | N51: =SUM(N40:N50)/N35 -> -1400000000 | O51: =SUM(O40:O50)/O35 -> -1400000000 | ... Q51: =SUM(Q40:Q50)/Q35 -> -1400000000 | R51: =SUM(R40:R50) -> 55674596 | S51: =SUM(S40:S50) -> 56025800 | T51: =SUM(T40:T50) -> 56596840 | U51: =SUM(U40:U50) -> 57367458 | V51: =SUM(V40:V50) -> 58320156 | W51: =SUM(W40:W50) -> 59439859 | X51: =SUM(X40:X50) -> 60713612 | Y51: =SUM(Y40:Y50) -> 62130323 | ... BO51: =SUM(BO40:BO50) -> 1.4140466e+10
F53: Maintenance Discounted | G53: =SUM(R53:BO53) -> -1.9611226e+08 | R53: =R42*R35 -> -7400000 | S53: =S42*S35 -> -7184466 | T53: =T42*T35 -> -6975209.7 | U53: =U42*U35 -> -6772048.3 | V53: =V42*V35 -> -6574804.2 | W53: =W42*W35 -> -6383305 | X53: =X42*X35 -> -6197383.5 | Y53: =Y42*Y35 -> -6016877.2 | ... BO53: =BO42*BO35 -> -1738632.2
F54: Scrap Value | G54: =G41 -> 3.2893041e+09 | BO54: =G54 -> 3.2893041e+09
F55: Passenger CS Discounted | G55: =SUM(R55:BO55) -> 9.5798225e+08 | R55: =R35*R44 -> 22463969 | S55: =S35*S44 -> 22424625 | T55: =T35*T44 -> 22385349 | U55: =U35*U44 -> 22346142 | V55: =V35*V44 -> 22307004 | W55: =W35*W44 -> 22267934 | X55: =X35*X44 -> 22228933 | Y55: =Y35*Y44 -> 22190000 | ... BO55: =BO35*BO44 -> 13584493
F56: Freight CS Discounted | G56: =SUM(R56:BO56) -> 1.6319342e+09 | R56: =R45*R35 -> 38267640 | S56: =S45*S35 -> 38200616 | T56: =T45*T35 -> 38133710 | U56: =U45*U35 -> 38066920 | V56: =V45*V35 -> 38000248 | W56: =W45*W35 -> 37933692 | X56: =X45*X35 -> 37867253 | Y56: =Y45*Y35 -> 37800930 | ... BO56: =BO45*BO35 -> 23141346
F57: Air Pollution Discounted | G57: =SUM(R57:BO57) -> 41465828 | R57: =R47*R35 -> 6302590.1 | S57: =S47*S35 -> 5347818.6 | T57: =T47*T35 -> 4537684.3 | U57: =U47*U35 -> 3850276.3 | V57: =V47*V35 -> 3267002.8 | W57: =W47*W35 -> 2772088.7 | X57: =X47*X35 -> 2352148.4 | Y57: =Y47*Y35 -> 1995824.4 | ... BO57: =BO47*BO35 -> 1326.1827
F58: Global Warming Discounted | G58: =SUM(R58:BO58) -> 29590502 | R58: =R48*R35 -> 4497602.3 | S58: =S48*S35 -> 3816266.2 | T58: =T48*T35 -> 3238144.9 | U58: =U48*U35 -> 2747602.4 | V58: =V48*V35 -> 2331371.6 | W58: =W48*W35 -> 1978195 | X58: =X48*X35 -> 1678520.8 | Y58: =Y48*Y35 -> 1424243.8 | ... BO58: =BO48*BO35 -> 946.37954
F59: Traffic Accidents Discounted | G59: =SUM(R59:BO59) -> -84902592 | R59: =R49*R35 -> -3203671.1 | S59: =S49*S35 -> -3110360.3 | T59: =T49*T35 -> -3019767.3 | U59: =U49*U35 -> -2931812.9 | V59: =V49*V35 -> -2846420.3 | W59: =W49*W35 -> -2763514.8 | X59: =X49*X35 -> -2683024.1 | Y59: =Y49*Y35 -> -2604877.8 | ... BO59: =BO49*BO35 -> -752703.46
F60: Noise Pollution | G60: =SUM(R60:BO60) -> -1.3922739e+08 | R60: =R50*R35 -> -5253535.2 | S60: =S50*S35 -> -5100519.6 | T60: =T50*T35 -> -4951960.8 | U60: =U50*U35 -> -4807728.9 | V60: =V50*V35 -> -4667698 | W60: =W50*W35 -> -4531745.6 | X60: =X50*X35 -> -4399753 | Y60: =Y50*Y35 -> -4271604.9 | ... BO60: =BO50*BO35 -> -1234319.6
F61: Discounted Sum | H61: =H35*H51 -> -1.8814829e+09 | I61: =I35*I51 -> -1.8266825e+09 | J61: =J35*J51 -> -1.7734781e+09 | K61: =K35*K51 -> -1.7218234e+09 | L61: =L35*L51 -> -1.6716732e+09 | M61: =M35*M51 -> -1.6229837e+09 | N61: =N35*N51 -> -1575712334 | O61: =O35*O51 -> -1529817800 | ... BN61: =BN35*BN51 -> 33470630 | BO61: =(BO35*(BO51-BO41))+BO54 -> 3.3223065e+09
F63: NPV | G63: =SUM(H61:BO61) -> -1.1000879e+10
F64: BCR | G64: =-SUM(G53:G60)/G40 -> 0.33452685
F65: IRR | G65: 0.0059987939 | H65: Calculated with Goal Seek
J67: 2020 | K67: 2021 | L67: 2022 | M67: 2023 | N67: 2024 | O67: 2025 | P67: 2026 | Q67: 2027 | R67: 2028 | S67: 2029 | T67: 2030 | U67: 2031 | V67: 2032 | W67: 2033 | X67: 2034 | Y67: 2035 | Z67: 2036 | AA67: 2037 | AB67: 2038 | AC67: 2039 | AD67: 2040 | AE67: 2041 | AF67: 2042 | AG67: 2043 | AH67: 2044 | AI67: 2045 | AJ67: 2046 | AK67: 2047 | AL67: 2048 | AM67: 2049 | AN67: 2050 | AO67: 2051 | AP67: 2052 | AQ67: 2053 | AR67: 2054 | AS67: 2055 | AT67: 2056 | AU67: 2057 | AV67: 2058 | AW67: 2059 | AX67: 2060 | AY67: 2061 | AZ67: 2062 | BA67: 2063 | BB67: 2064 | BC67: 2065 | BD67: 2066 | BE67: 2067 | BF67: 2068 | BG67: 2069 | BH67: 2070 | BI67: 2071 | BJ67: 2072 | BK67: 2073 | BL67: 2074 | BM67: 2075 | BN67: 2076 | BO67: 2077
D68: Scenario 10 | F68: Year | G68: Total | J68: -8 | K68: -7 | L68: -6 | M68: -5 | N68: -4 | O68: -3 | P68: -2 | Q68: -1 | R68: 0 | S68: 1 | T68: 2 | U68: 3 | V68: 4 | W68: 5 | X68: 6 | Y68: 7 | Z68: 8 | AA68: 9 | AB68: 10 | AC68: 11 | AD68: 12 | AE68: 13 | AF68: 14 | AG68: 15 | AH68: 16 | AI68: 17 | AJ68: 18 | AK68: 19 | AL68: 20 | AM68: 21 | AN68: 22 | AO68: 23 | AP68: 24 | AQ68: 25 | AR68: 26 | AS68: 27 | AT68: 28 | AU68: 29 | AV68: 30 | AW68: 31 | AX68: 32 | AY68: 33 | AZ68: 34 | BA68: 35 | BB68: 36 | BC68: 37 | BD68: 38 | BE68: 39 | BF68: 40 | BG68: 41 | BH68: 42 | BI68: 43 | BJ68: 44 | BK68: 45 | BL68: 46 | BM68: 47 | BN68: 48 | BO68: 49
F69: Discount Factor | J69: =1/((1+$C$5)^J68) -> 1.2667701 | K69: =1/((1+$C$5)^K68) -> 1.2298739 | L69: =1/((1+$C$5)^L68) -> 1.1940523 | M69: =1/((1+$C$5)^M68) -> 1.1592741 | N69: =1/((1+$C$5)^N68) -> 1.1255088 | O69: =1/((1+$C$5)^O68) -> 1.092727 | P69: =1/((1+$C$5)^P68) -> 1.0609 | Q69: =1/((1+$C$5)^Q68) -> 1.03 | R69: 1 | S69: =1/((1+$C$5)^S68) -> 0.97087379 | T69: =1/((1+$C$5)^T68) -> 0.94259591 | U69: =1/((1+$C$5)^U68) -> 0.91514166 | V69: =1/((1+$C$5)^V68) -> 0.88848705 | W69: =1/((1+$C$5)^W68) -> 0.86260878 | X69: =1/((1+$C$5)^X68) -> 0.83748426 | Y69: =1/((1+$C$5)^Y68) -> 0.81309151 | Z69: =1/((1+$C$5)^Z68) -> 0.78940923 | ... BO69: =1/((1+$C$5)^BO68) -> 0.23495029
F70: Traffic Growth | R70: 1 | S70: =(1+$C$3)^S68 -> 1.014 | T70: =(1+$C$3)^T68 -> 1.028196 | U70: =(1+$C$3)^U68 -> 1.0425907 | V70: =(1+$C$3)^V68 -> 1.057187 | W70: =(1+$C$3)^W68 -> 1.0719876 | X70: =(1+$C$3)^X68 -> 1.0869955 | Y70: =(1+$C$3)^Y68 -> 1.1022134 | Z70: =(1+$C$3)^Z68 -> 1.1176444 | ... AK70: =(1+$C$3)^AK68 -> 1.3023303 | AL70: =AK70 -> 1.3023303 | AM70: =AL70 -> 1.3023303 | AN70: =AM70 -> 1.3023303 | AO70: =AN70 -> 1.3023303 | AP70: =AO70 -> 1.3023303 | AQ70: =AP70 -> 1.3023303 | AR70: =AQ70 -> 1.3023303 | AS70: =AR70 -> 1.3023303 | ... BO70: =BN70 -> 1.3023303
F71: Price Growth | R71: 1 | S71: =(1+$C$2)^S68 -> 1.014 | T71: =(1+$C$2)^T68 -> 1.028196 | U71: =(1+$C$2)^U68 -> 1.0425907 | V71: =(1+$C$2)^V68 -> 1.057187 | W71: =(1+$C$2)^W68 -> 1.0719876 | X71: =(1+$C$2)^X68 -> 1.0869955 | Y71: =(1+$C$2)^Y68 -> 1.1022134 | Z71: =(1+$C$2)^Z68 -> 1.1176444 | ... BO71: =(1+$C$2)^BO68 -> 1.9763315
F72: Emission Growth | R72: 1 | S72: =(1+$C$4)^S68 -> 0.85 | T72: =(1+$C$4)^T68 -> 0.7225 | U72: =(1+$C$4)^U68 -> 0.614125 | V72: =(1+$C$4)^V68 -> 0.52200625 | W72: =(1+$C$4)^W68 -> 0.44370531 | X72: =(1+$C$4)^X68 -> 0.37714952 | Y72: =(1+$C$4)^Y68 -> 0.32057709 | Z72: =(1+$C$4)^Z68 -> 0.27249053 | ... BO72: =(1+$C$4)^BO68 -> 0.00034795843
F74: Construction Cost Discounted | G74: =SUM(H74:Q74) -> -1.1300047e+10 | J74: =-($I$4/-(MIN($J$68:$Q$68)))*J69 -> -1.5628776e+09 | K74: =-($I$4/-(MIN($J$68:$Q$68)))*K69 -> -1.5173569e+09 | L74: =-($I$4/-(MIN($J$68:$Q$68)))*L69 -> -1.473162e+09 | M74: =-($I$4/-(MIN($J$68:$Q$68)))*M69 -> -1.4302544e+09 | N74: =-($I$4/-(MIN($J$68:$Q$68)))*N69 -> -1.3885965e+09 | O74: =-($I$4/-(MIN($J$68:$Q$68)))*O69 -> -1.3481519e+09 | P74: =-($I$4/-(MIN($J$68:$Q$68)))*P69 -> -1308885375 | Q74: =-($I$4/-(MIN($J$68:$Q$68)))*Q69 -> -1270762500
F75: Scrap Value | G75: =I4*BO69 -> 2.3189594e+09 | BO75: =I4 -> 9870000000
F76: Maintenance | G76: =SUM(S76:BO76) -> -117600000 | R76: =-$J$4 -> -2400000 | S76: =-$J$4 -> -2400000 | T76: =-$J$4 -> -2400000 | U76: =-$J$4 -> -2400000 | V76: =-$J$4 -> -2400000 | W76: =-$J$4 -> -2400000 | X76: =-$J$4 -> -2400000 | Y76: =-$J$4 -> -2400000 | ... BO76: =-$J$4 -> -2400000
F78: Passenger CS | G78: =SUM(R78:BO78) -> 2.1203134e+10 | R78: =$M$4/(((1+C2)^(2035-$R$67))*((1+C3)^(2035-$R$67))) -> 2.3569911e+08 | S78: =$R$78*S36*S37 -> 2.4234488e+08 | T78: =$R$78*T36*T37 -> 2.4917804e+08 | U78: =$R$78*U36*U37 -> 2.5620386e+08 | V78: =$R$78*V36*V37 -> 2.6342779e+08 | W78: =$R$78*W36*W37 -> 2.708554e+08 | X78: =$R$78*X36*X37 -> 2.7849244e+08 | Y78: =$R$78*Y36*Y37 -> 2.8634481e+08 | Z78: =$R$78*Z36*Z37 -> 2.9441859e+08 | ... BO78: =$R$78*BO36*BO37 -> 6.0665096e+08
F79: Freight CS | G79: =SUM(R79:BO79) -> 1.3556016e+10 | R79: =$N$4/(((1+C2)^(2035-$R$67))*((1+C3)^(2035-$R$67))) -> 1.5069192e+08 | S79: =$R$79*S36*S37 -> 1.5494083e+08 | T79: =$R$79*T36*T37 -> 1.5930954e+08 | U79: =$R$79*U36*U37 -> 1.6380144e+08 | V79: =$R$79*V36*V37 -> 1.6841998e+08 | W79: =$R$79*W36*W37 -> 1.7316875e+08 | X79: =$R$79*X36*X37 -> 1.7805142e+08 | Y79: =$R$79*Y36*Y37 -> 1.8307176e+08 | Z79: =$R$79*Z36*Z37 -> 1.8823365e+08 | ... BO79: =$R$79*BO36*BO37 -> 3.8785636e+08
F81: Air Pollution | G81: =SUM(R81:BO81) -> 50923000 | R81: =$P$4 -> 6466250.5 | S81: =$R$81*S36*S37*S38 -> 5651286.9 | T81: =$R$81*T36*T37*T38 -> 4939036 | U81: =$R$81*U36*U37*U38 -> 4316552.5 | V81: =$R$81*V36*V37*V38 -> 3772522.7 | W81: =$R$81*W36*W37*W38 -> 3297058.9 | X81: =$R$81*X36*X37*X38 -> 2881519.3 | Y81: =$R$81*Y36*Y37*Y38 -> 2518351.6 | Z81: =$R$81*Z36*Z37*Z38 -> 2200955.2 | ... BO81: =$R$81*BO36*BO37*BO38 -> 5791.0968
F82: Global Warming | G82: =SUM(R82:BO82) -> -3.1395918e+08 | R82: =$Q$4 -> -39866832 | S82: =$R$82*S36*S37*S38 -> -34842279 | T82: =$R$82*T36*T37*T38 -> -30450989 | U82: =$R$82*U36*U37*U38 -> -26613147 | V82: =$R$82*V36*V37*V38 -> -23259002 | W82: =$R$82*W36*W37*W38 -> -20327590 | X82: =$R$82*X36*X37*X38 -> -17765635 | Y82: =$R$82*Y36*Y37*Y38 -> -15526572 | Z82: =$R$82*Z36*Z37*Z38 -> -13569705 | ... BO82: =$R$82*BO36*BO37*BO38 -> -35704.259
F83: Traffic Accidents | G83: =SUM(R83:BO83) -> -1.0383926e+09 | R83: =$R$4 -> -20767851 | S83: =$R$4 -> -20767851 | T83: =$R$4 -> -20767851 | U83: =$R$4 -> -20767851 | V83: =$R$4 -> -20767851 | W83: =$R$4 -> -20767851 | X83: =$R$4 -> -20767851 | Y83: =$R$4 -> -20767851 | ... BO83: =$R$4 -> -20767851
F84: Noise Pollution | G84: =SUM(R84:BO84) -> -1.0230103e+09 | R84: =$S$4 -> -20460206 | S84: =$S$4 -> -20460206 | T84: =$S$4 -> -20460206 | U84: =$S$4 -> -20460206 | V84: =$S$4 -> -20460206 | W84: =$S$4 -> -20460206 | X84: =$S$4 -> -20460206 | Y84: =$S$4 -> -20460206 | ... BO84: =$S$4 -> -20460206
F86: Non Discounted Sum | J86: =SUM(J74:J85)/J69 -> -1233750000 | K86: =SUM(K74:K85)/K69 -> -1233750000 | L86: =SUM(L74:L85)/L69 -> -1233750000 | M86: =SUM(M74:M85)/M69 -> -1233750000 | N86: =SUM(N74:N85)/N69 -> -1233750000 | O86: =SUM(O74:O85)/O69 -> -1233750000 | P86: =SUM(P74:P85)/P69 -> -1233750000 | Q86: =SUM(Q74:Q85)/Q69 -> -1233750000 | R86: =SUM(R74:R84) -> 3.093624e+08 | S86: =SUM(S74:S84) -> 3.2446667e+08 | T86: =SUM(T74:T84) -> 3.3934757e+08 | U86: =SUM(U74:U84) -> 3.5408065e+08 | V86: =SUM(V74:V84) -> 3.6873323e+08 | W86: =SUM(W74:W84) -> 3.8336556e+08 | X86: =SUM(X74:X84) -> 3.9803168e+08 | Y86: =SUM(Y74:Y84) -> 4.1278029e+08 | ... BO86: =SUM(BO74:BO84) -> 1.0820849e+10
F88: Maintenance Discounted | G88: =SUM(R88:BO88) -> -63603977 | R88: =R76*R35 -> -2400000 | S88: =S76*S35 -> -2330097.1 | T88: =T76*T35 -> -2262230.2 | U88: =U76*U35 -> -2196340 | V88: =V76*V35 -> -2132368.9 | W88: =W76*W35 -> -2070261.1 | X88: =X76*X35 -> -2009962.2 | Y88: =Y76*Y35 -> -1951419.6 | ... BO88: =BO76*BO35 -> -563880.7
F89: Scrap Value | G89: =G75 -> 2.3189594e+09 | BO89: =G89 -> 2.3189594e+09
F90: Passenger CS Discounted | G90: =SUM(R90:BO90) -> 1.0051454e+10 | R90: =R35*R78 -> 2.3569911e+08 | S90: =S35*S78 -> 2.352863e+08 | T90: =T35*T78 -> 2.348742e+08 | U90: =U35*U78 -> 2.3446283e+08 | V90: =V35*V78 -> 2.3405218e+08 | W90: =W35*W78 -> 2.3364225e+08 | X90: =X35*X78 -> 2.3323303e+08 | Y90: =Y35*Y78 -> 2.3282453e+08 | ... BO90: =BO35*BO78 -> 1.4253282e+08
F91: Freight CS Discounted | G91: =SUM(R91:BO91) -> 6.4262992e+09 | R91: =R35*R79 -> 1.5069192e+08 | S91: =S35*S79 -> 1.5042799e+08 | T91: =T35*T79 -> 1.5016452e+08 | U91: =U35*U79 -> 1.4990152e+08 | V91: =V35*V79 -> 1.4963897e+08 | W91: =W35*W79 -> 1.4937689e+08 | X91: =X35*X79 -> 1.4911526e+08 | Y91: =Y35*Y79 -> 1.4885409e+08 | ... BO91: =BO35*BO79 -> 91126965
F92: Air Pollution Discounted | G92: =SUM(R92:BO92) -> 42542578 | R92: =R35*R81 -> 6466250.5 | S92: =S35*S81 -> 5486686.3 | T92: =T35*T81 -> 4655515.2 | U92: =U35*U81 -> 3950257 | V92: =V35*V81 -> 3351837.6 | W92: =W35*W81 -> 2844071.9 | X92: =X35*X81 -> 2413227.1 | Y92: =Y35*Y81 -> 2047650.3 | ... BO92: =BO35*BO81 -> 1360.6199
F93: Global Warming Discounted | G93: =SUM(R93:BO93) -> -2.6229077e+08 | R93: =R35*R82 -> -39866832 | S93: =S35*S82 -> -33827456 | T93: =T35*T82 -> -28702977 | U93: =U35*U82 -> -24354799 | V93: =V35*V82 -> -20665322 | W93: =W35*W82 -> -17534758 | X93: =X35*X82 -> -14878440 | Y93: =Y35*Y82 -> -12624524 | ... BO93: =BO35*BO82 -> -8388.7261
F94: Traffic Accidents Discounted | G94: =SUM(R94:BO94) -> -5.5038247e+08 | R94: =R35*R83 -> -20767851 | S94: =S35*S83 -> -20162962 | T94: =T35*T83 -> -19575692 | U94: =U35*U83 -> -19005526 | V94: =V35*V83 -> -18451967 | W94: =W35*W83 -> -17914531 | X94: =X35*X83 -> -17392749 | Y94: =Y35*Y83 -> -16886164 | ... BO94: =BO35*BO83 -> -4879412.7
F95: Noise Pollution | G95: =SUM(R95:BO95) -> -5.4222937e+08 | R95: =R35*R84 -> -20460206 | S95: =S35*S84 -> -19864278 | T95: =T35*T84 -> -19285707 | U95: =U35*U84 -> -18723987 | V95: =V35*V84 -> -18178628 | W95: =W35*W84 -> -17649154 | X95: =X35*X84 -> -17135101 | Y95: =Y35*Y84 -> -16636020 | ... BO95: =BO35*BO84 -> -4807131.4
F96: Discounted Sum | J96: =J35*J86 -> -1.5628776e+09 | K96: =K35*K86 -> -1.5173569e+09 | L96: =L35*L86 -> -1.473162e+09 | M96: =M35*M86 -> -1.4302544e+09 | N96: =N35*N86 -> -1.3885965e+09 | O96: =O35*O86 -> -1.3481519e+09 | P96: =P35*P86 -> -1308885375 | Q96: =Q35*Q86 -> -1270762500 | ... BN96: =BN35*BN86 -> 2.2678039e+08 | BO96: =(BO35*(BO86-BO75))+BO89 -> 2.5423617e+09
F98: NPV | G98: =SUM(J96:BO96) -> 6.1207018e+09
F99: BCR | G99: =SUM(G88:G95)/-G74 -> 1.5416528
F100: IRR | G100: =IRR(J86:BO86) -> 0.045383536
K103: 2022 | L103: 2023 | M103: 2024 | N103: 2025 | O103: 2026 | P103: 2027 | Q103: 2028 | R103: 2029 | S103: 2030 | T103: 2031 | U103: 2032 | V103: 2033 | W103: 2034 | X103: 2035 | Y103: 2036 | Z103: 2037 | AA103: 2038 | AB103: 2039 | AC103: 2040 | AD103: 2041 | AE103: 2042 | AF103: 2043 | AG103: 2044 | AH103: 2045 | AI103: 2046 | AJ103: 2047 | AK103: 2048 | AL103: 2049 | AM103: 2050 | AN103: 2051 | AO103: 2052 | AP103: 2053 | AQ103: 2054 | AR103: 2055 | AS103: 2056 | AT103: 2057 | AU103: 2058 | AV103: 2059 | AW103: 2060 | AX103: 2061 | AY103: 2062 | AZ103: 2063 | BA103: 2064 | BB103: 2065 | BC103: 2066 | BD103: 2067 | BE103: 2068 | BF103: 2069 | BG103: 2070 | BH103: 2071 | BI103: 2072 | BJ103: 2073 | BK103: 2074 | BL103: 2075 | BM103: 2076 | BN103: 2077 | BO103: 2078
D104: Scenario 18 | F104: Year | G104: Total | K104: -7 | L104: -6 | M104: -5 | N104: -4 | O104: -3 | P104: -2 | Q104: -1 | R104: 0 | S104: 1 | T104: 2 | U104: 3 | V104: 4 | W104: 5 | X104: 6 | Y104: 7 | Z104: 8 | AA104: 9 | AB104: 10 | AC104: 11 | AD104: 12 | AE104: 13 | AF104: 14 | AG104: 15 | AH104: 16 | AI104: 17 | AJ104: 18 | AK104: 19 | AL104: 20 | AM104: 21 | AN104: 22 | AO104: 23 | AP104: 24 | AQ104: 25 | AR104: 26 | AS104: 27 | AT104: 28 | AU104: 29 | AV104: 30 | AW104: 31 | AX104: 32 | AY104: 33 | AZ104: 34 | BA104: 35 | BB104: 36 | BC104: 37 | BD104: 38 | BE104: 39 | BF104: 40 | BG104: 41 | BH104: 42 | BI104: 43 | BJ104: 44 | BK104: 45 | BL104: 46 | BM104: 47 | BN104: 48 | BO104: 49
F105: Discount Factor | K105: =1/((1+$C$5)^K104) -> 1.2298739 | L105: =1/((1+$C$5)^L104) -> 1.1940523 | M105: =1/((1+$C$5)^M104) -> 1.1592741 | N105: =1/((1+$C$5)^N104) -> 1.1255088 | O105: =1/((1+$C$5)^O104) -> 1.092727 | P105: =1/((1+$C$5)^P104) -> 1.0609 | Q105: =1/((1+$C$5)^Q104) -> 1.03 | R105: =1/((1+$C$5)^R104) -> 1 | ... BO105: =1/((1+$C$5)^BO104) -> 0.23495029
F106: Traffic Growth | R106: =(1+$C$3)^R104 -> 1 | S106: =(1+$C$3)^S104 -> 1.014 | T106: =(1+$C$3)^T104 -> 1.028196 | U106: =(1+$C$3)^U104 -> 1.0425907 | V106: =(1+$C$3)^V104 -> 1.057187 | W106: =(1+$C$3)^W104 -> 1.0719876 | X106: =(1+$C$3)^X104 -> 1.0869955 | Y106: =(1+$C$3)^Y104 -> 1.1022134 | ... AK106: =(1+$C$3)^AK104 -> 1.3023303 | AL106: =AK106 -> 1.3023303 | AM106: =AL106 -> 1.3023303 | AN106: =AM106 -> 1.3023303 | AO106: =AN106 -> 1.3023303 | AP106: =AO106 -> 1.3023303 | AQ106: =AP106 -> 1.3023303 | AR106: =AQ106 -> 1.3023303 | AS106: =AR106 -> 1.3023303 | ... BO106: =BN106 -> 1.3023303
F107: Price Growth | R107: =(1+$C$2)^R104 -> 1 | S107: =(1+$C$2)^S104 -> 1.014 | T107: =(1+$C$2)^T104 -> 1.028196 | U107: =(1+$C$2)^U104 -> 1.0425907 | V107: =(1+$C$2)^V104 -> 1.057187 | W107: =(1+$C$2)^W104 -> 1.0719876 | X107: =(1+$C$2)^X104 -> 1.0869955 | Y107: =(1+$C$2)^Y104 -> 1.1022134 | ... BO107: =(1+$C$2)^BO104 -> 1.9763315
F108: Emission Growth | R108: =(1+$C$4)^R104 -> 1 | S108: =(1+$C$4)^S104 -> 0.85 | T108: =(1+$C$4)^T104 -> 0.7225 | U108: =(1+$C$4)^U104 -> 0.614125 | V108: =(1+$C$4)^V104 -> 0.52200625 | W108: =(1+$C$4)^W104 -> 0.44370531 | X108: =(1+$C$4)^X104 -> 0.37714952 | Y108: =(1+$C$4)^Y104 -> 0.32057709 | ... BO108: =(1+$C$4)^BO104 -> 0.00034795843
F110: Construction Cost Discounted | G110: =SUM(H110:Q110) -> -7.3849716e+09 | K110: =-($I$5/-(MIN($K$104:$Q$104)))*K105 -> -1.1508105e+09 | L110: =-($I$5/-(MIN($K$104:$Q$104)))*L105 -> -1.1172918e+09 | M110: =-($I$5/-(MIN($K$104:$Q$104)))*M105 -> -1.0847493e+09 | N110: =-($I$5/-(MIN($K$104:$Q$104)))*N105 -> -1.0531547e+09 | O110: =-($I$5/-(MIN($K$104:$Q$104)))*O105 -> -1.0224803e+09 | P110: =-($I$5/-(MIN($K$104:$Q$104)))*P105 -> -9.9269929e+08 | Q110: =-($I$5/-(MIN($K$104:$Q$104)))*Q105 -> -9.6378571e+08
F111: Scrap Value | G111: =I5*BO105 -> 1.5389244e+09 | BO111: =I5 -> 6550000000
F112: Maintenance | G112: =SUM(S112:BO112) -> -196000000 | R112: =-$J$5 -> -4000000 | S112: =-$J$5 -> -4000000 | T112: =-$J$5 -> -4000000 | U112: =-$J$5 -> -4000000 | V112: =-$J$5 -> -4000000 | W112: =-$J$5 -> -4000000 | X112: =-$J$5 -> -4000000 | Y112: =-$J$5 -> -4000000 | ... BO112: =-$J$5 -> -4000000
F114: Passenger CS | G114: =SUM(R114:BO114) -> 7.6822589e+09 | R114: =$M$5/(((1+$C$2)^(2035-$R$103))*((1+$C$3)^(2035-$R$103))) -> 85397828 | S114: =$R$114*S106*S107 -> 87805706 | T114: =$R$114*T106*T107 -> 90281475 | U114: =$R$114*U106*U107 -> 92827052 | V114: =$R$114*V106*V107 -> 95444403 | W114: =$R$114*W106*W107 -> 98135554 | X114: =$R$114*X106*X107 -> 1.0090258e+08 | Y114: =$R$114*Y106*Y107 -> 1.0374763e+08 | Z114: =$R$114*Z106*Z107 -> 1.066729e+08 | ... BO114: =$R$114*BO106*BO107 -> 2.1980004e+08
F115: Freight CS | G115: =SUM(R115:BO115) -> 3.7423043e+09 | R115: =$N$5/(((1+$C$2)^(2035-$R$103))*((1+$C$3)^(2035-$R$103))) -> 41600351 | S115: =$R$115*S106*S107 -> 42773314 | T115: =$R$115*T106*T107 -> 43979351 | U115: =$R$115*U106*U107 -> 45219392 | V115: =$R$115*V106*V107 -> 46494398 | W115: =$R$115*W106*W107 -> 47805355 | X115: =$R$115*X106*X107 -> 49153274 | Y115: =$R$115*Y106*Y107 -> 50539200 | Z115: =$R$115*Z106*Z107 -> 51964203 | ... BO115: =$R$115*BO106*BO107 -> 1.070725e+08
F117: Air Pollution | G117: =SUM(R117:BO117) -> 2.7615269e+08 | R117: =$P$5 -> 35066129 | S117: =$R$117*S106*S107*S108 -> 30646626 | T117: =$R$117*T106*T107*T108 -> 26784127 | U117: =$R$117*U106*U107*U108 -> 23408433 | V117: =$R$117*V106*V107*V108 -> 20458188 | W117: =$R$117*W106*W107*W108 -> 17879773 | X117: =$R$117*X106*X107*X108 -> 15626325 | Y117: =$R$117*Y106*Y107*Y108 -> 13656886 | Z117: =$R$117*Z106*Z107*Z108 -> 11935662 | ... BO117: =$R$117*BO106*BO107*BO108 -> 31404.807
F118: Global Warming | G118: =SUM(R118:BO118) -> 3.3534784e+08 | R118: =$Q$5 -> 42582785 | S118: =$R$118*S106*S107*S108 -> 37215932 | T118: =$R$118*T106*T107*T108 -> 32525481 | U118: =$R$118*U106*U107*U108 -> 28426184 | V118: =$R$118*V106*V107*V108 -> 24843536 | W118: =$R$118*W106*W107*W108 -> 21712420 | X118: =$R$118*X106*X107*X108 -> 18975930 | Y118: =$R$118*Y106*Y107*Y108 -> 16584329 | Z118: =$R$118*Z106*Z107*Z108 -> 14494150 | ... BO118: =$R$118*BO106*BO107*BO108 -> 38136.634
F119: Traffic Accidents | G119: =SUM(R119:BO119) -> 1.1367908e+08 | R119: =$R$5 -> 2273581.6 | S119: =$R$119 -> 2273581.6 | T119: =$R$119 -> 2273581.6 | U119: =$R$119 -> 2273581.6 | V119: =$R$119 -> 2273581.6 | W119: =$R$119 -> 2273581.6 | X119: =$R$119 -> 2273581.6 | Y119: =$R$119 -> 2273581.6 | Z119: =$R$119 -> 2273581.6 | ... BO119: =$R$119 -> 2273581.6
F120: Noise Pollution | G120: =SUM(R120:BO120) -> 4.9741593e+08 | R120: =$S$5 -> 9948318.7 | S120: =$R$120 -> 9948318.7 | T120: =$R$120 -> 9948318.7 | U120: =$R$120 -> 9948318.7 | V120: =$R$120 -> 9948318.7 | W120: =$R$120 -> 9948318.7 | X120: =$R$120 -> 9948318.7 | Y120: =$R$120 -> 9948318.7 | Z120: =$R$120 -> 9948318.7 | ... BO120: =$R$120 -> 9948318.7
F121: Non Discounted Sum | K121: =SUM(K110:K120)/K105 -> -9.3571429e+08 | L121: =SUM(L110:L120)/L105 -> -9.3571429e+08 | M121: =SUM(M110:M120)/M105 -> -9.3571429e+08 | N121: =SUM(N110:N120)/N105 -> -9.3571429e+08 | O121: =SUM(O110:O120)/O105 -> -9.3571429e+08 | P121: =SUM(P110:P120)/P105 -> -9.3571429e+08 | Q121: =SUM(Q110:Q120)/Q105 -> -9.3571429e+08 | R121: =SUM(R110:R120) -> 2.1286899e+08 | S121: =SUM(S110:S120) -> 2.0666348e+08 | T121: =SUM(T110:T120) -> 2.0179233e+08 | U121: =SUM(U110:U120) -> 1.9810296e+08 | V121: =SUM(V110:V120) -> 1.9546243e+08 | W121: =SUM(W110:W120) -> 1.93755e+08 | X121: =SUM(X110:X120) -> 1.9288001e+08 | Y121: =SUM(Y110:Y120) -> 1.9274995e+08 | ... BO121: =SUM(BO110:BO120) -> 6.885164e+09
F123: Maintenance Discounted | G123: =SUM(R123:BO123) -> -1.0600663e+08 | R123: =R112*R105 -> -4000000 | S123: =S112*S105 -> -3883495.1 | T123: =T112*T105 -> -3770383.6 | U123: =U112*U105 -> -3660566.6 | V123: =V112*V105 -> -3553948.2 | W123: =W112*W105 -> -3450435.1 | X123: =X112*X105 -> -3349937 | Y123: =Y112*Y105 -> -3252366 | ... BO123: =BO112*BO105 -> -939801.17
F124: Scrap Value | G124: =G111 -> 1.5389244e+09 | BO124: =G124 -> 1.5389244e+09
F125: Passenger CS Discounted | G125: =SUM(R125:BO125) -> 3.6418142e+09 | R125: =R105*R114 -> 85397828 | S125: =S105*S114 -> 85248258 | T125: =T105*T114 -> 85098949 | U125: =U105*U114 -> 84949902 | V125: =V105*V114 -> 84801116 | W125: =W105*W114 -> 84652591 | X125: =X105*X114 -> 84504325 | Y125: =Y105*Y114 -> 84356320 | ... BO125: =BO105*BO114 -> 51642084
F126: Freight CS Discounted | G126: =SUM(R126:BO126) -> 1.7740586e+09 | R126: =R115*R105 -> 41600351 | S126: =S115*S105 -> 41527490 | T126: =T115*T105 -> 41454756 | U126: =U115*U105 -> 41382150 | V126: =V115*V105 -> 41309671 | W126: =W115*W105 -> 41237319 | X126: =X115*X105 -> 41165093 | Y126: =Y115*Y105 -> 41092995 | ... BO126: =BO115*BO105 -> 25156715
F127: Air Pollution Discounted | G127: =SUM(R127:BO127) -> 2.3070612e+08 | R127: =R117*R105 -> 35066129 | S127: =S117*S105 -> 29754005 | T127: =T117*T105 -> 25246609 | U127: =U117*U105 -> 21422032 | V127: =V117*V105 -> 18176835 | W127: =W117*W105 -> 15423249 | X127: =X117*X105 -> 13086801 | Y127: =Y117*Y105 -> 11104298 | ... BO127: =BO117*BO105 -> 7378.5685
F128: Global Warming Discounted | G128: =SUM(R128:BO128) -> 2.8015949e+08 | R128: =R118*R105 -> 42582785 | S128: =S118*S105 -> 36131972 | T128: =T118*T105 -> 30658385 | U128: =U118*U105 -> 26013985 | V128: =V118*V105 -> 22073160 | W128: =W118*W105 -> 18729324 | X128: =X118*X105 -> 15892043 | Y128: =Y118*Y105 -> 13484577 | ... BO128: =BO118*BO105 -> 8960.2133
F129: Traffic Accidents Discounted | G129: =SUM(R129:BO129) -> 60253679 | R129: =R119*R105 -> 2273581.6 | S129: =S119*S105 -> 2207360.8 | T129: =T119*T105 -> 2143068.7 | U129: =U119*U105 -> 2080649.2 | V129: =V119*V105 -> 2020047.8 | W129: =W119*W105 -> 1961211.4 | X129: =X119*X105 -> 1904088.8 | Y129: =Y119*Y105 -> 1848629.9 | ... BO129: =BO119*BO105 -> 534178.66
F130: Noise Pollution | G130: =SUM(R130:BO130) -> 2.6364693e+08 | R130: =R120*R105 -> 9948318.7 | S130: =S120*S105 -> 9658561.8 | T130: =T120*T105 -> 9377244.5 | U130: =U120*U105 -> 9104120.9 | V130: =V120*V105 -> 8838952.3 | W130: =W120*W105 -> 8581507.1 | X130: =X120*X105 -> 8331560.3 | Y130: =Y120*Y105 -> 8088893.5 | ... BO130: =BO120*BO105 -> 2337360.4
F131: Discounted Sum | K131: =K105*K121 -> -1.1508105e+09 | L131: =L105*L121 -> -1.1172918e+09 | M131: =M105*M121 -> -1.0847493e+09 | N131: =N105*N121 -> -1.0531547e+09 | O131: =O105*O121 -> -1.0224803e+09 | P131: =P105*P121 -> -9.9269929e+08 | Q131: =Q105*Q121 -> -9.6378571e+08 | R131: =R105*R121 -> 2.1286899e+08 | ... BN131: =BN105*BN121 -> 80019829 | BO131: =(BO105*(BO121-BO111))+BO124 -> 1.6176713e+09
F133: NPV | G133: =SUM(K131:BO131) -> 2.9858524e+08
F134: BCR | G134: =-SUM(G123:G130)/G110 -> 1.0404315
F135: IRR | G135: =IRR(K121:BO121) -> 0.031345361
H142: 2020 | I142: 2021 | J142: 2022 | K142: 2023 | L142: 2024 | M142: 2025 | N142: 2026 | O142: 2027 | P142: 2028 | Q142: 2029 | R142: 2027 | S142: 2028 | T142: 2029 | U142: 2030 | V142: 2031 | W142: 2032 | X142: 2033 | Y142: 2034 | Z142: 2035 | AA142: 2036 | AB142: 2037 | AC142: 2038 | AD142: 2039 | AE142: 2040 | AF142: 2041 | AG142: 2042 | AH142: 2043 | AI142: 2044 | AJ142: 2045 | AK142: 2046 | AL142: 2047 | AM142: 2048 | AN142: 2049 | AO142: 2050 | AP142: 2051 | AQ142: 2052 | AR142: 2053 | AS142: 2054 | AT142: 2055 | AU142: 2056 | AV142: 2057 | AW142: 2058 | AX142: 2059 | AY142: 2060 | AZ142: 2061 | BA142: 2062 | BB142: 2063 | BC142: 2064 | BD142: 2065 | BE142: 2066 | BF142: 2067 | BG142: 2068 | BH142: 2069 | BI142: 2070 | BJ142: 2071 | BK142: 2072 | BL142: 2073 | BM142: 2074 | BN142: 2075 | BO142: 2076
D143: Scenario 20 | F143: Year | G143: Total | L143: -6 | M143: -5 | N143: -4 | O143: -3 | P143: -2 | Q143: -1 | R143: 0 | S143: 1 | T143: 2 | U143: 3 | V143: 4 | W143: 5 | X143: 6 | Y143: 7 | Z143: 8 | AA143: 9 | AB143: 10 | AC143: 11 | AD143: 12 | AE143: 13 | AF143: 14 | AG143: 15 | AH143: 16 | AI143: 17 | AJ143: 18 | AK143: 19 | AL143: 20 | AM143: 21 | AN143: 22 | AO143: 23 | AP143: 24 | AQ143: 25 | AR143: 26 | AS143: 27 | AT143: 28 | AU143: 29 | AV143: 30 | AW143: 31 | AX143: 32 | AY143: 33 | AZ143: 34 | BA143: 35 | BB143: 36 | BC143: 37 | BD143: 38 | BE143: 39 | BF143: 40 | BG143: 41 | BH143: 42 | BI143: 43 | BJ143: 44 | BK143: 45 | BL143: 46 | BM143: 47 | BN143: 48 | BO143: 49
F144: Discount Factor | L144: =1/((1+$C$5)^L143) -> 1.1940523 | M144: =1/((1+$C$5)^M143) -> 1.1592741 | N144: =1/((1+$C$5)^N143) -> 1.1255088 | O144: =1/((1+$C$5)^O143) -> 1.092727 | P144: =1/((1+$C$5)^P143) -> 1.0609 | Q144: =1/((1+$C$5)^Q143) -> 1.03 | R144: 1 | S144: =1/((1+$C$5)^S143) -> 0.97087379 | T144: =1/((1+$C$5)^T143) -> 0.94259591 | U144: =1/((1+$C$5)^U143) -> 0.91514166 | V144: =1/((1+$C$5)^V143) -> 0.88848705 | W144: =1/((1+$C$5)^W143) -> 0.86260878 | X144: =1/((1+$C$5)^X143) -> 0.83748426 | Y144: =1/((1+$C$5)^Y143) -> 0.81309151 | Z144: =1/((1+$C$5)^Z143) -> 0.78940923 | ... BO144: =1/((1+$C$5)^BO143) -> 0.23495029
F145: Traffic Growth | R145: 1 | S145: =(1+$C$3)^S143 -> 1.014 | T145: =(1+$C$3)^T143 -> 1.028196 | U145: =(1+$C$3)^U143 -> 1.0425907 | V145: =(1+$C$3)^V143 -> 1.057187 | W145: =(1+$C$3)^W143 -> 1.0719876 | X145: =(1+$C$3)^X143 -> 1.0869955 | Y145: =(1+$C$3)^Y143 -> 1.1022134 | Z145: =(1+$C$3)^Z143 -> 1.1176444 | ... AK145: =(1+$C$3)^AK143 -> 1.3023303 | AL145: =$AK$36 -> 1.3023303 | AM145: =$AK$36 -> 1.3023303 | AN145: =$AK$36 -> 1.3023303 | AO145: =$AK$36 -> 1.3023303 | AP145: =$AK$36 -> 1.3023303 | AQ145: =$AK$36 -> 1.3023303 | AR145: =$AK$36 -> 1.3023303 | AS145: =$AK$36 -> 1.3023303 | ... BO145: =$AK$36 -> 1.3023303
F146: Price Growth | R146: 1 | S146: =(1+$C$2)^S143 -> 1.014 | T146: =(1+$C$2)^T143 -> 1.028196 | U146: =(1+$C$2)^U143 -> 1.0425907 | V146: =(1+$C$2)^V143 -> 1.057187 | W146: =(1+$C$2)^W143 -> 1.0719876 | X146: =(1+$C$2)^X143 -> 1.0869955 | Y146: =(1+$C$2)^Y143 -> 1.1022134 | Z146: =(1+$C$2)^Z143 -> 1.1176444 | ... BO146: =(1+$C$2)^BO143 -> 1.9763315
F147: Emission Growth | R147: 1 | S147: =(1+$C$4)^S143 -> 0.85 | T147: =(1+$C$4)^T143 -> 0.7225 | U147: =(1+$C$4)^U143 -> 0.614125 | V147: =(1+$C$4)^V143 -> 0.52200625 | W147: =(1+$C$4)^W143 -> 0.44370531 | X147: =(1+$C$4)^X143 -> 0.37714952 | Y147: =(1+$C$4)^Y143 -> 0.32057709 | Z147: =(1+$C$4)^Z143 -> 0.27249053 | ... BO147: =(1+$C$4)^BO143 -> 0.00034795843
F149: Construction Cost Discounted | G149: =SUM(H149:Q149) -> -2.7427136e+09 | L149: =-($I$6/-(MIN($L$143:$Q$143)))*L144 -> -4.9155153e+08 | M149: =-($I$6/-(MIN($L$143:$Q$143)))*M144 -> -4.7723449e+08 | N149: =-($I$6/-(MIN($L$143:$Q$143)))*N144 -> -4.6333446e+08 | O149: =-($I$6/-(MIN($L$143:$Q$143)))*O144 -> -4.4983928e+08 | P149: =-($I$6/-(MIN($L$143:$Q$143)))*P144 -> -4.3673717e+08 | Q149: =-($I$6/-(MIN($L$143:$Q$143)))*Q144 -> -4.2401667e+08
F150: Scrap Value | G150: =I6*BO144 -> 5.8032722e+08 | BO150: =I6 -> 2470000000
F151: Maintenance | G151: =SUM(S151:BO151) -> -93100000 | R151: =-$J$6 -> -1900000 | S151: =-$J$6 -> -1900000 | T151: =-$J$6 -> -1900000 | U151: =-$J$6 -> -1900000 | V151: =-$J$6 -> -1900000 | W151: =-$J$6 -> -1900000 | X151: =-$J$6 -> -1900000 | Y151: =-$J$6 -> -1900000 | ... BO151: =-$J$6 -> -1900000
BS152: For thescrap value to calculate the IRR do not keep it discounted
...

Sheet Risk Analysis - S01
N2: S01 - Monte Carlo Result | O2: Railway
R3: Consumer Surplus | T3: Construction
M4: Iteration | N4: New Scrap Value | O4: Benefit (before CS + Scrap Value) | P4: Consumer Surplus | Q4: Construction | R4: Random | S4: Beta-PERT | T4: Random | U4: Gamma-Erlang | V4: BCR | X4: No.bins | Y4: Min | Z4: Max | AA4: Range | AB4: Count
M5: 1 | N5: ='CBA Result'!$G$54*_xlfn.GAMMA.INV(T5,IF($O$2="Railway",$D$31,$D$32),IF($O$2="Railway",$F$31,$F$32)) -> 5.0388347e+09 | O5: ='CBA Result'!$G$53+'CBA Result'!$G$57+'CBA Result'!$G$58+'CBA Result'!$G$59+'CBA Result'!$G$60 -> -3.4918591e+08 | P5: ='CBA Result'!$G$55+'CBA Result'!$G$56 -> 2.5899165e+09 | Q5: ='CBA Result'!$G$40 -> -1.6530914e+10 | R5: 0.97578078 | S5: =_xlfn.BETA.INV(R5,IF($O$2="Railway",$I$30,$J$30),IF($O$2="Railway",$I$31,$J$31),IF($O$2="Railway",$I$27,$J$27),IF($O$2="Railway",$I$29,$J$29))*P5 -> 4.5382203e+09 | T5: 0.31273669 | U5: =_xlfn.GAMMA.INV(T5,IF($O$2="Railway",$D$31,$D$32),IF($O$2="Railway",$F$31,$F$32))*Q5 -> -2.5323455e+10 | V5: =(N5+O5+S5)/-U5 -> 0.36440009 | X5: 1 | Y5: =E37 -> 0.19241814 | Z5: =(($F$37-$E$37)/MAX($X$5:$X$1004))+Y5 -> 0.19804722 | AA5: =TEXT(Y5,"0.00000") & " - " & TEXT(Z5,"0.00000") -> 0.19242 - 0.19805 | AB5: =COUNTIFS($V$5:$V$2004, ">=" & Y5, $V$5:$V$2004, "<" & Z5) -> 11
M6: 2 | N6: ='CBA Result'!$G$54*_xlfn.GAMMA.INV(T6,IF($O$2="Railway",$D$31,$D$32),IF($O$2="Railway",$F$31,$F$32)) -> 5.9839981e+09 | O6: ='CBA Result'!$G$53+'CBA Result'!$G$57+'CBA Result'!$G$58+'CBA Result'!$G$59+'CBA Result'!$G$60 -> -3.4918591e+08 | P6: ='CBA Result'!$G$55+'CBA Result'!$G$56 -> 2.5899165e+09 | Q6: ='CBA Result'!$G$40 -> -1.6530914e+10 | R6: 0.60693101 | S6: =_xlfn.BETA.INV(R6,IF($O$2="Railway",$I$30,$J$30),IF($O$2="Railway",$I$31,$J$31),IF($O$2="Railway",$I$27,$J$27),IF($O$2="Railway",$I$29,$J$29))*P6 -> 2.3811563e+09 | T6: 0.62802158 | U6: =_xlfn.GAMMA.INV(T6,IF($O$2="Railway",$D$31,$D$32),IF($O$2="Railway",$F$31,$F$32))*Q6 -> -3.0073522e+10 | V6: =(N6+O6+S6)/-U6 -> 0.26654572 | X6: 2 | Y6: =Z5 -> 0.19804722 | Z6: =(($F$37-$E$37)/MAX($X$5:$X$1004))+Y6 -> 0.20367629 | AA6: =TEXT(Y6,"0.00000") & " - " & TEXT(Z6,"0.00000") -> 0.19805 - 0.20368 | AB6: =COUNTIFS($V$5:$V$2004, ">=" & Y6, $V$5:$V$2004, "<" & Z6) -> 34
M7: 3 | N7: ='CBA Result'!$G$54*_xlfn.GAMMA.INV(T7,IF($O$2="Railway",$D$31,$D$32),IF($O$2="Railway",$F$31,$F$32)) -> 4.677269e+09 | O7: ='CBA Result'!$G$53+'CBA Result'!$G$57+'CBA Result'!$G$58+'CBA Result'!$G$59+'CBA Result'!$G$60 -> -3.4918591e+08 | P7: ='CBA Result'!$G$55+'CBA Result'!$G$56 -> 2.5899165e+09 | Q7: ='CBA Result'!$G$40 -> -1.6530914e+10 | R7: 0.71210878 | S7: =_xlfn.BETA.INV(R7,IF($O$2="Railway",$I$30,$J$30),IF($O$2="Railway",$I$31,$J$31),IF($O$2="Railway",$I$27,$J$27),IF($O$2="Railway",$I$29,$J$29))*P7 -> 2.7519873e+09 | T7: 0.20413078 | U7: =_xlfn.GAMMA.INV(T7,IF($O$2="Railway",$D$31,$D$32),IF($O$2="Railway",$F$31,$F$32))*Q7 -> -2.3506349e+10 | V7: =(N7+O7+S7)/-U7 -> 0.30119821 | X7: 3 | Y7: =Z6 -> 0.20367629 | Z7: =(($F$37-$E$37)/MAX($X$5:$X$1004))+Y7 -> 0.20930537 | AA7: =TEXT(Y7,"0.00000") & " - " & TEXT(Z7,"0.00000") -> 0.20368 - 0.20931 | AB7: =COUNTIFS($V$5:$V$2004, ">=" & Y7, $V$5:$V$2004, "<" & Z7) -> 55
M8: 4 | N8: ='CBA Result'!$G$54*_xlfn.GAMMA.INV(T8,IF($O$2="Railway",$D$31,$D$32),IF($O$2="Railway",$F$31,$F$32)) -> 1.1236031e+10 | O8: ='CBA Result'!$G$53+'CBA Result'!$G$57+'CBA Result'!$G$58+'CBA Result'!$G$59+'CBA Result'!$G$60 -> -3.4918591e+08 | P8: ='CBA Result'!$G$55+'CBA Result'!$G$56 -> 2.5899165e+09 | Q8: ='CBA Result'!$G$40 -> -1.6530914e+10 | R8: 0.34517349 | S8: =_xlfn.BETA.INV(R8,IF($O$2="Railway",$I$30,$J$30),IF($O$2="Railway",$I$31,$J$31),IF($O$2="Railway",$I$27,$J$27),IF($O$2="Railway",$I$29,$J$29))*P8 -> 1.5999247e+09 | T8: 0.99991556 | U8: =_xlfn.GAMMA.INV(T8,IF($O$2="Railway",$D$31,$D$32),IF($O$2="Railway",$F$31,$F$32))*Q8 -> -5.646844e+10 | V8: =(N8+O8+S8)/-U8 -> 0.2211283 | X8: 4 | Y8: =Z7 -> 0.20930537 | Z8: =(($F$37-$E$37)/MAX($X$5:$X$1004))+Y8 -> 0.21493445 | AA8: =TEXT(Y8,"0.00000") & " - " & TEXT(Z8,"0.00000") -> 0.20931 - 0.21493 | AB8: =COUNTIFS($V$5:$V$2004, ">=" & Y8, $V$5:$V$2004, "<" & Z8) -> 73
M9: 5 | N9: ='CBA Result'!$G$54*_xlfn.GAMMA.INV(T9,IF($O$2="Railway",$D$31,$D$32),IF($O$2="Railway",$F$31,$F$32)) -> 5.986286e+09 | O9: ='CBA Result'!$G$53+'CBA Result'!$G$57+'CBA Result'!$G$58+'CBA Result'!$G$59+'CBA Result'!$G$60 -> -3.4918591e+08 | P9: ='CBA Result'!$G$55+'CBA Result'!$G$56 -> 2.5899165e+09 | Q9: ='CBA Result'!$G$40 -> -1.6530914e+10 | R9: 0.93675493 | S9: =_xlfn.BETA.INV(R9,IF($O$2="Railway",$I$30,$J$30),IF($O$2="Railway",$I$31,$J$31),IF($O$2="Railway",$I$27,$J$27),IF($O$2="Railway",$I$29,$J$29))*P9 -> 4.0127766e+09 | T9: 0.6287264 | U9: =_xlfn.GAMMA.INV(T9,IF($O$2="Railway",$D$31,$D$32),IF($O$2="Railway",$F$31,$F$32))*Q9 -> -3.008502e+10 | V9: =(N9+O9+S9)/-U9 -> 0.32075354 | X9: 5 | Y9: =Z8 -> 0.21493445 | Z9: =(($F$37-$E$37)/MAX($X$5:$X$1004))+Y9 -> 0.22056352 | AA9: =TEXT(Y9,"0.00000") & " - " & TEXT(Z9,"0.00000") -> 0.21493 - 0.22056 | AB9: =COUNTIFS($V$5:$V$2004, ">=" & Y9, $V$5:$V$2004, "<" & Z9) -> 92
M10: 6 | N10: ='CBA Result'!$G$54*_xlfn.GAMMA.INV(T10,IF($O$2="Railway",$D$31,$D$32),IF($O$2="Railway",$F$31,$F$32)) -> 6.3162529e+09 | O10: ='CBA Result'!$G$53+'CBA Result'!$G$57+'CBA Result'!$G$58+'CBA Result'!$G$59+'CBA Result'!$G$60 -> -3.4918591e+08 | P10: ='CBA Result'!$G$55+'CBA Result'!$G$56 -> 2.5899165e+09 | Q10: ='CBA Result'!$G$40 -> -1.6530914e+10 | R10: 0.020434689 | S10: =_xlfn.BETA.INV(R10,IF($O$2="Railway",$I$30,$J$30),IF($O$2="Railway",$I$31,$J$31),IF($O$2="Railway",$I$27,$J$27),IF($O$2="Railway",$I$29,$J$29))*P10 -> 4.6383677e+08 | T10: 0.72325052 | U10: =_xlfn.GAMMA.INV(T10,IF($O$2="Railway",$D$31,$D$32),IF($O$2="Railway",$F$31,$F$32))*Q10 -> -3.174332e+10 | V10: =(N10+O10+S10)/-U10 -> 0.20259077 | X10: 6 | Y10: =Z9 -> 0.22056352 | Z10: =(($F$37-$E$37)/MAX($X$5:$X$1004))+Y10 -> 0.2261926 | AA10: =TEXT(Y10,"0.00000") & " - " & TEXT(Z10,"0.00000") -> 0.22056 - 0.22619 | AB10: =COUNTIFS($V$5:$V$2004, ">=" & Y10, $V$5:$V$2004, "<" & Z10) -> 102
M11: 7 | N11: ='CBA Result'!$G$54*_xlfn.GAMMA.INV(T11,IF($O$2="Railway",$D$31,$D$32),IF($O$2="Railway",$F$31,$F$32)) -> 5.0596971e+09 | O11: ='CBA Result'!$G$53+'CBA Result'!$G$57+'CBA Result'!$G$58+'CBA Result'!$G$59+'CBA Result'!$G$60 -> -3.4918591e+08 | P11: ='CBA Result'!$G$55+'CBA Result'!$G$56 -> 2.5899165e+09 | Q11: ='CBA Result'!$G$40 -> -1.6530914e+10 | R11: 0.8027507 | S11: =_xlfn.BETA.INV(R11,IF($O$2="Railway",$I$30,$J$30),IF($O$2="Railway",$I$31,$J$31),IF($O$2="Railway",$I$27,$J$27),IF($O$2="Railway",$I$29,$J$29))*P11 -> 3.1366869e+09 | T11: 0.31951197 | U11: =_xlfn.GAMMA.INV(T11,IF($O$2="Railway",$D$31,$D$32),IF($O$2="Railway",$F$31,$F$32))*Q11 -> -2.5428302e+10 | V11: =(N11+O11+S11)/-U11 -> 0.30860095 | X11: 7 | Y11: =Z10 -> 0.2261926 | Z11: =(($F$37-$E$37)/MAX($X$5:$X$1004))+Y11 -> 0.23182168 | AA11: =TEXT(Y11,"0.00000") & " - " & TEXT(Z11,"0.00000") -> 0.22619 - 0.23182 | AB11: =COUNTIFS($V$5:$V$2004, ">=" & Y11, $V$5:$V$2004, "<" & Z11) -> 111
M12: 8 | N12: ='CBA Result'!$G$54*_xlfn.GAMMA.INV(T12,IF($O$2="Railway",$D$31,$D$32),IF($O$2="Railway",$F$31,$F$32)) -> 4.0291328e+09 | O12: ='CBA Result'!$G$53+'CBA Result'!$G$57+'CBA Result'!$G$58+'CBA Result'!$G$59+'CBA Result'!$G$60 -> -3.4918591e+08 | P12: ='CBA Result'!$G$55+'CBA Result'!$G$56 -> 2.5899165e+09 | Q12: ='CBA Result'!$G$40 -> -1.6530914e+10 | R12: 0.1979453 | S12: =_xlfn.BETA.INV(R12,IF($O$2="Railway",$I$30,$J$30),IF($O$2="Railway",$I$31,$J$31),IF($O$2="Railway",$I$27,$J$27),IF($O$2="Railway",$I$29,$J$29))*P12 -> 1.1690737e+09 | T12: 0.069187454 | U12: =_xlfn.GAMMA.INV(T12,IF($O$2="Railway",$D$31,$D$32),IF($O$2="Railway",$F$31,$F$32))*Q12 -> -2.0249039e+10 | V12: =(N12+O12+S12)/-U12 -> 0.23946917 | X12: 8 | Y12: =Z11 -> 0.23182168 | Z12: =(($F$37-$E$37)/MAX($X$5:$X$1004))+Y12 -> 0.23745075 | AA12: =TEXT(Y12,"0.00000") & " - " & TEXT(Z12,"0.00000") -> 0.23182 - 0.23745 | AB12: =COUNTIFS($V$5:$V$2004, ">=" & Y12, $V$5:$V$2004, "<" & Z12) -> 132
M13: 9 | N13: ='CBA Result'!$G$54*_xlfn.GAMMA.INV(T13,IF($O$2="Railway",$D$31,$D$32),IF($O$2="Railway",$F$31,$F$32)) -> 6.1727255e+09 | O13: ='CBA Result'!$G$53+'CBA Result'!$G$57+'CBA Result'!$G$58+'CBA Result'!$G$59+'CBA Result'!$G$60 -> -3.4918591e+08 | P13: ='CBA Result'!$G$55+'CBA Result'!$G$56 -> 2.5899165e+09 | Q13: ='CBA Result'!$G$40 -> -1.6530914e+10 | R13: 0.044111019 | S13: =_xlfn.BETA.INV(R13,IF($O$2="Railway",$I$30,$J$30),IF($O$2="Railway",$I$31,$J$31),IF($O$2="Railway",$I$27,$J$27),IF($O$2="Railway",$I$29,$J$29))*P13 -> 6.0260629e+08 | T13: 0.68396788 | U13: =_xlfn.GAMMA.INV(T13,IF($O$2="Railway",$D$31,$D$32),IF($O$2="Railway",$F$31,$F$32))*Q13 -> -3.1022001e+10 | V13: =(N13+O13+S13)/-U13 -> 0.20714801 | X13: 9 | Y13: =Z12 -> 0.23745075 | Z13: =(($F$37-$E$37)/MAX($X$5:$X$1004))+Y13 -> 0.24307983 | AA13: =TEXT(Y13,"0.00000") & " - " & TEXT(Z13,"0.00000") -> 0.23745 - 0.24308 | AB13: =COUNTIFS($V$5:$V$2004, ">=" & Y13, $V$5:$V$2004, "<" & Z13) -> 96
M14: 10 | N14: ='CBA Result'!$G$54*_xlfn.GAMMA.INV(T14,IF($O$2="Railway",$D$31,$D$32),IF($O$2="Railway",$F$31,$F$32)) -> 4.2054084e+09 | O14: ='CBA Result'!$G$53+'CBA Result'!$G$57+'CBA Result'!$G$58+'CBA Result'!$G$59+'CBA Result'!$G$60 -> -3.4918591e+08 | P14: ='CBA Result'!$G$55+'CBA Result'!$G$56 -> 2.5899165e+09 | Q14: ='CBA Result'!$G$40 -> -1.6530914e+10 | R14: 0.3576383 | S14: =_xlfn.BETA.INV(R14,IF($O$2="Railway",$I$30,$J$30),IF($O$2="Railway",$I$31,$J$31),IF($O$2="Railway",$I$27,$J$27),IF($O$2="Railway",$I$29,$J$29))*P14 -> 1.635476e+09 | T14: 0.097310668 | U14: =_xlfn.GAMMA.INV(T14,IF($O$2="Railway",$D$31,$D$32),IF($O$2="Railway",$F$31,$F$32))*Q14 -> -2.113494e+10 | V14: =(N14+O14+S14)/-U14 -> 0.25983979 | X14: 10 | Y14: =Z13 -> 0.24307983 | Z14: =(($F$37-$E$37)/MAX($X$5:$X$1004))+Y14 -> 0.24870891 | AA14: =TEXT(Y14,"0.00000") & " - " & TEXT(Z14,"0.00000") -> 0.24308 - 0.24871 | AB14: =COUNTIFS($V$5:$V$2004, ">=" & Y14, $V$5:$V$2004, "<" & Z14) -> 100
M15: 11 | N15: ='CBA Result'!$G$54*_xlfn.GAMMA.INV(T15,IF($O$2="Railway",$D$31,$D$32),IF($O$2="Railway",$F$31,$F$32)) -> 4.8451051e+09 | O15: ='CBA Result'!$G$53+'CBA Result'!$G$57+'CBA Result'!$G$58+'CBA Result'!$G$59+'CBA Result'!$G$60 -> -3.4918591e+08 | P15: ='CBA Result'!$G$55+'CBA Result'!$G$56 -> 2.5899165e+09 | Q15: ='CBA Result'!$G$40 -> -1.6530914e+10 | R15: 0.57220822 | S15: =_xlfn.BETA.INV(R15,IF($O$2="Railway",$I$30,$J$30),IF($O$2="Railway",$I$31,$J$31),IF($O$2="Railway",$I$27,$J$27),IF($O$2="Railway",$I$29,$J$29))*P15 -> 2.2694032e+09 | T15: 0.25221255 | U15: =_xlfn.GAMMA.INV(T15,IF($O$2="Railway",$D$31,$D$32),IF($O$2="Railway",$F$31,$F$32))*Q15 -> -2.4349836e+10 | V15: =(N15+O15+S15)/-U15 -> 0.27783852 | X15: 11 | Y15: =Z14 -> 0.24870891 | Z15: =(($F$37-$E$37)/MAX($X$5:$X$1004))+Y15 -> 0.25433798 | AA15: =TEXT(Y15,"0.00000") & " - " & TEXT(Z15,"0.00000") -> 0.24871 - 0.25434 | AB15: =COUNTIFS($V$5:$V$2004, ">=" & Y15, $V$5:$V$2004, "<" & Z15) -> 98
M16: 12 | N16: ='CBA Result'!$G$54*_xlfn.GAMMA.INV(T16,IF($O$2="Railway",$D$31,$D$32),IF($O$2="Railway",$F$31,$F$32)) -> 7.0531187e+09 | O16: ='CBA Result'!$G$53+'CBA Result'!$G$57+'CBA Result'!$G$58+'CBA Result'!$G$59+'CBA Result'!$G$60 -> -3.4918591e+08 | P16: ='CBA Result'!$G$55+'CBA Result'!$G$56 -> 2.5899165e+09 | Q16: ='CBA Result'!$G$40 -> -1.6530914e+10 | R16: 0.41192877 | S16: =_xlfn.BETA.INV(R16,IF($O$2="Railway",$I$30,$J$30),IF($O$2="Railway",$I$31,$J$31),IF($O$2="Railway",$I$27,$J$27),IF($O$2="Railway",$I$29,$J$29))*P16 -> 1.7906895e+09 | T16: 0.87511989 | U16: =_xlfn.GAMMA.INV(T16,IF($O$2="Railway",$D$31,$D$32),IF($O$2="Railway",$F$31,$F$32))*Q16 -> -3.5446555e+10 | V16: =(N16+O16+S16)/-U16 -> 0.23964592 | X16: 12 | Y16: =Z15 -> 0.25433798 | Z16: =(($F$37-$E$37)/MAX($X$5:$X$1004))+Y16 -> 0.25996706 | AA16: =TEXT(Y16,"0.00000") & " - " & TEXT(Z16,"0.00000") -> 0.25434 - 0.25997 | AB16: =COUNTIFS($V$5:$V$2004, ">=" & Y16, $V$5:$V$2004, "<" & Z16) -> 124
M17: 13 | N17: ='CBA Result'!$G$54*_xlfn.GAMMA.INV(T17,IF($O$2="Railway",$D$31,$D$32),IF($O$2="Railway",$F$31,$F$32)) -> 4.3904243e+09 | O17: ='CBA Result'!$G$53+'CBA Result'!$G$57+'CBA Result'!$G$58+'CBA Result'!$G$59+'CBA Result'!$G$60 -> -3.4918591e+08 | P17: ='CBA Result'!$G$55+'CBA Result'!$G$56 -> 2.5899165e+09 | Q17: ='CBA Result'!$G$40 -> -1.6530914e+10 | R17: 0.11515555 | S17: =_xlfn.BETA.INV(R17,IF($O$2="Railway",$I$30,$J$30),IF($O$2="Railway",$I$31,$J$31),IF($O$2="Railway",$I$27,$J$27),IF($O$2="Railway",$I$29,$J$29))*P17 -> 8.9697793e+08 | T17: 0.13379408 | U17: =_xlfn.GAMMA.INV(T17,IF($O$2="Railway",$D$31,$D$32),IF($O$2="Railway",$F$31,$F$32))*Q17 -> -2.2064766e+10 | V17: =(N17+O17+S17)/-U17 -> 0.22380551 | X17: 13 | Y17: =Z16 -> 0.25996706 | Z17: =(($F$37-$E$37)/MAX($X$5:$X$1004))+Y17 -> 0.26559613 | AA17: =TEXT(Y17,"0.00000") & " - " & TEXT(Z17,"0.00000") -> 0.25997 - 0.26560 | AB17: =COUNTIFS($V$5:$V$2004, ">=" & Y17, $V$5:$V$2004, "<" & Z17) -> 79
... M25: 21 | N25: ='CBA Result'!$G$54*_xlfn.GAMMA.INV(T25,IF($O$2="Railway",$D$31,$D$32),IF($O$2="Railway",$F$31,$F$32)) -> 8.1583601e+09 | O25: ='CBA Result'!$G$53+'CBA Result'!$G$57+'CBA Result'!$G$58+'CBA Result'!$G$59+'CBA Result'!$G$60 -> -3.4918591e+08 | P25: ='CBA Result'!$G$55+'CBA Result'!$G$56 -> 2.5899165e+09 | Q25: ='CBA Result'!$G$40 -> -1.6530914e+10 | R25: 0.045470787 | S25: =_xlfn.BETA.INV(R25,IF($O$2="Railway",$I$30,$J$30),IF($O$2="Railway",$I$31,$J$31),IF($O$2="Railway",$I$27,$J$27),IF($O$2="Railway",$I$29,$J$29))*P25 -> 6.094765e+08 | T25: 0.97263434 | U25: =_xlfn.GAMMA.INV(T25,IF($O$2="Railway",$D$31,$D$32),IF($O$2="Railway",$F$31,$F$32))*Q25 -> -4.1001119e+10 | V25: =(N25+O25+S25)/-U25 -> 0.20532734 | X25: 21 | Y25: =Z24 -> 0.30499967 | Z25: =(($F$37-$E$37)/MAX($X$5:$X$1004))+Y25 -> 0.31062875 | AA25: =TEXT(Y25,"0.00000") & " - " & TEXT(Z25,"0.00000") -> 0.30500 - 0.31063 | AB25: =COUNTIFS($V$5:$V$2004, ">=" & Y25, $V$5:$V$2004, "<" & Z25) -> 52
B26: Consumer Surplus - beta-PERT | I26: Rail | J26: Road | M26: 22 | N26: ='CBA Result'!$G$54*_xlfn.GAMMA.INV(T26,IF($O$2="Railway",$D$31,$D$32),IF($O$2="Railway",$F$31,$F$32)) -> 6.2580866e+09 | O26: ='CBA Result'!$G$53+'CBA Result'!$G$57+'CBA Result'!$G$58+'CBA Result'!$G$59+'CBA Result'!$G$60 -> -3.4918591e+08 | P26: ='CBA Result'!$G$55+'CBA Result'!$G$56 -> 2.5899165e+09 | Q26: ='CBA Result'!$G$40 -> -1.6530914e+10 | R26: 0.64444024 | S26: =_xlfn.BETA.INV(R26,IF($O$2="Railway",$I$30,$J$30),IF($O$2="Railway",$I$31,$J$31),IF($O$2="Railway",$I$27,$J$27),IF($O$2="Railway",$I$29,$J$29))*P26 -> 2.5070014e+09 | T26: 0.70769182 | U26: =_xlfn.GAMMA.INV(T26,IF($O$2="Railway",$D$31,$D$32),IF($O$2="Railway",$F$31,$F$32))*Q26 -> -3.1450996e+10 | V26: =(N26+O26+S26)/-U26 -> 0.26758777 | X26: 22 | Y26: =Z25 -> 0.31062875 | Z26: =(($F$37-$E$37)/MAX($X$5:$X$1004))+Y26 -> 0.31625782 | AA26: =TEXT(Y26,"0.00000") & " - " & TEXT(Z26,"0.00000") -> 0.31063 - 0.31626 | AB26: =COUNTIFS($V$5:$V$2004, ">=" & Y26, $V$5:$V$2004, "<" & Z26) -> 39
B27: Rail | C27: -0.923 | D27: -0.37 | E27: 1.442 | H27: a | I27: =1+C27 -> 0.077 | J27: =1+C28 -> 0.215 | M27: 23 | N27: ='CBA Result'!$G$54*_xlfn.GAMMA.INV(T27,IF($O$2="Railway",$D$31,$D$32),IF($O$2="Railway",$F$31,$F$32)) -> 4.1122873e+09 | O27: ='CBA Result'!$G$53+'CBA Result'!$G$57+'CBA Result'!$G$58+'CBA Result'!$G$59+'CBA Result'!$G$60 -> -3.4918591e+08 | P27: ='CBA Result'!$G$55+'CBA Result'!$G$56 -> 2.5899165e+09 | Q27: ='CBA Result'!$G$40 -> -1.6530914e+10 | R27: 0.92117475 | S27: =_xlfn.BETA.INV(R27,IF($O$2="Railway",$I$30,$J$30),IF($O$2="Railway",$I$31,$J$31),IF($O$2="Railway",$I$27,$J$27),IF($O$2="Railway",$I$29,$J$29))*P27 -> 3.8685668e+09 | T27: 0.081658964 | U27: =_xlfn.GAMMA.INV(T27,IF($O$2="Railway",$D$31,$D$32),IF($O$2="Railway",$F$31,$F$32))*Q27 -> -2.0666945e+10 | V27: =(N27+O27+S27)/-U27 -> 0.36926929 | X27: 23 | Y27: =Z26 -> 0.31625782 | Z27: =(($F$37-$E$37)/MAX($X$5:$X$1004))+Y27 -> 0.3218869 | AA27: =TEXT(Y27,"0.00000") & " - " & TEXT(Z27,"0.00000") -> 0.31626 - 0.32189 | AB27: =COUNTIFS($V$5:$V$2004, ">=" & Y27, $V$5:$V$2004, "<" & Z27) -> 51
B28: Road | C28: -0.785 | D28: 0.096 | E28: 1.7934 | H28: b | I28: =1+D27 -> 0.63 | J28: =1+D28 -> 1.096 | M28: 24 | N28: ='CBA Result'!$G$54*_xlfn.GAMMA.INV(T28,IF($O$2="Railway",$D$31,$D$32),IF($O$2="Railway",$F$31,$F$32)) -> 4.3820543e+09 | O28: ='CBA Result'!$G$53+'CBA Result'!$G$57+'CBA Result'!$G$58+'CBA Result'!$G$59+'CBA Result'!$G$60 -> -3.4918591e+08 | P28: ='CBA Result'!$G$55+'CBA Result'!$G$56 -> 2.5899165e+09 | Q28: ='CBA Result'!$G$40 -> -1.6530914e+10 | R28: 0.60102755 | S28: =_xlfn.BETA.INV(R28,IF($O$2="Railway",$I$30,$J$30),IF($O$2="Railway",$I$31,$J$31),IF($O$2="Railway",$I$27,$J$27),IF($O$2="Railway",$I$29,$J$29))*P28 -> 2.3618622e+09 | T28: 0.13198893 | U28: =_xlfn.GAMMA.INV(T28,IF($O$2="Railway",$D$31,$D$32),IF($O$2="Railway",$F$31,$F$32))*Q28 -> -2.2022702e+10 | V28: =(N28+O28+S28)/-U28 -> 0.29036994 | X28: 24 | Y28: =Z27 -> 0.3218869 | Z28: =(($F$37-$E$37)/MAX($X$5:$X$1004))+Y28 -> 0.32751598 | AA28: =TEXT(Y28,"0.00000") & " - " & TEXT(Z28,"0.00000") -> 0.32189 - 0.32752 | AB28: =COUNTIFS($V$5:$V$2004, ">=" & Y28, $V$5:$V$2004, "<" & Z28) -> 38
H29: c | I29: =1+E27 -> 2.442 | J29: =1+E28 -> 2.7934 | M29: 25 | N29: ='CBA Result'!$G$54*_xlfn.GAMMA.INV(T29,IF($O$2="Railway",$D$31,$D$32),IF($O$2="Railway",$F$31,$F$32)) -> 5.0130379e+09 | O29: ='CBA Result'!$G$53+'CBA Result'!$G$57+'CBA Result'!$G$58+'CBA Result'!$G$59+'CBA Result'!$G$60 -> -3.4918591e+08 | P29: ='CBA Result'!$G$55+'CBA Result'!$G$56 -> 2.5899165e+09 | Q29: ='CBA Result'!$G$40 -> -1.6530914e+10 | R29: 0.52686044 | S29: =_xlfn.BETA.INV(R29,IF($O$2="Railway",$I$30,$J$30),IF($O$2="Railway",$I$31,$J$31),IF($O$2="Railway",$I$27,$J$27),IF($O$2="Railway",$I$29,$J$29))*P29 -> 2.1288726e+09 | T29: 0.30442007 | U29: =_xlfn.GAMMA.INV(T29,IF($O$2="Railway",$D$31,$D$32),IF($O$2="Railway",$F$31,$F$32))*Q29 -> -2.5193809e+10 | V29: =(N29+O29+S29)/-U29 -> 0.2696188 | X29: 25 | Y29: =Z28 -> 0.32751598 | Z29: =(($F$37-$E$37)/MAX($X$5:$X$1004))+Y29 -> 0.33314505 | AA29: =TEXT(Y29,"0.00000") & " - " & TEXT(Z29,"0.00000") -> 0.32752 - 0.33315 | AB29: =COUNTIFS($V$5:$V$2004, ">=" & Y29, $V$5:$V$2004, "<" & Z29) -> 37
B30: Construction Cost - Gamma (Erlang) | H30: Alpha | I30: =((4 * (I28-I27))/(I29-I27) )+1 -> 1.9353066 | J30: =((4 * (J28-J27))/(J29-J27) )+1 -> 2.3667391 | M30: 26 | N30: ='CBA Result'!$G$54*_xlfn.GAMMA.INV(T30,IF($O$2="Railway",$D$31,$D$32),IF($O$2="Railway",$F$31,$F$32)) -> 4.5415399e+09 | O30: ='CBA Result'!$G$53+'CBA Result'!$G$57+'CBA Result'!$G$58+'CBA Result'!$G$59+'CBA Result'!$G$60 -> -3.4918591e+08 | P30: ='CBA Result'!$G$55+'CBA Result'!$G$56 -> 2.5899165e+09 | Q30: ='CBA Result'!$G$40 -> -1.6530914e+10 | R30: 0.48415841 | S30: =_xlfn.BETA.INV(R30,IF($O$2="Railway",$I$30,$J$30),IF($O$2="Railway",$I$31,$J$31),IF($O$2="Railway",$I$27,$J$27),IF($O$2="Railway",$I$29,$J$29))*P30 -> 2.0008574e+09 | T30: 0.16884665 | U30: =_xlfn.GAMMA.INV(T30,IF($O$2="Railway",$D$31,$D$32),IF($O$2="Railway",$F$31,$F$32))*Q30 -> -2.2824221e+10 | V30: =(N30+O30+S30)/-U30 -> 0.27134382 | X30: 26 | Y30: =Z29 -> 0.33314505 | Z30: =(($F$37-$E$37)/MAX($X$5:$X$1004))+Y30 -> 0.33877413 | AA30: =TEXT(Y30,"0.00000") & " - " & TEXT(Z30,"0.00000") -> 0.33315 - 0.33877 | AB30: =COUNTIFS($V$5:$V$2004, ">=" & Y30, $V$5:$V$2004, "<" & Z30) -> 21
B31: Rail | C31: k | D31: 23 | E31: theta | F31: 0.075 | H31: Beta | I31: =((4 * (I29 - I28))/(I29-I27)) + 1 -> 4.0646934 | J31: =((4 * (J29 - J28))/(J29-J27)) + 1 -> 3.6332609 | M31: 27 | N31: ='CBA Result'!$G$54*_xlfn.GAMMA.INV(T31,IF($O$2="Railway",$D$31,$D$32),IF($O$2="Railway",$F$31,$F$32)) -> 6.0479143e+09 | O31: ='CBA Result'!$G$53+'CBA Result'!$G$57+'CBA Result'!$G$58+'CBA Result'!$G$59+'CBA Result'!$G$60 -> -3.4918591e+08 | P31: ='CBA Result'!$G$55+'CBA Result'!$G$56 -> 2.5899165e+09 | Q31: ='CBA Result'!$G$40 -> -1.6530914e+10 | R31: 0.10864386 | S31: =_xlfn.BETA.INV(R31,IF($O$2="Railway",$I$30,$J$30),IF($O$2="Railway",$I$31,$J$31),IF($O$2="Railway",$I$27,$J$27),IF($O$2="Railway",$I$29,$J$29))*P31 -> 8.734541e+08 | T31: 0.64747679 | U31: =_xlfn.GAMMA.INV(T31,IF($O$2="Railway",$D$31,$D$32),IF($O$2="Railway",$F$31,$F$32))*Q31 -> -3.0394743e+10 | V31: =(N31+O31+S31)/-U31 -> 0.21622761 | X31: 27 | Y31: =Z30 -> 0.33877413 | Z31: =(($F$37-$E$37)/MAX($X$5:$X$1004))+Y31 -> 0.34440321 | AA31: =TEXT(Y31,"0.00000") & " - " & TEXT(Z31,"0.00000") -> 0.33877 - 0.34440 | AB31: =COUNTIFS($V$5:$V$2004, ">=" & Y31, $V$5:$V$2004, "<" & Z31) -> 30
B32: Road | C32: k | D32: 8 | E32: theta | F32: 0.09 | M32: 28 | N32: ='CBA Result'!$G$54*_xlfn.GAMMA.INV(T32,IF($O$2="Railway",$D$31,$D$32),IF($O$2="Railway",$F$31,$F$32)) -> 7.6099218e+09 | O32: ='CBA Result'!$G$53+'CBA Result'!$G$57+'CBA Result'!$G$58+'CBA Result'!$G$59+'CBA Result'!$G$60 -> -3.4918591e+08 | P32: ='CBA Result'!$G$55+'CBA Result'!$G$56 -> 2.5899165e+09 | Q32: ='CBA Result'!$G$40 -> -1.6530914e+10 | R32: 0.30333684 | S32: =_xlfn.BETA.INV(R32,IF($O$2="Railway",$I$30,$J$30),IF($O$2="Railway",$I$31,$J$31),IF($O$2="Railway",$I$27,$J$27),IF($O$2="Railway",$I$29,$J$29))*P32 -> 1.4802579e+09 | T32: 0.93918746 | U32: =_xlfn.GAMMA.INV(T32,IF($O$2="Railway",$D$31,$D$32),IF($O$2="Railway",$F$31,$F$32))*Q32 -> -3.8244856e+10 | V32: =(N32+O32+S32)/-U32 -> 0.22855345 | X32: 28 | Y32: =Z31 -> 0.34440321 | Z32: =(($F$37-$E$37)/MAX($X$5:$X$1004))+Y32 -> 0.35003228 | AA32: =TEXT(Y32,"0.00000") & " - " & TEXT(Z32,"0.00000") -> 0.34440 - 0.35003 | AB32: =COUNTIFS($V$5:$V$2004, ">=" & Y32, $V$5:$V$2004, "<" & Z32) -> 25
M33: 29 | N33: ='CBA Result'!$G$54*_xlfn.GAMMA.INV(T33,IF($O$2="Railway",$D$31,$D$32),IF($O$2="Railway",$F$31,$F$32)) -> 6.8402822e+09 | O33: ='CBA Result'!$G$53+'CBA Result'!$G$57+'CBA Result'!$G$58+'CBA Result'!$G$59+'CBA Result'!$G$60 -> -3.4918591e+08 | P33: ='CBA Result'!$G$55+'CBA Result'!$G$56 -> 2.5899165e+09 | Q33: ='CBA Result'!$G$40 -> -1.6530914e+10 | R33: 0.5487683 | S33: =_xlfn.BETA.INV(R33,IF($O$2="Railway",$I$30,$J$30),IF($O$2="Railway",$I$31,$J$31),IF($O$2="Railway",$I$27,$J$27),IF($O$2="Railway",$I$29,$J$29))*P33 -> 2.1960872e+09 | T33: 0.83982684 | U33: =_xlfn.GAMMA.INV(T33,IF($O$2="Railway",$D$31,$D$32),IF($O$2="Railway",$F$31,$F$32))*Q33 -> -3.4376912e+10 | V33: =(N33+O33+S33)/-U33 -> 0.25270401 | X33: 29 | Y33: =Z32 -> 0.35003228 | Z33: =(($F$37-$E$37)/MAX($X$5:$X$1004))+Y33 -> 0.35566136 | AA33: =TEXT(Y33,"0.00000") & " - " & TEXT(Z33,"0.00000") -> 0.35003 - 0.35566 | AB33: =COUNTIFS($V$5:$V$2004, ">=" & Y33, $V$5:$V$2004, "<" & Z33) -> 14
C34: Mean | D34: Std.Dev | E34: Min | F34: Max | M34: 30 | N34: ='CBA Result'!$G$54*_xlfn.GAMMA.INV(T34,IF($O$2="Railway",$D$31,$D$32),IF($O$2="Railway",$F$31,$F$32)) -> 6.3598802e+09 | O34: ='CBA Result'!$G$53+'CBA Result'!$G$57+'CBA Result'!$G$58+'CBA Result'!$G$59+'CBA Result'!$G$60 -> -3.4918591e+08 | P34: ='CBA Result'!$G$55+'CBA Result'!$G$56 -> 2.5899165e+09 | Q34: ='CBA Result'!$G$40 -> -1.6530914e+10 | R34: 0.68455495 | S34: =_xlfn.BETA.INV(R34,IF($O$2="Railway",$I$30,$J$30),IF($O$2="Railway",$I$31,$J$31),IF($O$2="Railway",$I$27,$J$27),IF($O$2="Railway",$I$29,$J$29))*P34 -> 2.6489752e+09 | T34: 0.73458766 | U34: =_xlfn.GAMMA.INV(T34,IF($O$2="Railway",$D$31,$D$32),IF($O$2="Railway",$F$31,$F$32))*Q34 -> -3.1962576e+10 | V34: =(N34+O34+S34)/-U34 -> 0.27093152 | X34: 30 | Y34: =Z33 -> 0.35566136 | Z34: =(($F$37-$E$37)/MAX($X$5:$X$1004))+Y34 -> 0.36129044 | AA34: =TEXT(Y34,"0.00000") & " - " & TEXT(Z34,"0.00000") -> 0.35566 - 0.36129 | AB34: =COUNTIFS($V$5:$V$2004, ">=" & Y34, $V$5:$V$2004, "<" & Z34) -> 12
B35: Consumer Surplus | C35: =AVERAGE($S$5:$S$2004) -> 2.1872951e+09 | D35: =_xlfn.STDEV.P($S$5:$S$2004) -> 1.0809055e+09 | E35: =MIN($S$5:$S$2004) -> 2.0711117e+08 | F35: =MAX($S$5:$S$2004) -> 5.8253544e+09 | M35: 31 | N35: ='CBA Result'!$G$54*_xlfn.GAMMA.INV(T35,IF($O$2="Railway",$D$31,$D$32),IF($O$2="Railway",$F$31,$F$32)) -> 5.3463618e+09 | O35: ='CBA Result'!$G$53+'CBA Result'!$G$57+'CBA Result'!$G$58+'CBA Result'!$G$59+'CBA Result'!$G$60 -> -3.4918591e+08 | P35: ='CBA Result'!$G$55+'CBA Result'!$G$56 -> 2.5899165e+09 | Q35: ='CBA Result'!$G$40 -> -1.6530914e+10 | R35: 0.15208362 | S35: =_xlfn.BETA.INV(R35,IF($O$2="Railway",$I$30,$J$30),IF($O$2="Railway",$I$31,$J$31),IF($O$2="Railway",$I$27,$J$27),IF($O$2="Railway",$I$29,$J$29))*P35 -> 1.0234103e+09 | T35: 0.41583006 | U35: =_xlfn.GAMMA.INV(T35,IF($O$2="Railway",$D$31,$D$32),IF($O$2="Railway",$F$31,$F$32))*Q35 -> -2.686898e+10 | V35: =(N35+O35+S35)/-U35 -> 0.224072 | X35: 31 | Y35: =Z34 -> 0.36129044 | Z35: =(($F$37-$E$37)/MAX($X$5:$X$1004))+Y35 -> 0.36691951 | AA35: =TEXT(Y35,"0.00000") & " - " & TEXT(Z35,"0.00000") -> 0.36129 - 0.36692 | AB35: =COUNTIFS($V$5:$V$2004, ">=" & Y35, $V$5:$V$2004, "<" & Z35) -> 19
B36: Construction Cost | C36: =AVERAGE($U$5:$U$2004) -> -2.8657223e+10 | D36: =_xlfn.STDEV.P($U$5:$U$2004) -> 6.1640746e+09 | E36: =MIN($U$5:$U$2004) -> -6.1792691e+10 | F36: =MAX($U$5:$U$2004) -> -1.2682617e+10 | M36: 32 | N36: ='CBA Result'!$G$54*_xlfn.GAMMA.INV(T36,IF($O$2="Railway",$D$31,$D$32),IF($O$2="Railway",$F$31,$F$32)) -> 5.6397009e+09 | O36: ='CBA Result'!$G$53+'CBA Result'!$G$57+'CBA Result'!$G$58+'CBA Result'!$G$59+'CBA Result'!$G$60 -> -3.4918591e+08 | P36: ='CBA Result'!$G$55+'CBA Result'!$G$56 -> 2.5899165e+09 | Q36: ='CBA Result'!$G$40 -> -1.6530914e+10 | R36: 0.49122321 | S36: =_xlfn.BETA.INV(R36,IF($O$2="Railway",$I$30,$J$30),IF($O$2="Railway",$I$31,$J$31),IF($O$2="Railway",$I$27,$J$27),IF($O$2="Railway",$I$29,$J$29))*P36 -> 2.0217987e+09 | T36: 0.5161607 | U36: =_xlfn.GAMMA.INV(T36,IF($O$2="Railway",$D$31,$D$32),IF($O$2="Railway",$F$31,$F$32))*Q36 -> -2.8343202e+10 | V36: =(N36+O36+S36)/-U36 -> 0.2579918 | X36: 32 | Y36: =Z35 -> 0.36691951 | Z36: =(($F$37-$E$37)/MAX($X$5:$X$1004))+Y36 -> 0.37254859 | AA36: =TEXT(Y36,"0.00000") & " - " & TEXT(Z36,"0.00000") -> 0.36692 - 0.37255 | AB36: =COUNTIFS($V$5:$V$2004, ">=" & Y36, $V$5:$V$2004, "<" & Z36) -> 5
B37: BCR | C37: =AVERAGE($V$5:$V$2004) -> 0.26641346 | D37: =_xlfn.STDEV.P($V$5:$V$2004) -> 0.043385505 | E37: =MIN($V$5:$V$2004) -> 0.19241814 | F37: =MAX($V$5:$V$2004) -> 0.47387197 | M37: 33 | N37: ='CBA Result'!$G$54*_xlfn.GAMMA.INV(T37,IF($O$2="Railway",$D$31,$D$32),IF($O$2="Railway",$F$31,$F$32)) -> 4.7994331e+09 | O37: ='CBA Result'!$G$53+'CBA Result'!$G$57+'CBA Result'!$G$58+'CBA Result'!$G$59+'CBA Result'!$G$60 -> -3.4918591e+08 | P37: ='CBA Result'!$G$55+'CBA Result'!$G$56 -> 2.5899165e+09 | Q37: ='CBA Result'!$G$40 -> -1.6530914e+10 | R37: 0.60383518 | S37: =_xlfn.BETA.INV(R37,IF($O$2="Railway",$I$30,$J$30),IF($O$2="Railway",$I$31,$J$31),IF($O$2="Railway",$I$27,$J$27),IF($O$2="Railway",$I$29,$J$29))*P37 -> 2.3710223e+09 | T37: 0.23868201 | U37: =_xlfn.GAMMA.INV(T37,IF($O$2="Railway",$D$31,$D$32),IF($O$2="Railway",$F$31,$F$32))*Q37 -> -2.4120305e+10 | V37: =(N37+O37+S37)/-U37 -> 0.28280197 | X37: 33 | Y37: =Z36 -> 0.37254859 | Z37: =(($F$37-$E$37)/MAX($X$5:$X$1004))+Y37 -> 0.37817767 | AA37: =TEXT(Y37,"0.00000") & " - " & TEXT(Z37,"0.00000") -> 0.37255 - 0.37818 | AB37: =COUNTIFS($V$5:$V$2004, ">=" & Y37, $V$5:$V$2004, "<" & Z37) -> 5
M38: 34 | N38: ='CBA Result'!$G$54*_xlfn.GAMMA.INV(T38,IF($O$2="Railway",$D$31,$D$32),IF($O$2="Railway",$F$31,$F$32)) -> 5.0095667e+09 | O38: ='CBA Result'!$G$53+'CBA Result'!$G$57+'CBA Result'!$G$58+'CBA Result'!$G$59+'CBA Result'!$G$60 -> -3.4918591e+08 | P38: ='CBA Result'!$G$55+'CBA Result'!$G$56 -> 2.5899165e+09 | Q38: ='CBA Result'!$G$40 -> -1.6530914e+10 | R38: 0.64820525 | S38: =_xlfn.BETA.INV(R38,IF($O$2="Railway",$I$30,$J$30),IF($O$2="Railway",$I$31,$J$31),IF($O$2="Railway",$I$27,$J$27),IF($O$2="Railway",$I$29,$J$29))*P38 -> 2.5199746e+09 | T38: 0.30330636 | U38: =_xlfn.GAMMA.INV(T38,IF($O$2="Railway",$D$31,$D$32),IF($O$2="Railway",$F$31,$F$32))*Q38 -> -2.5176364e+10 | V38: =(N38+O38+S38)/-U38 -> 0.28520224 | X38: 34 | Y38: =Z37 -> 0.37817767 | Z38: =(($F$37-$E$37)/MAX($X$5:$X$1004))+Y38 -> 0.38380674 | AA38: =TEXT(Y38,"0.00000") & " - " & TEXT(Z38,"0.00000") -> 0.37818 - 0.38381 | AB38: =COUNTIFS($V$5:$V$2004, ">=" & Y38, $V$5:$V$2004, "<" & Z38) -> 7
M39: 35 | N39: ='CBA Result'!$G$54*_xlfn.GAMMA.INV(T39,IF($O$2="Railway",$D$31,$D$32),IF($O$2="Railway",$F$31,$F$32)) -> 6.9712967e+09 | O39: ='CBA Result'!$G$53+'CBA Result'!$G$57+'CBA Result'!$G$58+'CBA Result'!$G$59+'CBA Result'!$G$60 -> -3.4918591e+08 | P39: ='CBA Result'!$G$55+'CBA Result'!$G$56 -> 2.5899165e+09 | Q39: ='CBA Result'!$G$40 -> -1.6530914e+10 | R39: 0.53869042 | S39: =_xlfn.BETA.INV(R39,IF($O$2="Railway",$I$30,$J$30),IF($O$2="Railway",$I$31,$J$31),IF($O$2="Railway",$I$27,$J$27),IF($O$2="Railway",$I$29,$J$29))*P39 -> 2.1650216e+09 | T39: 0.86233649 | U39: =_xlfn.GAMMA.INV(T39,IF($O$2="Railway",$D$31,$D$32),IF($O$2="Railway",$F$31,$F$32))*Q39 -> -3.5035346e+10 | V39: =(N39+O39+S39)/-U39 -> 0.25080764 | X39: 35 | Y39: =Z38 -> 0.38380674 | Z39: =(($F$37-$E$37)/MAX($X$5:$X$1004))+Y39 -> 0.38943582 | AA39: =TEXT(Y39,"0.00000") & " - " & TEXT(Z39,"0.00000") -> 0.38381 - 0.38944 | AB39: =COUNTIFS($V$5:$V$2004, ">=" & Y39, $V$5:$V$2004, "<" & Z39) -> 5
M40: 36 | N40: ='CBA Result'!$G$54*_xlfn.GAMMA.INV(T40,IF($O$2="Railway",$D$31,$D$32),IF($O$2="Railway",$F$31,$F$32)) -> 5.9195469e+09 | O40: ='CBA Result'!$G$53+'CBA Result'!$G$57+'CBA Result'!$G$58+'CBA Result'!$G$59+'CBA Result'!$G$60 -> -3.4918591e+08 | P40: ='CBA Result'!$G$55+'CBA Result'!$G$56 -> 2.5899165e+09 | Q40: ='CBA Result'!$G$40 -> -1.6530914e+10 | R40: 0.66192447 | S40: =_xlfn.BETA.INV(R40,IF($O$2="Railway",$I$30,$J$30),IF($O$2="Railway",$I$31,$J$31),IF($O$2="Railway",$I$27,$J$27),IF($O$2="Railway",$I$29,$J$29))*P40 -> 2.5678351e+09 | T40: 0.60792327 | U40: =_xlfn.GAMMA.INV(T40,IF($O$2="Railway",$D$31,$D$32),IF($O$2="Railway",$F$31,$F$32))*Q40 -> -2.9749612e+10 | V40: =(N40+O40+S40)/-U40 -> 0.27355638 | X40: 36 | Y40: =Z39 -> 0.38943582 | Z40: =(($F$37-$E$37)/MAX($X$5:$X$1004))+Y40 -> 0.3950649 | AA40: =TEXT(Y40,"0.00000") & " - " & TEXT(Z40,"0.00000") -> 0.38944 - 0.39506 | AB40: =COUNTIFS($V$5:$V$2004, ">=" & Y40, $V$5:$V$2004, "<" & Z40) -> 5
M41: 37 | N41: ='CBA Result'!$G$54*_xlfn.GAMMA.INV(T41,IF($O$2="Railway",$D$31,$D$32),IF($O$2="Railway",$F$31,$F$32)) -> 3.8932137e+09 | O41: ='CBA Result'!$G$53+'CBA Result'!$G$57+'CBA Result'!$G$58+'CBA Result'!$G$59+'CBA Result'!$G$60 -> -3.4918591e+08 | P41: ='CBA Result'!$G$55+'CBA Result'!$G$56 -> 2.5899165e+09 | Q41: ='CBA Result'!$G$40 -> -1.6530914e+10 | R41: 0.92155923 | S41: =_xlfn.BETA.INV(R41,IF($O$2="Railway",$I$30,$J$30),IF($O$2="Railway",$I$31,$J$31),IF($O$2="Railway",$I$27,$J$27),IF($O$2="Railway",$I$29,$J$29))*P41 -> 3.8718814e+09 | T41: 0.051739373 | U41: =_xlfn.GAMMA.INV(T41,IF($O$2="Railway",$D$31,$D$32),IF($O$2="Railway",$F$31,$F$32))*Q41 -> -1.9565957e+10 | V41: =(N41+O41+S41)/-U41 -> 0.37902104 | X41: 37 | Y41: =Z40 -> 0.3950649 | Z41: =(($F$37-$E$37)/MAX($X$5:$X$1004))+Y41 -> 0.40069397 | AA41: =TEXT(Y41,"0.00000") & " - " & TEXT(Z41,"0.00000") -> 0.39506 - 0.40069 | AB41: =COUNTIFS($V$5:$V$2004, ">=" & Y41, $V$5:$V$2004, "<" & Z41) -> 2
M42: 38 | N42: ='CBA Result'!$G$54*_xlfn.GAMMA.INV(T42,IF($O$2="Railway",$D$31,$D$32),IF($O$2="Railway",$F$31,$F$32)) -> 5.7776335e+09 | O42: ='CBA Result'!$G$53+'CBA Result'!$G$57+'CBA Result'!$G$58+'CBA Result'!$G$59+'CBA Result'!$G$60 -> -3.4918591e+08 | P42: ='CBA Result'!$G$55+'CBA Result'!$G$56 -> 2.5899165e+09 | Q42: ='CBA Result'!$G$40 -> -1.6530914e+10 | R42: 0.68371017 | S42: =_xlfn.BETA.INV(R42,IF($O$2="Railway",$I$30,$J$30),IF($O$2="Railway",$I$31,$J$31),IF($O$2="Railway",$I$27,$J$27),IF($O$2="Railway",$I$29,$J$29))*P42 -> 2.6458935e+09 | T42: 0.56217883 | U42: =_xlfn.GAMMA.INV(T42,IF($O$2="Railway",$D$31,$D$32),IF($O$2="Railway",$F$31,$F$32))*Q42 -> -2.9036404e+10 | V42: =(N42+O42+S42)/-U42 -> 0.27807648 | X42: 38 | Y42: =Z41 -> 0.40069397 | Z42: =(($F$37-$E$37)/MAX($X$5:$X$1004))+Y42 -> 0.40632305 | AA42: =TEXT(Y42,"0.00000") & " - " & TEXT(Z42,"0.00000") -> 0.40069 - 0.40632 | AB42: =COUNTIFS($V$5:$V$2004, ">=" & Y42, $V$5:$V$2004, "<" & Z42) -> 4
M43: 39 | N43: ='CBA Result'!$G$54*_xlfn.GAMMA.INV(T43,IF($O$2="Railway",$D$31,$D$32),IF($O$2="Railway",$F$31,$F$32)) -> 4.9378873e+09 | O43: ='CBA Result'!$G$53+'CBA Result'!$G$57+'CBA Result'!$G$58+'CBA Result'!$G$59+'CBA Result'!$G$60 -> -3.4918591e+08 | P43: ='CBA Result'!$G$55+'CBA Result'!$G$56 -> 2.5899165e+09 | Q43: ='CBA Result'!$G$40 -> -1.6530914e+10 | R43: 0.70357555 | S43: =_xlfn.BETA.INV(R43,IF($O$2="Railway",$I$30,$J$30),IF($O$2="Railway",$I$31,$J$31),IF($O$2="Railway",$I$27,$J$27),IF($O$2="Railway",$I$29,$J$29))*P43 -> 2.7195442e+09 | T43: 0.28061525 | U43: =_xlfn.GAMMA.INV(T43,IF($O$2="Railway",$D$31,$D$32),IF($O$2="Railway",$F$31,$F$32))*Q43 -> -2.4816127e+10 | V43: =(N43+O43+S43)/-U43 -> 0.29449581 | X43: 39 | Y43: =Z42 -> 0.40632305 | Z43: =(($F$37-$E$37)/MAX($X$5:$X$1004))+Y43 -> 0.41195212 | AA43: =TEXT(Y43,"0.00000") & " - " & TEXT(Z43,"0.00000") -> 0.40632 - 0.41195 | AB43: =COUNTIFS($V$5:$V$2004, ">=" & Y43, $V$5:$V$2004, "<" & Z43) -> 0
M44: 40 | N44: ='CBA Result'!$G$54*_xlfn.GAMMA.INV(T44,IF($O$2="Railway",$D$31,$D$32),IF($O$2="Railway",$F$31,$F$32)) -> 5.9330221e+09 | O44: ='CBA Result'!$G$53+'CBA Result'!$G$57+'CBA Result'!$G$58+'CBA Result'!$G$59+'CBA Result'!$G$60 -> -3.4918591e+08 | P44: ='CBA Result'!$G$55+'CBA Result'!$G$56 -> 2.5899165e+09 | Q44: ='CBA Result'!$G$40 -> -1.6530914e+10 | R44: 0.22842841 | S44: =_xlfn.BETA.INV(R44,IF($O$2="Railway",$I$30,$J$30),IF($O$2="Railway",$I$31,$J$31),IF($O$2="Railway",$I$27,$J$27),IF($O$2="Railway",$I$29,$J$29))*P44 -> 1.261484e+09 | T44: 0.61216326 | U44: =_xlfn.GAMMA.INV(T44,IF($O$2="Railway",$D$31,$D$32),IF($O$2="Railway",$F$31,$F$32))*Q44 -> -2.9817334e+10 | V44: =(N44+O44+S44)/-U44 -> 0.22957519 | X44: 40 | Y44: =Z43 -> 0.41195212 | Z44: =(($F$37-$E$37)/MAX($X$5:$X$1004))+Y44 -> 0.4175812 | AA44: =TEXT(Y44,"0.00000") & " - " & TEXT(Z44,"0.00000") -> 0.41195 - 0.41758 | AB44: =COUNTIFS($V$5:$V$2004, ">=" & Y44, $V$5:$V$2004, "<" & Z44) -> 0
M45: 41 | N45: ='CBA Result'!$G$54*_xlfn.GAMMA.INV(T45,IF($O$2="Railway",$D$31,$D$32),IF($O$2="Railway",$F$31,$F$32)) -> 7.1013153e+09 | O45: ='CBA Result'!$G$53+'CBA Result'!$G$57+'CBA Result'!$G$58+'CBA Result'!$G$59+'CBA Result'!$G$60 -> -3.4918591e+08 | P45: ='CBA Result'!$G$55+'CBA Result'!$G$56 -> 2.5899165e+09 | Q45: ='CBA Result'!$G$40 -> -1.6530914e+10 | R45: 0.12700117 | S45: =_xlfn.BETA.INV(R45,IF($O$2="Railway",$I$30,$J$30),IF($O$2="Railway",$I$31,$J$31),IF($O$2="Railway",$I$27,$J$27),IF($O$2="Railway",$I$29,$J$29))*P45 -> 9.3871558e+08 | T45: 0.88220733 | U45: =_xlfn.GAMMA.INV(T45,IF($O$2="Railway",$D$31,$D$32),IF($O$2="Railway",$F$31,$F$32))*Q45 -> -3.5688775e+10 | V45: =(N45+O45+S45)/-U45 -> 0.21549759 | X45: 41 | Y45: =Z44 -> 0.4175812 | Z45: =(($F$37-$E$37)/MAX($X$5:$X$1004))+Y45 -> 0.42321028 | AA45: =TEXT(Y45,"0.00000") & " - " & TEXT(Z45,"0.00000") -> 0.41758 - 0.42321 | AB45: =COUNTIFS($V$5:$V$2004, ">=" & Y45, $V$5:$V$2004, "<" & Z45) -> 0
M46: 42 | N46: ='CBA Result'!$G$54*_xlfn.GAMMA.INV(T46,IF($O$2="Railway",$D$31,$D$32),IF($O$2="Railway",$F$31,$F$32)) -> 7.0300046e+09 | O46: ='CBA Result'!$G$53+'CBA Result'!$G$57+'CBA Result'!$G$58+'CBA Result'!$G$59+'CBA Result'!$G$60 -> -3.4918591e+08 | P46: ='CBA Result'!$G$55+'CBA Result'!$G$56 -> 2.5899165e+09 | Q46: ='CBA Result'!$G$40 -> -1.6530914e+10 | R46: 0.011487942 | S46: =_xlfn.BETA.INV(R46,IF($O$2="Railway",$I$30,$J$30),IF($O$2="Railway",$I$31,$J$31),IF($O$2="Railway",$I$27,$J$27),IF($O$2="Railway",$I$29,$J$29))*P46 -> 3.9339172e+08 | T46: 0.87160551 | U46: =_xlfn.GAMMA.INV(T46,IF($O$2="Railway",$D$31,$D$32),IF($O$2="Railway",$F$31,$F$32))*Q46 -> -3.5330391e+10 | V46: =(N46+O46+S46)/-U46 -> 0.20023017 | X46: 42 | Y46: =Z45 -> 0.42321028 | Z46: =(($F$37-$E$37)/MAX($X$5:$X$1004))+Y46 -> 0.42883935 | AA46: =TEXT(Y46,"0.00000") & " - " & TEXT(Z46,"0.00000") -> 0.42321 - 0.42884 | AB46: =COUNTIFS($V$5:$V$2004, ">=" & Y46, $V$5:$V$2004, "<" & Z46) -> 0
M47: 43 | N47: ='CBA Result'!$G$54*_xlfn.GAMMA.INV(T47,IF($O$2="Railway",$D$31,$D$32),IF($O$2="Railway",$F$31,$F$32)) -> 5.0434743e+09 | O47: ='CBA Result'!$G$53+'CBA Result'!$G$57+'CBA Result'!$G$58+'CBA Result'!$G$59+'CBA Result'!$G$60 -> -3.4918591e+08 | P47: ='CBA Result'!$G$55+'CBA Result'!$G$56 -> 2.5899165e+09 | Q47: ='CBA Result'!$G$40 -> -1.6530914e+10 | R47: 0.25129023 | S47: =_xlfn.BETA.INV(R47,IF($O$2="Railway",$I$30,$J$30),IF($O$2="Railway",$I$31,$J$31),IF($O$2="Railway",$I$27,$J$27),IF($O$2="Railway",$I$29,$J$29))*P47 -> 1.3292332e+09 | T47: 0.31423973 | U47: =_xlfn.GAMMA.INV(T47,IF($O$2="Railway",$D$31,$D$32),IF($O$2="Railway",$F$31,$F$32))*Q47 -> -2.5346772e+10 | V47: =(N47+O47+S47)/-U47 -> 0.23764453 | X47: 43 | Y47: =Z46 -> 0.42883935 | Z47: =(($F$37-$E$37)/MAX($X$5:$X$1004))+Y47 -> 0.43446843 | AA47: =TEXT(Y47,"0.00000") & " - " & TEXT(Z47,"0.00000") -> 0.42884 - 0.43447 | AB47: =COUNTIFS($V$5:$V$2004, ">=" & Y47, $V$5:$V$2004, "<" & Z47) -> 1
M48: 44 | N48: ='CBA Result'!$G$54*_xlfn.GAMMA.INV(T48,IF($O$2="Railway",$D$31,$D$32),IF($O$2="Railway",$F$31,$F$32)) -> 6.1719919e+09 | O48: ='CBA Result'!$G$53+'CBA Result'!$G$57+'CBA Result'!$G$58+'CBA Result'!$G$59+'CBA Result'!$G$60 -> -3.4918591e+08 | P48: ='CBA Result'!$G$55+'CBA Result'!$G$56 -> 2.5899165e+09 | Q48: ='CBA Result'!$G$40 -> -1.6530914e+10 | R48: 0.93560938 | S48: =_xlfn.BETA.INV(R48,IF($O$2="Railway",$I$30,$J$30),IF($O$2="Railway",$I$31,$J$31),IF($O$2="Railway",$I$27,$J$27),IF($O$2="Railway",$I$29,$J$29))*P48 -> 4.0013985e+09 | T48: 0.68375955 | U48: =_xlfn.GAMMA.INV(T48,IF($O$2="Railway",$D$31,$D$32),IF($O$2="Railway",$F$31,$F$32))*Q48 -> -3.1018314e+10 | V48: =(N48+O48+S48)/-U48 -> 0.31672271 | X48: 44 | Y48: =Z47 -> 0.43446843 | Z48: =(($F$37-$E$37)/MAX($X$5:$X$1004))+Y48 -> 0.44009751 | AA48: =TEXT(Y48,"0.00000") & " - " & TEXT(Z48,"0.00000") -> 0.43447 - 0.44010 | AB48: =COUNTIFS($V$5:$V$2004, ">=" & Y48, $V$5:$V$2004, "<" & Z48) -> 1
M49: 45 | N49: ='CBA Result'!$G$54*_xlfn.GAMMA.INV(T49,IF($O$2="Railway",$D$31,$D$32),IF($O$2="Railway",$F$31,$F$32)) -> 4.97683e+09 | O49: ='CBA Result'!$G$53+'CBA Result'!$G$57+'CBA Result'!$G$58+'CBA Result'!$G$59+'CBA Result'!$G$60 -> -3.4918591e+08 | P49: ='CBA Result'!$G$55+'CBA Result'!$G$56 -> 2.5899165e+09 | Q49: ='CBA Result'!$G$40 -> -1.6530914e+10 | R49: 0.45990978 | S49: =_xlfn.BETA.INV(R49,IF($O$2="Railway",$I$30,$J$30),IF($O$2="Railway",$I$31,$J$31),IF($O$2="Railway",$I$27,$J$27),IF($O$2="Railway",$I$29,$J$29))*P49 -> 1.9295808e+09 | T49: 0.29286866 | U49: =_xlfn.GAMMA.INV(T49,IF($O$2="Railway",$D$31,$D$32),IF($O$2="Railway",$F$31,$F$32))*Q49 -> -2.501184e+10 | V49: =(N49+O49+S49)/-U49 -> 0.26216483 | X49: 45 | Y49: =Z48 -> 0.44009751 | Z49: =(($F$37-$E$37)/MAX($X$5:$X$1004))+Y49 -> 0.44572658 | AA49: =TEXT(Y49,"0.00000") & " - " & TEXT(Z49,"0.00000") -> 0.44010 - 0.44573 | AB49: =COUNTIFS($V$5:$V$2004, ">=" & Y49, $V$5:$V$2004, "<" & Z49) -> 1
... M54: 50 | N54: ='CBA Result'!$G$54*_xlfn.GAMMA.INV(T54,IF($O$2="Railway",$D$31,$D$32),IF($O$2="Railway",$F$31,$F$32)) -> 4.7066627e+09 | O54: ='CBA Result'!$G$53+'CBA Result'!$G$57+'CBA Result'!$G$58+'CBA Result'!$G$59+'CBA Result'!$G$60 -> -3.4918591e+08 | P54: ='CBA Result'!$G$55+'CBA Result'!$G$56 -> 2.5899165e+09 | Q54: ='CBA Result'!$G$40 -> -1.6530914e+10 | R54: 0.71168374 | S54: =_xlfn.BETA.INV(R54,IF($O$2="Railway",$I$30,$J$30),IF($O$2="Railway",$I$31,$J$31),IF($O$2="Railway",$I$27,$J$27),IF($O$2="Railway",$I$29,$J$29))*P54 -> 2.7503591e+09 | T54: 0.21221431 | U54: =_xlfn.GAMMA.INV(T54,IF($O$2="Railway",$D$31,$D$32),IF($O$2="Railway",$F$31,$F$32))*Q54 -> -2.3654072e+10 | V54: =(N54+O54+S54)/-U54 -> 0.30049101 | X54: 50 | Y54: =Z53 -> 0.46824289 | Z54: =(($F$37-$E$37)/MAX($X$5:$X$1004))+Y54 -> 0.47387197 | AA54: =TEXT(Y54,"0.00000") & " - " & TEXT(Z54,"0.00000") -> 0.46824 - 0.47387 | AB54: =COUNTIFS($V$5:$V$2004, ">=" & Y54, $V$5:$V$2004, "<" & Z54) -> 1
M55: 51 | N55: ='CBA Result'!$G$54*_xlfn.GAMMA.INV(T55,IF($O$2="Railway",$D$31,$D$32),IF($O$2="Railway",$F$31,$F$32)) -> 6.2827621e+09 | O55: ='CBA Result'!$G$53+'CBA Result'!$G$57+'CBA Result'!$G$58+'CBA Result'!$G$59+'CBA Result'!$G$60 -> -3.4918591e+08 | P55: ='CBA Result'!$G$55+'CBA Result'!$G$56 -> 2.5899165e+09 | Q55: ='CBA Result'!$G$40 -> -1.6530914e+10 | R55: 0.31661675 | S55: =_xlfn.BETA.INV(R55,IF($O$2="Railway",$I$30,$J$30),IF($O$2="Railway",$I$31,$J$31),IF($O$2="Railway",$I$27,$J$27),IF($O$2="Railway",$I$29,$J$29))*P55 -> 1.5183393e+09 | T55: 0.71435341 | U55: =_xlfn.GAMMA.INV(T55,IF($O$2="Railway",$D$31,$D$32),IF($O$2="Railway",$F$31,$F$32))*Q55 -> -3.1575007e+10 | V55: =(N55+O55+S55)/-U55 -> 0.23600677
M56: 52 | N56: ='CBA Result'!$G$54*_xlfn.GAMMA.INV(T56,IF($O$2="Railway",$D$31,$D$32),IF($O$2="Railway",$F$31,$F$32)) -> 6.0300842e+09 | O56: ='CBA Result'!$G$53+'CBA Result'!$G$57+'CBA Result'!$G$58+'CBA Result'!$G$59+'CBA Result'!$G$60 -> -3.4918591e+08 | P56: ='CBA Result'!$G$55+'CBA Result'!$G$56 -> 2.5899165e+09 | Q56: ='CBA Result'!$G$40 -> -1.6530914e+10 | R56: 0.86140295 | S56: =_xlfn.BETA.INV(R56,IF($O$2="Railway",$I$30,$J$30),IF($O$2="Railway",$I$31,$J$31),IF($O$2="Railway",$I$27,$J$27),IF($O$2="Railway",$I$29,$J$29))*P56 -> 3.4469421e+09 | T56: 0.64209942 | U56: =_xlfn.GAMMA.INV(T56,IF($O$2="Railway",$D$31,$D$32),IF($O$2="Railway",$F$31,$F$32))*Q56 -> -3.0305135e+10 | V56: =(N56+O56+S56)/-U56 -> 0.30119782
M57: 53 | N57: ='CBA Result'!$G$54*_xlfn.GAMMA.INV(T57,IF($O$2="Railway",$D$31,$D$32),IF($O$2="Railway",$F$31,$F$32)) -> 9.1583265e+09 | O57: ='CBA Result'!$G$53+'CBA Result'!$G$57+'CBA Result'!$G$58+'CBA Result'!$G$59+'CBA Result'!$G$60 -> -3.4918591e+08 | P57: ='CBA Result'!$G$55+'CBA Result'!$G$56 -> 2.5899165e+09 | Q57: ='CBA Result'!$G$40 -> -1.6530914e+10 | R57: 0.3123104 | S57: =_xlfn.BETA.INV(R57,IF($O$2="Railway",$I$30,$J$30),IF($O$2="Railway",$I$31,$J$31),IF($O$2="Railway",$I$27,$J$27),IF($O$2="Railway",$I$29,$J$29))*P57 -> 1.5060036e+09 | T57: 0.99478792 | U57: =_xlfn.GAMMA.INV(T57,IF($O$2="Railway",$D$31,$D$32),IF($O$2="Railway",$F$31,$F$32))*Q57 -> -4.6026607e+10 | V57: =(N57+O57+S57)/-U57 -> 0.22411263
M58: 54 | N58: ='CBA Result'!$G$54*_xlfn.GAMMA.INV(T58,IF($O$2="Railway",$D$31,$D$32),IF($O$2="Railway",$F$31,$F$32)) -> 4.1453787e+09 | O58: ='CBA Result'!$G$53+'CBA Result'!$G$57+'CBA Result'!$G$58+'CBA Result'!$G$59+'CBA Result'!$G$60 -> -3.4918591e+08 | P58: ='CBA Result'!$G$55+'CBA Result'!$G$56 -> 2.5899165e+09 | Q58: ='CBA Result'!$G$40 -> -1.6530914e+10 | R58: 0.24870439 | S58: =_xlfn.BETA.INV(R58,IF($O$2="Railway",$I$30,$J$30),IF($O$2="Railway",$I$31,$J$31),IF($O$2="Railway",$I$27,$J$27),IF($O$2="Railway",$I$29,$J$29))*P58 -> 1.3216245e+09 | T58: 0.087014816 | U58: =_xlfn.GAMMA.INV(T58,IF($O$2="Railway",$D$31,$D$32),IF($O$2="Railway",$F$31,$F$32))*Q58 -> -2.0833251e+10 | V58: =(N58+O58+S58)/-U58 -> 0.2456562
M59: 55 | N59: ='CBA Result'!$G$54*_xlfn.GAMMA.INV(T59,IF($O$2="Railway",$D$31,$D$32),IF($O$2="Railway",$F$31,$F$32)) -> 4.8964183e+09 | O59: ='CBA Result'!$G$53+'CBA Result'!$G$57+'CBA Result'!$G$58+'CBA Result'!$G$59+'CBA Result'!$G$60 -> -3.4918591e+08 | P59: ='CBA Result'!$G$55+'CBA Result'!$G$56 -> 2.5899165e+09 | Q59: ='CBA Result'!$G$40 -> -1.6530914e+10 | R59: 0.14886086 | S59: =_xlfn.BETA.INV(R59,IF($O$2="Railway",$I$30,$J$30),IF($O$2="Railway",$I$31,$J$31),IF($O$2="Railway",$I$27,$J$27),IF($O$2="Railway",$I$29,$J$29))*P59 -> 1.0127686e+09 | T59: 0.26777642 | U59: =_xlfn.GAMMA.INV(T59,IF($O$2="Railway",$D$31,$D$32),IF($O$2="Railway",$F$31,$F$32))*Q59 -> -2.4607719e+10 | V59: =(N59+O59+S59)/-U59 -> 0.22594541
M60: 56 | N60: ='CBA Result'!$G$54*_xlfn.GAMMA.INV(T60,IF($O$2="Railway",$D$31,$D$32),IF($O$2="Railway",$F$31,$F$32)) -> 5.465231e+09 | O60: ='CBA Result'!$G$53+'CBA Result'!$G$57+'CBA Result'!$G$58+'CBA Result'!$G$59+'CBA Result'!$G$60 -> -3.4918591e+08 | P60: ='CBA Result'!$G$55+'CBA Result'!$G$56 -> 2.5899165e+09 | Q60: ='CBA Result'!$G$40 -> -1.6530914e+10 | R60: 0.033704856 | S60: =_xlfn.BETA.INV(R60,IF($O$2="Railway",$I$30,$J$30),IF($O$2="Railway",$I$31,$J$31),IF($O$2="Railway",$I$27,$J$27),IF($O$2="Railway",$I$29,$J$29))*P60 -> 5.4685736e+08 | T60: 0.45663284 | U60: =_xlfn.GAMMA.INV(T60,IF($O$2="Railway",$D$31,$D$32),IF($O$2="Railway",$F$31,$F$32))*Q60 -> -2.7466376e+10 | V60: =(N60+O60+S60)/-U60 -> 0.20617581
M61: 57 | N61: ='CBA Result'!$G$54*_xlfn.GAMMA.INV(T61,IF($O$2="Railway",$D$31,$D$32),IF($O$2="Railway",$F$31,$F$32)) -> 5.7688539e+09 | O61: ='CBA Result'!$G$53+'CBA Result'!$G$57+'CBA Result'!$G$58+'CBA Result'!$G$59+'CBA Result'!$G$60 -> -3.4918591e+08 | P61: ='CBA Result'!$G$55+'CBA Result'!$G$56 -> 2.5899165e+09 | Q61: ='CBA Result'!$G$40 -> -1.6530914e+10 | R61: 0.85465465 | S61: =_xlfn.BETA.INV(R61,IF($O$2="Railway",$I$30,$J$30),IF($O$2="Railway",$I$31,$J$31),IF($O$2="Railway",$I$27,$J$27),IF($O$2="Railway",$I$29,$J$29))*P61 -> 3.4074846e+09 | T61: 0.55928986 | U61: =_xlfn.GAMMA.INV(T61,IF($O$2="Railway",$D$31,$D$32),IF($O$2="Railway",$F$31,$F$32))*Q61 -> -2.8992281e+10 | V61: =(N61+O61+S61)/-U61 -> 0.30446562
M62: 58 | N62: ='CBA Result'!$G$54*_xlfn.GAMMA.INV(T62,IF($O$2="Railway",$D$31,$D$32),IF($O$2="Railway",$F$31,$F$32)) -> 5.8149158e+09 | O62: ='CBA Result'!$G$53+'CBA Result'!$G$57+'CBA Result'!$G$58+'CBA Result'!$G$59+'CBA Result'!$G$60 -> -3.4918591e+08 | P62: ='CBA Result'!$G$55+'CBA Result'!$G$56 -> 2.5899165e+09 | Q62: ='CBA Result'!$G$40 -> -1.6530914e+10 | R62: 0.92267206 | S62: =_xlfn.BETA.INV(R62,IF($O$2="Railway",$I$30,$J$30),IF($O$2="Railway",$I$31,$J$31),IF($O$2="Railway",$I$27,$J$27),IF($O$2="Railway",$I$29,$J$29))*P62 -> 3.8815372e+09 | T62: 0.57437588 | U62: =_xlfn.GAMMA.INV(T62,IF($O$2="Railway",$D$31,$D$32),IF($O$2="Railway",$F$31,$F$32))*Q62 -> -2.9223772e+10 | V62: =(N62+O62+S62)/-U62 -> 0.31985149
M63: 59 | N63: ='CBA Result'!$G$54*_xlfn.GAMMA.INV(T63,IF($O$2="Railway",$D$31,$D$32),IF($O$2="Railway",$F$31,$F$32)) -> 5.9142374e+09 | O63: ='CBA Result'!$G$53+'CBA Result'!$G$57+'CBA Result'!$G$58+'CBA Result'!$G$59+'CBA Result'!$G$60 -> -3.4918591e+08 | P63: ='CBA Result'!$G$55+'CBA Result'!$G$56 -> 2.5899165e+09 | Q63: ='CBA Result'!$G$40 -> -1.6530914e+10 | R63: 0.51154239 | S63: =_xlfn.BETA.INV(R63,IF($O$2="Railway",$I$30,$J$30),IF($O$2="Railway",$I$31,$J$31),IF($O$2="Railway",$I$27,$J$27),IF($O$2="Railway",$I$29,$J$29))*P63 -> 2.0825342e+09 | T63: 0.60624732 | U63: =_xlfn.GAMMA.INV(T63,IF($O$2="Railway",$D$31,$D$32),IF($O$2="Railway",$F$31,$F$32))*Q63 -> -2.9722929e+10 | V63: =(N63+O63+S63)/-U63 -> 0.25729584
M64: 60 | N64: ='CBA Result'!$G$54*_xlfn.GAMMA.INV(T64,IF($O$2="Railway",$D$31,$D$32),IF($O$2="Railway",$F$31,$F$32)) -> 6.752299e+09 | O64: ='CBA Result'!$G$53+'CBA Result'!$G$57+'CBA Result'!$G$58+'CBA Result'!$G$59+'CBA Result'!$G$60 -> -3.4918591e+08 | P64: ='CBA Result'!$G$55+'CBA Result'!$G$56 -> 2.5899165e+09 | Q64: ='CBA Result'!$G$40 -> -1.6530914e+10 | R64: 0.89388303 | S64: =_xlfn.BETA.INV(R64,IF($O$2="Railway",$I$30,$J$30),IF($O$2="Railway",$I$31,$J$31),IF($O$2="Railway",$I$27,$J$27),IF($O$2="Railway",$I$29,$J$29))*P64 -> 3.656595e+09 | T64: 0.82325237 | U64: =_xlfn.GAMMA.INV(T64,IF($O$2="Railway",$D$31,$D$32),IF($O$2="Railway",$F$31,$F$32))*Q64 -> -3.3934738e+10 | V64: =(N64+O64+S64)/-U64 -> 0.29644278
M65: 61 | N65: ='CBA Result'!$G$54*_xlfn.GAMMA.INV(T65,IF($O$2="Railway",$D$31,$D$32),IF($O$2="Railway",$F$31,$F$32)) -> 7.2922461e+09 | O65: ='CBA Result'!$G$53+'CBA Result'!$G$57+'CBA Result'!$G$58+'CBA Result'!$G$59+'CBA Result'!$G$60 -> -3.4918591e+08 | P65: ='CBA Result'!$G$55+'CBA Result'!$G$56 -> 2.5899165e+09 | Q65: ='CBA Result'!$G$40 -> -1.6530914e+10 | R65: 0.92108836 | S65: =_xlfn.BETA.INV(R65,IF($O$2="Railway",$I$30,$J$30),IF($O$2="Railway",$I$31,$J$31),IF($O$2="Railway",$I$27,$J$27),IF($O$2="Railway",$I$29,$J$29))*P65 -> 3.8678235e+09 | T65: 0.90722736 | U65: =_xlfn.GAMMA.INV(T65,IF($O$2="Railway",$D$31,$D$32),IF($O$2="Railway",$F$31,$F$32))*Q65 -> -3.6648327e+10 | V65: =(N65+O65+S65)/-U65 -> 0.29498983
M66: 62 | N66: ='CBA Result'!$G$54*_xlfn.GAMMA.INV(T66,IF($O$2="Railway",$D$31,$D$32),IF($O$2="Railway",$F$31,$F$32)) -> 5.4561399e+09 | O66: ='CBA Result'!$G$53+'CBA Result'!$G$57+'CBA Result'!$G$58+'CBA Result'!$G$59+'CBA Result'!$G$60 -> -3.4918591e+08 | P66: ='CBA Result'!$G$55+'CBA Result'!$G$56 -> 2.5899165e+09 | Q66: ='CBA Result'!$G$40 -> -1.6530914e+10 | R66: 0.34135479 | S66: =_xlfn.BETA.INV(R66,IF($O$2="Railway",$I$30,$J$30),IF($O$2="Railway",$I$31,$J$31),IF($O$2="Railway",$I$27,$J$27),IF($O$2="Railway",$I$29,$J$29))*P66 -> 1.5890297e+09 | T66: 0.45351161 | U66: =_xlfn.GAMMA.INV(T66,IF($O$2="Railway",$D$31,$D$32),IF($O$2="Railway",$F$31,$F$32))*Q66 -> -2.7420687e+10 | V66: =(N66+O66+S66)/-U66 -> 0.2441946
... M2004: 2000 | N2004: ='CBA Result'!$G$54*_xlfn.GAMMA.INV(T2004,IF($O$2="Railway",$D$31,$D$32),IF($O$2="Railway",$F$31,$F$32)) -> 6.0201884e+09 | O2004: ='CBA Result'!$G$53+'CBA Result'!$G$57+'CBA Result'!$G$58+'CBA Result'!$G$59+'CBA Result'!$G$60 -> -3.4918591e+08 | P2004: ='CBA Result'!$G$55+'CBA Result'!$G$56 -> 2.5899165e+09 | Q2004: ='CBA Result'!$G$40 -> -1.6530914e+10 | R2004: 0.81838964 | S2004: =_xlfn.BETA.INV(R2004,IF($O$2="Railway",$I$30,$J$30),IF($O$2="Railway",$I$31,$J$31),IF($O$2="Railway",$I$27,$J$27),IF($O$2="Railway",$I$29,$J$29))*P2004 -> 3.2130822e+09 | T2004: 0.63909807 | U2004: =_xlfn.GAMMA.INV(T2004,IF($O$2="Railway",$D$31,$D$32),IF($O$2="Railway",$F$31,$F$32))*Q2004 -> -3.0255402e+10 | V2004: =(N2004+O2004+S2004)/-U2004 -> 0.29363632

Sheet Risk Analysis - S10
N2: S10 - Monte Carlo Result | O2: Railway
R3: Consumer Surplus | T3: Construction
M4: Iteration | N4: New Scrap Value | O4: Benefit (before CS + Scrap Value) | P4: Consumer Surplus | Q4: Construction | R4: Random | S4: Beta-PERT | T4: Random | U4: Gamma-Erlang | V4: BCR | X4: No.bins | Y4: Min | Z4: Max | AA4: Range | AB4: Count
M5: 1 | N5: =(_xlfn.GAMMA.INV(T5,IF($O$2="Railway",$D$31,$D$32),IF($O$2="Railway",$F$31,$F$32))*'CBA Result'!$G$89) -> 3.5523785e+09 | O5: ='CBA Result'!$G$88+'CBA Result'!$G$92+'CBA Result'!$G$93+'CBA Result'!$G$94+'CBA Result'!$G$95 -> -1.375964e+09 | P5: ='CBA Result'!$G$90+'CBA Result'!$G$91 -> 1.6477754e+10 | Q5: ='CBA Result'!$G$74 -> -1.1300047e+10 | R5: 0.97578078 | S5: =_xlfn.BETA.INV(R5,IF($O$2="Railway",$I$30,$J$30),IF($O$2="Railway",$I$31,$J$31),IF($O$2="Railway",$I$27,$J$27),IF($O$2="Railway",$I$29,$J$29))*P5 -> 2.8873393e+10 | T5: 0.31273669 | U5: =_xlfn.GAMMA.INV(T5,IF($O$2="Railway",$D$31,$D$32),IF($O$2="Railway",$F$31,$F$32))*Q5 -> -1.731037e+10 | V5: =(N5+O5+S5)/-U5 -> 1.7937114 | X5: 1 | Y5: =E37 -> 0.2012806 | Z5: =(($F$37-$E$37)/MAX($X$5:$X$1004))+Y5 -> 0.25414553 | AA5: =TEXT(Y5,"0.00000") & " - " & TEXT(Z5,"0.00000") -> 0.20128 - 0.25415 | AB5: =COUNTIFS($V$5:$V$2004, ">=" & Y5, $V$5:$V$2004, "<" & Z5) -> 20
